Workbook

Sheet RiskSim
A1: SLoYkPQu0APGq0MGAJtL/Znx8FCpo3cRlNPQCK/SFyLT/B4QTyMLOyBSaZwWhemND+QaxRaqbaokYwzkNEKoudMcp2llkonQIJ8RUhZJLOcPf2KwlDB5vgyLtFsNjh9EnCdjI3bdFnNru3MQvVP68pLjTs1Ebhh5aWEnoJXwgMOw5JbeZDEVdhYD46hUVw72MNXCm4OHn5F85WBxq7aWoVTR3uUf/csJNmMkO10Fc7G3LlnDwAeqVMzKP/4=
A2: MUgCgJOnYkm5j+UrD+6NuUtSY8JqaaZCNxQm//q0448CszIn2JibQlF4dfSSco0H1d8DVP0oQ1mtT/xHmDFPl3aLT7Uf00naMT+cv0rVWleqBtYO0lvw4Afibu2AMayXDs4Nf8dJ+b93GcWozDBteM2eWwNxDDeqUeHZLe4krvrI5ripOAtI5VvmmNRQDv09khYLxAZSySAwvOhPWNA4E638O6GQyv73lyaGpMakhLvF2mRzSF5wdaP3tRI=
A3: EUb9smIcD0l6CgXZ85Ws5wRU0XvX0tWcjBERchcCp+zckLJ8auqT02LoDER0DF+wg05rAwd5SwbqWGmtx9jmwDqrG0Xgev9dXBkGm1QCPZDeajcFFUGvnW/iHWTQnsdNpwUnJb+0hA9eky6j4aBVHYBksLLtWhIJ3bq6Fq/ny6Kx6pqrdd0vkdDXid9yTVXWt2PvKAahir8lpTSvxaC2kNVVIrdxfRDpQTl8XHseGkN2ozqWwkluA/1+TX0=
A4: qnGmY/mPshfzgZADqDZJf6rfR+COz3RyinSq9DtsO+0LvEilqhUaScz5kh+mYUS+ClFPsbHYkJpkC0IuRLsdIl+J6+au2tOh52lYqyBh6LnTVcePA0O4OY8YT7LioQIhLwOw53QG3VkzQMIWopHDNpFOuJXVX4UlSlCSgJnMe1y29JyBrBy0JWceHPtrMWg7ZF2CPD7IsGcEFyrAGsg/6IDhJWT3D74RSGZvUZZq/ca4H1lCTK+CamV0NKo=
A5: R4TFBXfN5cSMNW7Y21a7oQd/KX63cRQ626HnFW2GNhSUMk/Yl1+lwJSY2KbdLvvhwNetXiVagCAf4rY3MDtnYTMrvAzdV2Ap2Ltayoaq9B1giKO67cML301OoPOvdK119txgUgUDxgwEfbbi7s7iboHqT0gpA7RJZInx3elo8fojMNbXzslmdSqcolqYGq6JcijS01tu+k9zfE38rbA8FO3VFgElrXvwxse0yHhr8yyO1nIlgizwC9UYgaI=
A6: 9uIl0/E8YWjnSvrHASd9KNY2xvqnfj/yJ8jU+MG3EJqhM5URhE//7CKCtazG53a7YcILEm6uynI+ZjMf7P1bJ2jrZZMqyeSi/kGRtA64SWF4zkTd0BuH9SR5pvxaJdAfPk9liBf9jYHZp8wfS8MdHTMetO7nVJllQfGb82GjLgNp0aIy3Zrs9NlKHr3toXy1WBrHXOnkbZj8+2sK2NuzVllCTyDKEztGXkBduFL2mgo6hQUyafSmtdElP64=
A7: cgtYu5kbhRtmoV1uFoieM6HogBT4qbHGLJPtdEqObM0WnG6jfT0rPfit5ALuuE75YMEfqf87hFOEmAUc83t3h+nhulyK56PoR5B80mflaRs+4A1G5EsFbkYCZzRGfeBHQVxkqCV4u8vaKB4+JFUDuUw5k/aIQXkRk1O31FVePTEbyDbhsatLMssnl7fHfcBPGFurErPB5xOeBFtdZHR4sJ72xMrIHMrVYZPmLR7uplMCM29m6tb1uTicDWg=
A8: xxUhCQwsanceMKUOHH2lxhzMbmm9O92au5nq7dG53LdFu6GJwcUB/evYNDcho51kgCm+/iXOOCjWNDQkRQFw5q0fO+IlHoLQSMeuvkpCKCJr2J4kZXTrcEZa0J1QnjSKQlo6Lw7oEV7M01CTowOhGSBCN+1D5ThBZ2C9LNsDdsFydzNJXd/B1pfeibhFiC3r0N2KY/wQHkfoCooHrgDn26iE6Pq0LWPu/KKzug9+h9RX2J2dbbvEQwrw0Yg=
A9: tEcuD5XgkJM65E54Z4qO5fu4eDwVgjKJkEc74sFJ8bCiigOSclQmfeZabcR4WzT2BsMxyp0eiCYpY/MSBmrQPth0r1jZg733HMcCfBKJ3rVEbsQ/09C4ulIVy2RUSwhnwqN0dvZzdSoW59/C/vouTQ+G2zmYLAQ+N3TQvRla+/21hTV0NR9hZ0R1LP+8LLBJ0icZj4E9+y3cRsUoVTNxAIj6SGcwSnZCCwdr0XVgr5G6803gy8/c0tvQuig=
A10: tX9FxSmBPtk9D1ojkc5jV4FOvifS5iGJxJYXjtHiZCizxIKIYnI2mHuhHswIJxH6zeZiYdXqR5OaKNloYsO/0ir/CqEKO5gXh4n5MnSh1SXs47seH10augB1fWGIJG/o+I2LbznZVhQIKS0UKJtT88JbI+tgLoE+kSBbn5NGNDNxOov6E0DpD+blvTCCKP7NKuPg0HCafv9g7DfaWN/0fWOceXzc+YrbPFM2PjGcgUt6v2ydEl3K3uDb/PQ=
A11: wPcDONaGs5lSsKMCpMd5lTb1korMzc7QxMSP/KVtXDqhWXQvkbfKKPIoeOwJ0LxlG7MwpY1rF8wTpC+zR7XygZezhdI/3DH9/BHWZZag2/lZ0XJNhqDlkbU8xP3+7Du0dhKiyySgxeXbQ0QXWd5H0oZY3FaV0t7y2XGBrBHpFtVefcEsOg2f2bdKdvyUA7ftEhGRuHnGe1sNePM/LPZKdBR/Ji7dWcCMOVcgNj5DXbFsLQCAC1bl4Dbh2Zc=
A12: yjx6G3kpMZt1LEJiE1IPSOQup7MJDHg2xiN5VS2dydPSuhC9iBkqotlP18Yt8UvNdLKzR9UeJW+jstz4Nq2qsuAojOQ6/7rLiQUvjDsiKVHlekkDXfbEUsCNvIFxzuM825PXJlcLeNXKogZZBJ6eF5dtr+hKwuKsQbMyrsSBcJ3KdFhQdDhAnmBCZP3IENV+bWZ6V2oDJ5189uO4pUT8WAXF3EqMWxuyGZn00g0T+uvSe9AOYlSKSH3E05I=
... A1017: 76oMsGlG+ess+04GIMWAxegYb6Hq51IWfqsn9xjXUTlNUurHimCal6+5GrIvZCsVppP2/wdLgC1eVjF/RI4ycBxnJ3IFUl/8E52gSQ1Hnv138jH2G5hqh6aGMEdWKZYWdCSuLBSwgAAybkrkZzn6URRuAe7HDJUH

Sheet BD Original
A1: Fecha | B1: Apple | C1: Coca-Cola | D1: JPMorgan | E1: AT&T
A2: 45154 | B2: 175.67108 | C2: 58.602821 | D2: 146.50507 | E2: 13.196151
A3: 45155 | B3: 173.11415 | C3: 58.72879 | D3: 144.98335 | E3: 13.111919 | G3: Fuente: https://finance.yahoo.com/
A4: 45156 | B4: 173.60165 | C4: 59.058239 | D4: 145.315 | E4: 13.149357
A5: 45159 | B5: 174.94478 | C5: 58.554379 | D5: 145.8125 | E5: 13.196151
A6: 45160 | B6: 176.3277 | C6: 58.195862 | D6: 142.78856 | E6: 13.345895
A7: 45161 | B7: 180.19791 | C7: 58.399345 | D7: 143.75426 | E7: 13.252305
A8: 45162 | B8: 175.48202 | C8: 58.244312 | D8: 143.61769 | E8: 13.242945
A9: 45163 | B9: 177.7007 | C9: 58.515617 | D9: 143.44211 | E9: 13.205509
A10: 45166 | B10: 179.27266 | C10: 58.68034 | D10: 143.93961 | E10: 13.299099
A11: 45167 | B11: 183.18263 | C11: 58.622204 | D11: 145.11015 | E11: 13.823201
A12: 45168 | B12: 186.69466 | C12: 58.593136 | D12: 144.52487 | E12: 13.785766
A13: 45169 | B13: 186.91354 | C13: 57.973003 | D13: 142.73978 | E13: 13.841919
A14: 45170 | B14: 188.49547 | C14: 57.469139 | D14: 143.21776 | E14: 13.710893
A15: 45174 | B15: 188.73424 | C15: 56.994347 | D15: 141.63748 | E15: 13.551791
... A254: 45520 | B254: 226.05 | C254: 69.18 | D254: 213.97 | E254: 19.34

Sheet Precios
A1: Fecha | B1: Apple | C1: Coca-Cola | D1: JPMorgan | E1: AT&T
A2: 45154 | B2: 175.67108 | C2: 58.602821 | D2: 146.50507 | E2: 13.196151 | J2: 1. Ver cómo descargar datos desde Yahoo Finance
A3: 45155 | B3: 173.11415 | C3: 58.72879 | D3: 144.98335 | E3: 13.111919 | J3: 2. Análisis de Acciones
A4: 45156 | B4: 173.60165 | C4: 59.058239 | D4: 145.315 | E4: 13.149357 | J4: 3. Cálculo de Retorno
A5: 45159 | B5: 174.94478 | C5: 58.554379 | D5: 145.8125 | E5: 13.196151 | J5: 4. Análisis de Retornos
A6: 45160 | B6: 176.3277 | C6: 58.195862 | D6: 142.78856 | E6: 13.345895
A7: 45161 | B7: 180.19791 | C7: 58.399345 | D7: 143.75426 | E7: 13.252305 | O7: 1. Por qué son constantes CC y AT
A8: 45162 | B8: 175.48202 | C8: 58.244312 | D8: 143.61769 | E8: 13.242945 | O8: 2. Por qué JPMorgan no tiene cambios tan cambios abructos como Apple
A9: 45163 | B9: 177.7007 | C9: 58.515617 | D9: 143.44211 | E9: 13.205509
A10: 45166 | B10: 179.27266 | C10: 58.68034 | D10: 143.93961 | E10: 13.299099
A11: 45167 | B11: 183.18263 | C11: 58.622204 | D11: 145.11015 | E11: 13.823201
A12: 45168 | B12: 186.69466 | C12: 58.593136 | D12: 144.52487 | E12: 13.785766
A13: 45169 | B13: 186.91354 | C13: 57.973003 | D13: 142.73978 | E13: 13.841919
A14: 45170 | B14: 188.49547 | C14: 57.469139 | D14: 143.21776 | E14: 13.710893
A15: 45174 | B15: 188.73424 | C15: 56.994347 | D15: 141.63748 | E15: 13.551791
A16: 45175 | B16: 181.97881 | C16: 56.955589 | D16: 141.40341 | E16: 13.673458
A17: 45176 | B17: 176.65604 | C17: 56.519558 | D17: 140.1938 | E17: 13.673458
A18: 45177 | B18: 177.27286 | C18: 56.519558 | D18: 140.30112 | E18: 13.47692
A19: 45180 | B19: 178.44685 | C19: 57.052486 | D19: 140.91566 | E19: 13.589228
A20: 45181 | B20: 175.40245 | C20: 56.490486 | D20: 142.74954 | E20: 13.533073
... A254: 45520 | B254: 226.05 | C254: 69.18 | D254: 213.97 | E254: 19.34

Sheet Retorno
A1: Fecha | B1: Apple | C1: Coca-Cola | D1: JPMorgan | E1: AT&T | F1: Retornos Continuos | J1: Retornos Discretos | N1: t+1
A2: 45154 | B2: 175.67108 | C2: 58.602821 | D2: 146.50507 | E2: 13.196151 | F2: Apple | G2: Coca-Cola | H2: JPMorgan | I2: AT&T | J2: Apple | K2: Coca-Cola | L2: JPMorgan | M2: AT&T | N2: Apple t+1 | O2: Coca-Cola t+1 | P2: JPMorgan t+1 | Q2: AT&T t+1
A3: 45155 | B3: 173.11415 | C3: 58.72879 | D3: 144.98335 | E3: 13.111919 | F3: =LN(B3/B2) -> -0.014662185 | G3: =LN(C3/C2) -> 0.0021472312 | H3: =LN(D3/D2) -> -0.010441079 | I3: =LN(E3/E2) -> -0.0064035323 | J3: =(B3-B2)/B3 -> -0.014770202 | K3: =(C3-C2)/C3 -> 0.0021449276 | L3: =(D3-D2)/D3 -> -0.010495777 | M3: =(E3-E2)/E3 -> -0.0064240787 | N3: =F4 -> 0.0028121206 | O3: =G4 -> 0.0055939922 | P3: =H4 -> 0.0022848848 | Q3: =I4 -> 0.0028511962
A4: 45156 | B4: 173.60165 | C4: 59.058239 | D4: 145.315 | E4: 13.149357 | F4: =LN(B4/B3) -> 0.0028121206 | G4: =LN(C4/C3) -> 0.0055939922 | H4: =LN(D4/D3) -> 0.0022848848 | I4: =LN(E4/E3) -> 0.0028511962 | J4: =(B4-B3)/B4 -> 0.0028081702 | K4: =(C4-C3)/C4 -> 0.0055783749 | L4: =(D4-D3)/D4 -> 0.0022822764 | M4: =(E4-E3)/E4 -> 0.0028471354 | N4: =F5 -> 0.00770704 | O4: =G5 -> -0.0085681807 | P4: =H5 -> 0.0034177361 | Q4: =I5 -> 0.0035523361
A5: 45159 | B5: 174.94478 | C5: 58.554379 | D5: 145.8125 | E5: 13.196151 | F5: =LN(B5/B4) -> 0.00770704 | G5: =LN(C5/C4) -> -0.0085681807 | H5: =LN(D5/D4) -> 0.0034177361 | I5: =LN(E5/E4) -> 0.0035523361 | J5: =(B5-B4)/B5 -> 0.0076774169 | K5: =(C5-C4)/C5 -> -0.0086049926 | L5: =(D5-D4)/D5 -> 0.0034119023 | M5: =(E5-E4)/E5 -> 0.003546034 | N5: =F6 -> 0.0078738144 | O5: =G6 -> -0.0061416255 | P5: =H6 -> -0.020956622 | Q5: =I6 -> 0.011283651
A6: 45160 | B6: 176.3277 | C6: 58.195862 | D6: 142.78856 | E6: 13.345895 | F6: =LN(B6/B5) -> 0.0078738144 | G6: =LN(C6/C5) -> -0.0061416255 | H6: =LN(D6/D5) -> -0.020956622 | I6: =LN(E6/E5) -> 0.011283651 | J6: =(B6-B5)/B6 -> 0.0078428971 | K6: =(C6-C5)/C6 -> -0.0061605239 | L6: =(D6-D5)/D6 -> -0.021177754 | M6: =(E6-E5)/E6 -> 0.011220229 | N6: =F7 -> 0.02171154 | O6: =G7 -> 0.0034904215 | P6: =H7 -> 0.0067403655 | Q6: =I7 -> -0.0070373474
A7: 45161 | B7: 180.19791 | C7: 58.399345 | D7: 143.75426 | E7: 13.252305 | F7: =LN(B7/B6) -> 0.02171154 | G7: =LN(C7/C6) -> 0.0034904215 | H7: =LN(D7/D6) -> 0.0067403655 | I7: =LN(E7/E6) -> -0.0070373474 | J7: =(B7-B6)/B7 -> 0.021477541 | K7: =(C7-C6)/C7 -> 0.003484337 | L7: =(D7-D6)/D7 -> 0.0067177002 | M7: =(E7-E6)/E7 -> -0.0070621677 | N7: =F8 -> -0.026519109 | O7: =G8 -> -0.0026582344 | P7: =H8 -> -0.00095044775 | Q7: =I8 -> -0.00070654177
A8: 45162 | B8: 175.48202 | C8: 58.244312 | D8: 143.61769 | E8: 13.242945 | F8: =LN(B8/B7) -> -0.026519109 | G8: =LN(C8/C7) -> -0.0026582344 | H8: =LN(D8/D7) -> -0.00095044775 | I8: =LN(E8/E7) -> -0.00070654177 | J8: =(B8-B7)/B8 -> -0.026873869 | K8: =(C8-C7)/C8 -> -0.0026617706 | L8: =(D8-D7)/D8 -> -0.00095089957 | M8: =(E8-E7)/E8 -> -0.00070679143 | N8: =F9 -> 0.012564053 | O8: =G9 -> 0.0046472363 | P8: =H9 -> -0.0012233202 | Q8: =I9 -> -0.0028308668
A9: 45163 | B9: 177.7007 | C9: 58.515617 | D9: 143.44211 | E9: 13.205509 | F9: =LN(B9/B8) -> 0.012564053 | G9: =LN(C9/C8) -> 0.0046472363 | H9: =LN(D9/D8) -> -0.0012233202 | I9: =LN(E9/E8) -> -0.0028308668 | J9: =(B9-B8)/B9 -> 0.012485455 | K9: =(C9-C8)/C9 -> 0.0046364546 | L9: =(D9-D8)/D9 -> -0.0012240687 | M9: =(E9-E8)/E9 -> -0.0028348775 | N9: =F10 -> 0.0088072128 | O9: =G10 -> 0.0028110715 | P9: =H10 -> 0.0034622836 | Q9: =I10 -> 0.0070621976
A10: 45166 | B10: 179.27266 | C10: 58.68034 | D10: 143.93961 | E10: 13.299099 | F10: =LN(B10/B9) -> 0.0088072128 | G10: =LN(C10/C9) -> 0.0028110715 | H10: =LN(D10/D9) -> 0.0034622836 | I10: =LN(E10/E9) -> 0.0070621976 | J10: =(B10-B9)/B10 -> 0.0087685429 | K10: =(C10-C9)/C10 -> 0.0028071242 | L10: =(D10-D9)/D10 -> 0.0034562968 | M10: =(E10-E9)/E10 -> 0.0070373188 | N10: =F11 -> 0.021575763 | O10: =G11 -> -0.00099121473 | P10: =H11 -> 0.0080993211 | Q10: =I11 -> 0.038652124
A11: 45167 | B11: 183.18263 | C11: 58.622204 | D11: 145.11015 | E11: 13.823201 | F11: =LN(B11/B10) -> 0.021575763 | G11: =LN(C11/C10) -> -0.00099121473 | H11: =LN(D11/D10) -> 0.0080993211 | I11: =LN(E11/E10) -> 0.038652124 | J11: =(B11-B10)/B11 -> 0.021344671 | K11: =(C11-C10)/C11 -> -0.00099170615 | L11: =(D11-D10)/D11 -> 0.0080666099 | M11: =(E11-E10)/E11 -> 0.037914662 | N11: =F12 -> 0.018990782 | O11: =G12 -> -0.00049597605 | P11: =H12 -> -0.0040415126 | Q11: =I12 -> -0.0027118018
A12: 45168 | B12: 186.69466 | C12: 58.593136 | D12: 144.52487 | E12: 13.785766 | F12: =LN(B12/B11) -> 0.018990782 | G12: =LN(C12/C11) -> -0.00049597605 | H12: =LN(D12/D11) -> -0.0040415126 | I12: =LN(E12/E11) -> -0.0027118018 | J12: =(B12-B11)/B12 -> 0.018811594 | K12: =(C12-C11)/C12 -> -0.00049609907 | L12: =(D12-D11)/D12 -> -0.0040496905 | M12: =(E12-E11)/E12 -> -0.002715482 | N12: =F13 -> 0.0011717517 | O12: =G13 -> -0.01064012 | P12: =H13 -> -0.012428386 | Q12: =I13 -> 0.0040649861
A13: 45169 | B13: 186.91354 | C13: 57.973003 | D13: 142.73978 | E13: 13.841919 | F13: =LN(B13/B12) -> 0.0011717517 | G13: =LN(C13/C12) -> -0.01064012 | H13: =LN(D13/D12) -> -0.012428386 | I13: =LN(E13/E12) -> 0.0040649861 | J13: =(B13-B12)/B13 -> 0.0011710655 | K13: =(C13-C12)/C13 -> -0.010696927 | L13: =(D13-D12)/D13 -> -0.012505939 | M13: =(E13-E12)/E13 -> 0.0040567352 | N13: =F14 -> 0.0084277858 | O13: =G14 -> -0.008729346 | P13: =H14 -> 0.003343024 | Q13: =I14 -> -0.0095109703
A14: 45170 | B14: 188.49547 | C14: 57.469139 | D14: 143.21776 | E14: 13.710893 | F14: =LN(B14/B13) -> 0.0084277858 | G14: =LN(C14/C13) -> -0.008729346 | H14: =LN(D14/D13) -> 0.003343024 | I14: =LN(E14/E13) -> -0.0095109703 | J14: =(B14-B13)/B14 -> 0.0083923715 | K14: =(C14-C13)/C14 -> -0.0087675578 | L14: =(D14-D13)/D14 -> 0.0033374423 | M14: =(E14-E13)/E14 -> -0.0095563433 | N14: =F15 -> 0.0012659132 | O14: =G15 -> -0.0082960032 | P14: =H15 -> -0.011095406 | Q14: =I15 -> -0.011671911
... A23: 45184 | B23: 174.119 | C23: 56.587074 | D23: 145.15892 | E23: 14.253714 | F23: =LN(B23/B22) -> -0.0041626265 | G23: =LN(C23/C22) -> -0.0089348416 | H23: =LN(D23/D22) -> -0.0029524998 | I23: =LN(E23/E22) -> 0.011224979 | J23: =(B23-B22)/B23 -> -0.0041713023 | K23: =(C23-C22)/C23 -> -0.0089748765 | L23: =(D23-D22)/D23 -> -0.0029568627 | M23: =(E23-E22)/E23 -> 0.011162214 | N23: =F24 -> 0.016771886 | O23: =G24 -> 0.0061940864 | P23: =H24 -> 0.0020810602 | Q23: =I24 -> -0.0092349221
A24: 45187 | B24: 177.06393 | C24: 56.938667 | D24: 145.46132 | E24: 14.122688 | F24: =LN(B24/B23) -> 0.016771886 | G24: =LN(C24/C23) -> 0.0061940864 | H24: =LN(D24/D23) -> 0.0020810602 | I24: =LN(E24/E23) -> -0.0092349221 | J24: =(B24-B23)/B24 -> 0.016632021 | K24: =(C24-C23)/C24 -> 0.0061749426 | L24: =(D24-D23)/D24 -> 0.0020788963 | M24: =(E24-E23)/E24 -> -0.0092776956 | N24: =F25 -> 0.006161829 | O24: =G25 -> -0.0020603885 | P24: =H25 -> -0.0012750275 | Q24: =I25 -> 0.0079209278 | T24: Apple | U24: Coca-Cola | V24: JPMorgan | W24: AT&T | Z24: Apple | AA24: Coca-Cola | AB24: JPMorgan | AC24: AT&T
A25: 45188 | B25: 178.15834 | C25: 56.821472 | D25: 145.27597 | E25: 14.234997 | F25: =LN(B25/B24) -> 0.006161829 | G25: =LN(C25/C24) -> -0.0020603885 | H25: =LN(D25/D24) -> -0.0012750275 | I25: =LN(E25/E24) -> 0.0079209278 | J25: =(B25-B24)/B25 -> 0.0061428839 | K25: =(C25-C24)/C25 -> -0.0020625126 | L25: =(D25-D24)/D25 -> -0.0012758407 | M25: =(E25-E24)/E25 -> 0.0078896399 | N25: =F26 -> -0.02019469 | O25: =G26 -> 0.0044589358 | P25: =H26 -> -0.0042389693 | Q25: =I26 -> 0.022107528 | S25: Media | T25: 0.0010005668 | U25: 0.00065844829 | V25: 0.0015030786 | W25: 0.0015168662 | Y25: Apple | Z25: 1
A26: 45189 | B26: 174.59657 | C26: 57.075401 | D26: 144.66145 | E26: 14.553202 | F26: =LN(B26/B25) -> -0.02019469 | G26: =LN(C26/C25) -> 0.0044589358 | H26: =LN(D26/D25) -> -0.0042389693 | I26: =LN(E26/E25) -> 0.022107528 | J26: =(B26-B25)/B26 -> -0.020399982 | K26: =(C26-C25)/C26 -> 0.0044490095 | L26: =(D26-D25)/D26 -> -0.0042479665 | M26: =(E26-E25)/E26 -> 0.021864948 | N26: =F27 -> -0.0089290842 | O26: =G27 -> -0.015520182 | P26: =H27 -> -0.007852781 | Q26: =I27 -> -0.015554405 | S26: Error típico | T26: 0.00090188668 | U26: 0.00053006717 | V26: 0.00073330291 | W26: 0.00084396576 | Y26: Coca-Cola | Z26: 0.092908388 | AA26: 1
A27: 45190 | B27: 173.04452 | C27: 56.196419 | D27: 143.52991 | E27: 14.328587 | F27: =LN(B27/B26) -> -0.0089290842 | G27: =LN(C27/C26) -> -0.015520182 | H27: =LN(D27/D26) -> -0.007852781 | I27: =LN(E27/E26) -> -0.015554405 | J27: =(B27-B26)/B27 -> -0.0089690674 | K27: =(C27-C26)/C27 -> -0.015641246 | L27: =(D27-D26)/D27 -> -0.0078836949 | M27: =(E27-E26)/E27 -> -0.015676005 | N27: =F28 -> 0.0049321571 | O27: =G28 -> 0.0010421744 | P27: =H28 -> -0.009629071 | Q27: =I28 -> -0.012488017 | S27: Mediana | T27: 0.0019470367 | U27: 0.0010502723 | V27: 0.0020270955 | W27: 0.001411637 | Y27: JPMorgan | Z27: 0.047823405 | AA27: 0.18624002 | AB27: 1
A28: 45191 | B28: 173.90012 | C28: 56.255016 | D28: 142.15448 | E28: 14.150764 | F28: =LN(B28/B27) -> 0.0049321571 | G28: =LN(C28/C27) -> 0.0010421744 | H28: =LN(D28/D27) -> -0.009629071 | I28: =LN(E28/E27) -> -0.012488017 | J28: =(B28-B27)/B28 -> 0.004920014 | K28: =(C28-C27)/C28 -> 0.0010416316 | L28: =(D28-D27)/D28 -> -0.0096755797 | M28: =(E28-E27)/E28 -> -0.012566318 | N28: =F29 -> 0.0073532672 | O28: =G29 -> -0.01047125 | P28: =H29 -> 0.0049286703 | Q28: =I29 -> -0.0039760898 | S28: Moda | T28: #N/A | U28: 0 | V28: #N/A | W28: 0 | Y28: AT&T | Z28: -0.019839153 | AA28: 0.34877913 | AB28: 0.18621074 | AC28: 1
A29: 45194 | B29: 175.18356 | C29: 55.669029 | D29: 142.85684 | E29: 14.094611 | F29: =LN(B29/B28) -> 0.0073532672 | G29: =LN(C29/C28) -> -0.01047125 | H29: =LN(D29/D28) -> 0.0049286703 | I29: =LN(E29/E28) -> -0.0039760898 | J29: =(B29-B28)/B29 -> 0.0073262981 | K29: =(C29-C28)/C29 -> -0.010526266 | L29: =(D29-D28)/D29 -> 0.0049165444 | M29: =(E29-E28)/E29 -> -0.003984005 | N29: =F30 -> -0.02367657 | O29: =G30 -> -0.0082798818 | P29: =H30 -> -0.010433243 | Q29: =I30 -> -0.002659513 | S29: Desviación estándar | T29: 0.014317007 | U29: 0.0084145555 | V29: 0.011640823 | W29: 0.013397541
A30: 45195 | B30: 171.08453 | C30: 55.209999 | D30: 141.37413 | E30: 14.057176 | F30: =LN(B30/B29) -> -0.02367657 | G30: =LN(C30/C29) -> -0.0082798818 | H30: =LN(D30/D29) -> -0.010433243 | I30: =LN(E30/E29) -> -0.002659513 | J30: =(B30-B29)/B30 -> -0.023959086 | K30: =(C30-C29)/C30 -> -0.0083142548 | L30: =(D30-D29)/D30 -> -0.010487859 | M30: =(E30-E29)/E30 -> -0.0026630527 | N30: =F31 -> -0.0089372741 | O30: =G31 -> -0.010313022 | P30: =H31 -> 0.0058476761 | Q30: =I31 -> -0.010036916 | S30: Varianza de la muestra | T30: 0.00020497669 | U30: 7.0804744e-05 | V30: 0.00013550876 | W30: 0.00017949411
A31: 45196 | B31: 169.56232 | C31: 54.643543 | D31: 142.20326 | E31: 13.916791 | F31: =LN(B31/B30) -> -0.0089372741 | G31: =LN(C31/C30) -> -0.010313022 | H31: =LN(D31/D30) -> 0.0058476761 | I31: =LN(E31/E30) -> -0.010036916 | J31: =(B31-B30)/B31 -> -0.0089773307 | K31: =(C31-C30)/C31 -> -0.010366385 | L31: =(D31-D30)/D31 -> 0.0058306117 | M31: =(E31-E30)/E31 -> -0.010087455 | N31: =F32 -> 0.0015245124 | O31: =G32 -> -0.0025052794 | P31: =H32 -> 0.012339653 | Q31: =I32 -> 0.0093709133 | S31: Curtosis | T31: 3.1993752 | U31: 5.0354703 | V31: 5.9450521 | W31: 2.3858239
A32: 45197 | B32: 169.82101 | C32: 54.506817 | D32: 143.96887 | E32: 14.047817 | F32: =LN(B32/B31) -> 0.0015245124 | G32: =LN(C32/C31) -> -0.0025052794 | H32: =LN(D32/D31) -> 0.012339653 | I32: =LN(E32/E31) -> 0.0093709133 | J32: =(B32-B31)/B32 -> 0.0015233509 | K32: =(C32-C31)/C32 -> -0.0025084202 | L32: =(D32-D31)/D32 -> 0.012263832 | M32: =(E32-E31)/E32 -> 0.0093271431 | N32: =F33 -> 0.0030418118 | O32: =G33 -> 0.0030412832 | P32: =H33 -> -0.017566588 | Q32: =I33 -> 0.00066600268 | S32: Coeficiente de asimetría | T32: 0.26385726 | U32: -0.51847268 | V32: -1.4361975 | W32: 0.55654666
A33: 45198 | B33: 170.33836 | C33: 54.67284 | D33: 141.46191 | E33: 14.057176 | F33: =LN(B33/B32) -> 0.0030418118 | G33: =LN(C33/C32) -> 0.0030412832 | H33: =LN(D33/D32) -> -0.017566588 | I33: =LN(E33/E32) -> 0.00066600268 | J33: =(B33-B32)/B33 -> 0.0030371901 | K33: =(C33-C32)/C33 -> 0.0030366632 | L33: =(D33-D32)/D33 -> -0.017721788 | M33: =(E33-E32)/E33 -> 0.00066578095 | N33: =F34 -> 0.014726613 | O33: =G34 -> -0.0089718562 | P33: =H34 -> -0.0086567489 | Q33: =I34 -> -0.023578125 | S33: Rango | T33: 0.11949705 | U33: 0.077973266 | V33: 0.094393619 | W33: 0.10225349
A34: 45201 | B34: 172.86543 | C34: 54.184517 | D34: 140.2426 | E34: 13.729611 | F34: =LN(B34/B33) -> 0.014726613 | G34: =LN(C34/C33) -> -0.0089718562 | H34: =LN(D34/D33) -> -0.0086567489 | I34: =LN(E34/E33) -> -0.023578125 | J34: =(B34-B33)/B34 -> 0.014618706 | K34: =(C34-C33)/C34 -> -0.0090122239 | L34: =(D34-D33)/D34 -> -0.0086943269 | M34: =(E34-E33)/E34 -> -0.023858287 | N34: =F35 -> -0.0078002014 | O34: =G35 -> -0.010873561 | P34: =H35 -> -0.0074001161 | Q34: =I35 -> 0.0074704184 | S34: Mínimo | T34: -0.049365633 | U34: -0.049535374 | V34: -0.066864291 | W34: -0.038675611
A35: 45202 | B35: 171.52229 | C35: 53.59853 | D35: 139.20862 | E35: 13.832561 | F35: =LN(B35/B34) -> -0.0078002014 | G35: =LN(C35/C34) -> -0.010873561 | H35: =LN(D35/D34) -> -0.0074001161 | I35: =LN(E35/E34) -> 0.0074704184 | J35: =(B35-B34)/B35 -> -0.0078307022 | K35: =(C35-C34)/C35 -> -0.010932893 | L35: =(D35-D34)/D35 -> -0.0074275646 | M35: =(E35-E34)/E35 -> 0.0074425842 | N35: =F36 -> 0.0072820978 | O35: =G36 -> 0.00291123 | P35: =H36 -> 0.0044743813 | Q35: =I36 -> -0.0088346793 | S35: Máximo | T35: 0.070131414 | U35: 0.028437891 | V35: 0.027529327 | W35: 0.063577877
A36: 45203 | B36: 172.77589 | C36: 53.754795 | D36: 139.83289 | E36: 13.710893 | F36: =LN(B36/B35) -> 0.0072820978 | G36: =LN(C36/C35) -> 0.00291123 | H36: =LN(D36/D35) -> 0.0044743813 | I36: =LN(E36/E35) -> -0.0088346793 | J36: =(B36-B35)/B36 -> 0.0072556476 | K36: =(C36-C35)/C36 -> 0.0029069965 | L36: =(D36-D35)/D36 -> 0.0044643862 | M36: =(E36-E35)/E36 -> -0.0088738203 | N36: =F37 -> 0.0071721957 | O36: =G37 -> -0.049535374 | P36: =H37 -> 0.0042075902 | Q36: =I37 -> 0.012211858 | S36: Suma | T36: 0.25214283 | U36: 0.16592897 | V36: 0.37877581 | W36: 0.38225029
A37: 45204 | B37: 174.01953 | C37: 51.156906 | D37: 140.42248 | E37: 13.879355 | F37: =LN(B37/B36) -> 0.0071721957 | G37: =LN(C37/C36) -> -0.049535374 | H37: =LN(D37/D36) -> 0.0042075902 | I37: =LN(E37/E36) -> 0.012211858 | J37: =(B37-B36)/B37 -> 0.0071465369 | K37: =(C37-C36)/C37 -> -0.050782762 | L37: =(D37-D36)/D37 -> 0.0041987506 | M37: =(E37-E36)/E37 -> 0.012137596 | N37: =F38 -> 0.014642797 | O37: =G38 -> 0.014405069 | P37: =H38 -> 0.015278133 | Q37: =I38 -> -0.0070340122 | S37: Cuenta | T37: 252 | U37: 252 | V37: 252 | W37: 252
A38: 45205 | B38: 176.58641 | C38: 51.899158 | D38: 142.58435 | E38: 13.78207 | F38: =LN(B38/B37) -> 0.014642797 | G38: =LN(C38/C37) -> 0.014405069 | H38: =LN(D38/D37) -> 0.015278133 | I38: =LN(E38/E37) -> -0.0070340122 | J38: =(B38-B37)/B38 -> 0.014536113 | K38: =(C38-C37)/C38 -> 0.014301812 | L38: =(D38-D37)/D38 -> 0.015162015 | M38: =(E38-E37)/E38 -> -0.007058809 | N38: =F39 -> 0.0084155365 | O38: =G39 -> -0.0049046695 | P38: =H39 -> -0.0022767876 | Q38: =I39 -> 0.019191787
A39: 45208 | B39: 178.07875 | C39: 51.645233 | D39: 142.26009 | E39: 14.049127 | F39: =LN(B39/B38) -> 0.0084155365 | G39: =LN(C39/C38) -> -0.0049046695 | H39: =LN(D39/D38) -> -0.0022767876 | I39: =LN(E39/E38) -> 0.019191787 | J39: =(B39-B38)/B39 -> 0.008380225 | K39: =(C39-C38)/C39 -> -0.0049167171 | L39: =(D39-D38)/D39 -> -0.0022793814 | M39: =(E39-E38)/E39 -> 0.019008797 | N39: =F40 -> -0.0033577377 | O39: =G40 -> 0.021514156 | P39: =H40 -> 0.0060600171 | Q39: =I40 -> 0.015493841 | S39: Máxima JPMorgan | T39: =_xlfn.PERCENTRANK.INC(F3:F254,$V$35) -> 0.979 | U39: =_xlfn.PERCENTRANK.INC(G3:G254,$V$35) -> 0.999 | V39: =_xlfn.PERCENTRANK.INC(H3:H254,$V$35) -> #N/A | W39: =_xlfn.PERCENTRANK.INC(I3:I254,$V$35) -> 0.96
A40: 45209 | B40: 177.48181 | C40: 52.768375 | D40: 143.1248 | E40: 14.268497 | F40: =LN(B40/B39) -> -0.0033577377 | G40: =LN(C40/C39) -> 0.021514156 | H40: =LN(D40/D39) -> 0.0060600171 | I40: =LN(E40/E39) -> 0.015493841 | J40: =(B40-B39)/B40 -> -0.0033633813 | K40: =(C40-C39)/C40 -> 0.021284377 | L40: =(D40-D39)/D40 -> 0.0060416922 | M40: =(E40-E39)/E40 -> 0.015374429 | N40: =F41 -> 0.0078729257 | O40: =G41 -> -0.0059402086 | P40: =H41 -> 0.0034271246 | Q40: =I41 -> -0.012781979
A41: 45210 | B41: 178.88463 | C41: 52.455849 | D41: 143.61615 | E41: 14.087278 | F41: =LN(B41/B40) -> 0.0078729257 | G41: =LN(C41/C40) -> -0.0059402086 | H41: =LN(D41/D40) -> 0.0034271246 | I41: =LN(E41/E40) -> -0.012781979 | J41: =(B41-B40)/B41 -> 0.0078420154 | K41: =(C41-C40)/C41 -> -0.0059578866 | L41: =(D41-D40)/D41 -> 0.0034212587 | M41: =(E41-E40)/E41 -> -0.012864018 | N41: =F42 -> 0.0050484915 | O41: =G42 -> -0.016898606 | P41: =H42 -> -0.0023292037 | Q41: =I42 -> -0.021903649 | S41: H0: La variable se distribuye como una normal
A42: 45211 | B42: 179.79001 | C42: 51.576866 | D42: 143.28203 | E42: 13.78207 | F42: =LN(B42/B41) -> 0.0050484915 | G42: =LN(C42/C41) -> -0.016898606 | H42: =LN(D42/D41) -> -0.0023292037 | I42: =LN(E42/E41) -> -0.021903649 | J42: =(B42-B41)/B42 -> 0.0050357693 | K42: =(C42-C41)/C42 -> -0.017042195 | L42: =(D42-D41)/D42 -> -0.0023319184 | M42: =(E42-E41)/E42 -> -0.022145295 | N42: =F43 -> -0.010346128 | O42: =G43 -> 0.0015136609 | P42: =H43 -> 0.014908028 | Q42: =I43 -> -0.0062479325 | S42: Test de Jarque-Beta | T42: =(T32^2)/6+(T31^2)/24 -> 0.43810351 | U42: =(U32^2)/6+(U31^2)/24 -> 1.1013007 | V42: =(V32^2)/6+(V31^2)/24 -> 1.8164291 | W42: =(W32^2)/6+(W31^2)/24 -> 0.28879719
A43: 45212 | B43: 177.93947 | C43: 51.654995 | D43: 145.43408 | E43: 13.696229 | F43: =LN(B43/B42) -> -0.010346128 | G43: =LN(C43/C42) -> 0.0015136609 | H43: =LN(D43/D42) -> 0.014908028 | I43: =LN(E43/E42) -> -0.0062479325 | J43: =(B43-B42)/B43 -> -0.010399834 | K43: =(C43-C42)/C43 -> 0.0015125159 | L43: =(D43-D42)/D43 -> 0.014797453 | M43: =(E43-E42)/E43 -> -0.0062674916 | N43: =F44 -> -0.00072710134 | O43: =G44 -> 0.010158067 | P43: =H44 -> -0.0010140315 | Q43: =I44 -> 0.0034759323 | S43: p-value | T43: =CHIDIST(T42,2) -> 0.80328014 | U43: =CHIDIST(U42,2) -> 0.57657472 | V43: =CHIDIST(V42,2) -> 0.40324356 | W43: =CHIDIST(W42,2) -> 0.86554268
A44: 45215 | B44: 177.81014 | C44: 52.182384 | D44: 145.28668 | E44: 13.743919 | F44: =LN(B44/B43) -> -0.00072710134 | G44: =LN(C44/C43) -> 0.010158067 | H44: =LN(D44/D43) -> -0.0010140315 | I44: =LN(E44/E43) -> 0.0034759323 | J44: =(B44-B43)/B44 -> -0.00072736574 | K44: =(C44-C43)/C44 -> 0.010106648 | L44: =(D44-D43)/D44 -> -0.0010145458 | M44: =(E44-E43)/E44 -> 0.0034698982 | N44: =F45 -> -0.0088236168 | O44: =G45 -> 0.011907237 | P44: =H45 -> -0.0021668113 | Q44: =I45 -> 0.011728317
A45: 45216 | B45: 176.24811 | C45: 52.807446 | D45: 144.97221 | E45: 13.906061 | F45: =LN(B45/B44) -> -0.0088236168 | G45: =LN(C45/C44) -> 0.011907237 | H45: =LN(D45/D44) -> -0.0021668113 | I45: =LN(E45/E44) -> 0.011728317 | J45: =(B45-B44)/B45 -> -0.0088626597 | K45: =(C45-C44)/C45 -> 0.011836626 | L45: =(D45-D44)/D45 -> -0.0021691605 | M45: =(E45-E44)/E45 -> 0.011659808 | N45: =F46 -> -0.007422337 | O45: =G46 -> -0.00037001628 | P45: =H46 -> -0.011041381 | Q45: =I46 -> -0.017993647
A46: 45217 | B46: 174.94478 | C46: 52.78791 | D46: 143.38032 | E46: 13.658078 | F46: =LN(B46/B45) -> -0.007422337 | G46: =LN(C46/C45) -> -0.00037001628 | H46: =LN(D46/D45) -> -0.011041381 | I46: =LN(E46/E45) -> -0.017993647 | J46: =(B46-B45)/B46 -> -0.0074499509 | K46: =(C46-C45)/C46 -> -0.00037008474 | L46: =(D46-D45)/D46 -> -0.011102562 | M46: =(E46-E45)/E46 -> -0.018156508 | N46: =F47 -> -0.0021632257 | O46: =G47 -> 0.0055350153 | P46: =H47 -> -0.0042583678 | Q46: =I47 -> 0.063577877
A47: 45218 | B47: 174.56674 | C47: 53.080902 | D47: 142.77106 | E47: 14.554628 | F47: =LN(B47/B46) -> -0.0021632257 | G47: =LN(C47/C46) -> 0.0055350153 | H47: =LN(D47/D46) -> -0.0042583678 | I47: =LN(E47/E46) -> 0.063577877 | J47: =(B47-B46)/B47 -> -0.0021655671 | K47: =(C47-C46)/C47 -> 0.0055197253 | L47: =(D47-D46)/D47 -> -0.0042674476 | M47: =(E47-E46)/E47 -> 0.061598964 | N47: =F48 -> -0.014813464 | O47: =G48 -> 0.0040397446 | P47: =H48 -> -0.016236772 | Q47: =I48 -> 0.007833063
A48: 45219 | B48: 171.99986 | C48: 53.295769 | D48: 140.47163 | E48: 14.669083 | F48: =LN(B48/B47) -> -0.014813464 | G48: =LN(C48/C47) -> 0.0040397446 | H48: =LN(D48/D47) -> -0.016236772 | I48: =LN(E48/E47) -> 0.007833063 | J48: =(B48-B47)/B48 -> -0.014923727 | K48: =(C48-C47)/C48 -> 0.0040315958 | L48: =(D48-D47)/D48 -> -0.016369305 | M48: =(E48-E47)/E48 -> 0.0078024645 | N48: =F49 -> 0.0006938528 | O48: =G49 -> -0.0090198437 | P48: =H49 -> -0.013735077 | Q48: =I49 -> -0.028356671
A49: 45222 | B49: 172.11925 | C49: 52.817211 | D49: 138.55543 | E49: 14.258959 | F49: =LN(B49/B48) -> 0.0006938528 | G49: =LN(C49/C48) -> -0.0090198437 | H49: =LN(D49/D48) -> -0.013735077 | I49: =LN(E49/E48) -> -0.028356671 | J49: =(B49-B48)/B49 -> 0.00069361214 | K49: =(C49-C48)/C49 -> -0.009060645 | L49: =(D49-D48)/D49 -> -0.013829836 | M49: =(E49-E48)/E49 -> -0.028762549 | N49: =F50 -> 0.0025402111 | O49: =G50 -> 0.028437891 | P49: =H50 -> 0.00120495 | Q49: =I50 -> 0.038062244
A50: 45223 | B50: 172.55702 | C50: 54.340782 | D50: 138.72249 | E50: 14.812148 | F50: =LN(B50/B49) -> 0.0025402111 | G50: =LN(C50/C49) -> 0.028437891 | H50: =LN(D50/D49) -> 0.00120495 | I50: =LN(E50/E49) -> 0.038062244 | J50: =(B50-B49)/B50 -> 0.0025369875 | K50: =(C50-C49)/C50 -> 0.02803734 | L50: =(D50-D49)/D50 -> 0.0012042244 | M50: =(E50-E49)/E50 -> 0.03734698 | N50: =F51 -> -0.013583578 | O50: =G51 -> 0.008589892 | P50: =H51 -> -0.005469475 | Q50: =I51 -> -0.022136321
A51: 45224 | B51: 170.22893 | C51: 54.809574 | D51: 137.96582 | E51: 14.487864 | F51: =LN(B51/B50) -> -0.013583578 | G51: =LN(C51/C50) -> 0.008589892 | H51: =LN(D51/D50) -> -0.005469475 | I51: =LN(E51/E50) -> -0.022136321 | J51: =(B51-B50)/B51 -> -0.013676254 | K51: =(C51-C50)/C51 -> 0.0085531042 | L51: =(D51-D50)/D51 -> -0.0054844598 | M51: =(E51-E50)/E51 -> -0.022383148 | N51: =F52 -> -0.024913185 | O51: =G52 -> -0.0060768941 | P51: =H52 -> 0.0025609401 | Q51: =I52 -> -0.0046189216
A52: 45225 | B52: 166.04038 | C52: 54.477512 | D52: 138.31959 | E52: 14.4211 | F52: =LN(B52/B51) -> -0.024913185 | G52: =LN(C52/C51) -> -0.0060768941 | H52: =LN(D52/D51) -> 0.0025609401 | I52: =LN(E52/E51) -> -0.0046189216 | J52: =(B52-B51)/B52 -> -0.025226111 | K52: =(C52-C51)/C52 -> -0.0060953958 | L52: =(D52-D51)/D52 -> 0.0025576636 | M52: =(E52-E51)/E52 -> -0.0046296052 | N52: =F53 -> 0.0079376258 | O52: =G53 -> -0.0097279469 | P52: =H53 -> -0.036683338 | Q52: =I53 -> -0.020040685
A53: 45226 | B53: 167.36359 | C53: 53.950127 | D53: 133.33751 | E53: 14.134968 | F53: =LN(B53/B52) -> 0.0079376258 | G53: =LN(C53/C52) -> -0.0097279469 | H53: =LN(D53/D52) -> -0.036683338 | I53: =LN(E53/E52) -> -0.020040685 | J53: =(B53-B52)/B53 -> 0.0079062061 | K53: =(C53-C52)/C53 -> -0.0097754172 | L53: =(D53-D52)/D53 -> -0.037364475 | M53: =(E53-E52)/E53 -> -0.020242847 | N53: =F54 -> 0.012230145 | O53: =G54 -> 0.016339295 | P53: =H54 -> 0.012668987 | Q53: =I54 -> 0.029257291
A54: 45229 | B54: 169.42303 | C54: 54.838875 | D54: 135.03751 | E54: 14.554628 | F54: =LN(B54/B53) -> 0.012230145 | G54: =LN(C54/C53) -> 0.016339295 | H54: =LN(D54/D53) -> 0.012668987 | I54: =LN(E54/E53) -> 0.029257291 | J54: =(B54-B53)/B54 -> 0.012155661 | K54: =(C54-C53)/C54 -> 0.016206532 | L54: =(D54-D53)/D54 -> 0.012589073 | M54: =(E54-E53)/E54 -> 0.02883344 | N54: =F55 -> 0.0028148308 | O54: =G55 -> 0.0060369707 | P54: =H55 -> 0.011863603 | Q54: =I55 -> 0.0091325042
A55: 45230 | B55: 169.9006 | C55: 55.170937 | D55: 136.64908 | E55: 14.688157 | F55: =LN(B55/B54) -> 0.0028148308 | G55: =LN(C55/C54) -> 0.0060369707 | H55: =LN(D55/D54) -> 0.011863603 | I55: =LN(E55/E54) -> 0.0091325042 | J55: =(B55-B54)/B55 -> 0.0028108729 | K55: =(C55-C54)/C55 -> 0.0060187849 | L55: =(D55-D54)/D55 -> 0.011793508 | M55: =(E55-E54)/E55 -> 0.0090909295 | N55: =F56 -> 0.018565291 | O55: =G56 -> -0.00088556819 | P55: =H56 -> -0.00086331287 | Q55: =I56 -> 0.011620615
... A254: 45520 | B254: 226.05 | C254: 69.18 | D254: 213.97 | E254: 19.34 | F254: =LN(B254/B253) -> 0.0059010398 | G254: =LN(C254/C253) -> 0.0076906422 | H254: =LN(D254/D253) -> 0.011374432 | I254: =LN(E254/E253) -> 0.013010852 | J254: =(B254-B253)/B254 -> 0.0058836628 | K254: =(C254-C253)/C254 -> 0.0076611448 | L254: =(D254-D253)/D254 -> 0.011309987 | M254: =(E254-E253)/E254 -> 0.012926577 | N254: =F255 -> 0 | O254: =G255 -> 0 | P254: =H255 -> 0 | Q254: =I255 -> 0

Sheet Portafolio
A1: Fecha | B1: Apple | C1: Coca-Cola | D1: JPMorgan | E1: AT&T | F1: Rentabilidad
A2: 45154 | B2: 175.67108 | C2: 58.602821 | D2: 146.50507 | E2: 13.196151 | F2: ="r_"&B1 -> r_Apple | G2: ="r_"&C1 -> r_Coca-Cola | H2: ="r_"&D1 -> r_JPMorgan | I2: ="r_"&E1 -> r_AT&T | J2: Portafolio
A3: 45155 | B3: 173.11415 | C3: 58.72879 | D3: 144.98335 | E3: 13.111919 | F3: =LN(B3/B2) -> -0.014662185 | G3: =LN(C3/C2) -> 0.0021472312 | H3: =LN(D3/D2) -> -0.010441079 | I3: =LN(E3/E2) -> -0.0064035323 | J3: =SUMPRODUCT(F3:I3,$M$37:$P$37) -> -0.009467057
A4: 45156 | B4: 173.60165 | C4: 59.058239 | D4: 145.315 | E4: 13.149357 | F4: =LN(B4/B3) -> 0.0028121206 | G4: =LN(C4/C3) -> 0.0055939922 | H4: =LN(D4/D3) -> 0.0022848848 | I4: =LN(E4/E3) -> 0.0028511962 | J4: =SUMPRODUCT(F4:I4,$M$37:$P$37) -> 0.0027076334
A5: 45159 | B5: 174.94478 | C5: 58.554379 | D5: 145.8125 | E5: 13.196151 | F5: =LN(B5/B4) -> 0.00770704 | G5: =LN(C5/C4) -> -0.0085681807 | H5: =LN(D5/D4) -> 0.0034177361 | I5: =LN(E5/E4) -> 0.0035523361 | J5: =SUMPRODUCT(F5:I5,$M$37:$P$37) -> 0.0038265778
A6: 45160 | B6: 176.3277 | C6: 58.195862 | D6: 142.78856 | E6: 13.345895 | F6: =LN(B6/B5) -> 0.0078738144 | G6: =LN(C6/C5) -> -0.0061416255 | H6: =LN(D6/D5) -> -0.020956622 | I6: =LN(E6/E5) -> 0.011283651 | J6: =SUMPRODUCT(F6:I6,$M$37:$P$37) -> -0.004214152
A7: 45161 | B7: 180.19791 | C7: 58.399345 | D7: 143.75426 | E7: 13.252305 | F7: =LN(B7/B6) -> 0.02171154 | G7: =LN(C7/C6) -> 0.0034904215 | H7: =LN(D7/D6) -> 0.0067403655 | I7: =LN(E7/E6) -> -0.0070373474 | J7: =SUMPRODUCT(F7:I7,$M$37:$P$37) -> 0.0051511975
A8: 45162 | B8: 175.48202 | C8: 58.244312 | D8: 143.61769 | E8: 13.242945 | F8: =LN(B8/B7) -> -0.026519109 | G8: =LN(C8/C7) -> -0.0026582344 | H8: =LN(D8/D7) -> -0.00095044775 | I8: =LN(E8/E7) -> -0.00070654177 | J8: =SUMPRODUCT(F8:I8,$M$37:$P$37) -> -0.0060379501
A9: 45163 | B9: 177.7007 | C9: 58.515617 | D9: 143.44211 | E9: 13.205509 | F9: =LN(B9/B8) -> 0.012564053 | G9: =LN(C9/C8) -> 0.0046472363 | H9: =LN(D9/D8) -> -0.0012233202 | I9: =LN(E9/E8) -> -0.0028308668 | J9: =SUMPRODUCT(F9:I9,$M$37:$P$37) -> 0.0012464294
A10: 45166 | B10: 179.27266 | C10: 58.68034 | D10: 143.93961 | E10: 13.299099 | F10: =LN(B10/B9) -> 0.0088072128 | G10: =LN(C10/C9) -> 0.0028110715 | H10: =LN(D10/D9) -> 0.0034622836 | I10: =LN(E10/E9) -> 0.0070621976 | J10: =SUMPRODUCT(F10:I10,$M$37:$P$37) -> 0.0056612861
A11: 45167 | B11: 183.18263 | C11: 58.622204 | D11: 145.11015 | E11: 13.823201 | F11: =LN(B11/B10) -> 0.021575763 | G11: =LN(C11/C10) -> -0.00099121473 | H11: =LN(D11/D10) -> 0.0080993211 | I11: =LN(E11/E10) -> 0.038652124 | J11: =SUMPRODUCT(F11:I11,$M$37:$P$37) -> 0.020261285
A12: 45168 | B12: 186.69466 | C12: 58.593136 | D12: 144.52487 | E12: 13.785766 | F12: =LN(B12/B11) -> 0.018990782 | G12: =LN(C12/C11) -> -0.00049597605 | H12: =LN(D12/D11) -> -0.0040415126 | I12: =LN(E12/E11) -> -0.0027118018 | J12: =SUMPRODUCT(F12:I12,$M$37:$P$37) -> 0.0011226617
A13: 45169 | B13: 186.91354 | C13: 57.973003 | D13: 142.73978 | E13: 13.841919 | F13: =LN(B13/B12) -> 0.0011717517 | G13: =LN(C13/C12) -> -0.01064012 | H13: =LN(D13/D12) -> -0.012428386 | I13: =LN(E13/E12) -> 0.0040649861 | J13: =SUMPRODUCT(F13:I13,$M$37:$P$37) -> -0.0043288022
A14: 45170 | B14: 188.49547 | C14: 57.469139 | D14: 143.21776 | E14: 13.710893 | F14: =LN(B14/B13) -> 0.0084277858 | G14: =LN(C14/C13) -> -0.008729346 | H14: =LN(D14/D13) -> 0.003343024 | I14: =LN(E14/E13) -> -0.0095109703 | J14: =SUMPRODUCT(F14:I14,$M$37:$P$37) -> -0.00027929642
... A23: 45184 | B23: 174.119 | C23: 56.587074 | D23: 145.15892 | E23: 14.253714 | F23: =LN(B23/B22) -> -0.0041626265 | G23: =LN(C23/C22) -> -0.0089348416 | H23: =LN(D23/D22) -> -0.0029524998 | I23: =LN(E23/E22) -> 0.011224979 | J23: =SUMPRODUCT(F23:I23,$M$37:$P$37) -> 0.001131343
A24: 45187 | B24: 177.06393 | C24: 56.938667 | D24: 145.46132 | E24: 14.122688 | F24: =LN(B24/B23) -> 0.016771886 | G24: =LN(C24/C23) -> 0.0061940864 | H24: =LN(D24/D23) -> 0.0020810602 | I24: =LN(E24/E23) -> -0.0092349221 | J24: =SUMPRODUCT(F24:I24,$M$37:$P$37) -> 0.0015301137 | L24: diario | M24: Apple | N24: Coca-Cola | O24: JPMorgan | P24: AT&T
A25: 45188 | B25: 178.15834 | C25: 56.821472 | D25: 145.27597 | E25: 14.234997 | F25: =LN(B25/B24) -> 0.006161829 | G25: =LN(C25/C24) -> -0.0020603885 | H25: =LN(D25/D24) -> -0.0012750275 | I25: =LN(E25/E24) -> 0.0079209278 | J25: =SUMPRODUCT(F25:I25,$M$37:$P$37) -> 0.0031390479 | L25: promedio | M25: =AVERAGE(F3:F254) -> 0.0010005668 | N25: =AVERAGE(G3:G254) -> 0.00065844829 | O25: =AVERAGE(H3:H254) -> 0.0015030786 | P25: =AVERAGE(I3:I254) -> 0.0015168662
A26: 45189 | B26: 174.59657 | C26: 57.075401 | D26: 144.66145 | E26: 14.553202 | F26: =LN(B26/B25) -> -0.02019469 | G26: =LN(C26/C25) -> 0.0044589358 | H26: =LN(D26/D25) -> -0.0042389693 | I26: =LN(E26/E25) -> 0.022107528 | J26: =SUMPRODUCT(F26:I26,$M$37:$P$37) -> 0.0014273245 | L26: mediana | M26: =MEDIAN(F3:F254) -> 0.0019470367 | N26: =MEDIAN(G3:G254) -> 0.0010502723 | O26: =MEDIAN(H3:H254) -> 0.0020270955 | P26: =MEDIAN(I3:I254) -> 0.001411637
A27: 45190 | B27: 173.04452 | C27: 56.196419 | D27: 143.52991 | E27: 14.328587 | F27: =LN(B27/B26) -> -0.0089290842 | G27: =LN(C27/C26) -> -0.015520182 | H27: =LN(D27/D26) -> -0.007852781 | I27: =LN(E27/E26) -> -0.015554405 | J27: =SUMPRODUCT(F27:I27,$M$37:$P$37) -> -0.010862645 | L27: stdev | M27: =_xlfn.STDEV.S(F3:F254) -> 0.014317007 | N27: =_xlfn.STDEV.S(G3:G254) -> 0.0084145555 | O27: =_xlfn.STDEV.S(H3:H254) -> 0.011640823 | P27: =_xlfn.STDEV.S(I3:I254) -> 0.013397541
A28: 45191 | B28: 173.90012 | C28: 56.255016 | D28: 142.15448 | E28: 14.150764 | F28: =LN(B28/B27) -> 0.0049321571 | G28: =LN(C28/C27) -> 0.0010421744 | H28: =LN(D28/D27) -> -0.009629071 | I28: =LN(E28/E27) -> -0.012488017 | J28: =SUMPRODUCT(F28:I28,$M$37:$P$37) -> -0.0072123448
A29: 45194 | B29: 175.18356 | C29: 55.669029 | D29: 142.85684 | E29: 14.094611 | F29: =LN(B29/B28) -> 0.0073532672 | G29: =LN(C29/C28) -> -0.01047125 | H29: =LN(D29/D28) -> 0.0049286703 | I29: =LN(E29/E28) -> -0.0039760898 | J29: =SUMPRODUCT(F29:I29,$M$37:$P$37) -> 0.0019130568 | L29: anualizado | M29: =M24 -> Apple | N29: =N24 -> Coca-Cola | O29: =O24 -> JPMorgan | P29: =P24 -> AT&T
A30: 45195 | B30: 171.08453 | C30: 55.209999 | D30: 141.37413 | E30: 14.057176 | F30: =LN(B30/B29) -> -0.02367657 | G30: =LN(C30/C29) -> -0.0082798818 | H30: =LN(D30/D29) -> -0.010433243 | I30: =LN(E30/E29) -> -0.002659513 | J30: =SUMPRODUCT(F30:I30,$M$37:$P$37) -> -0.010479527 | L30: promedio | M30: =((1+M25)^250)-1 -> 0.28404678 | N30: =((1+N25)^250)-1 -> 0.17887183 | O30: =((1+O25)^250)-1 -> 0.45570095 | P30: =((1+P25)^250)-1 -> 0.46071967
A31: 45196 | B31: 169.56232 | C31: 54.643543 | D31: 142.20326 | E31: 13.916791 | F31: =LN(B31/B30) -> -0.0089372741 | G31: =LN(C31/C30) -> -0.010313022 | H31: =LN(D31/D30) -> 0.0058476761 | I31: =LN(E31/E30) -> -0.010036916 | J31: =SUMPRODUCT(F31:I31,$M$37:$P$37) -> -0.002878807 | L31: mediana | M31: =(1+M26)^250-1 -> 0.62626493 | N31: =(1+N26)^250-1 -> 0.30008584 | O31: =(1+O26)^250-1 -> 0.65907619 | P31: =(1+P26)^250-1 -> 0.42284786
A32: 45197 | B32: 169.82101 | C32: 54.506817 | D32: 143.96887 | E32: 14.047817 | F32: =LN(B32/B31) -> 0.0015245124 | G32: =LN(C32/C31) -> -0.0025052794 | H32: =LN(D32/D31) -> 0.012339653 | I32: =LN(E32/E31) -> 0.0093709133 | J32: =SUMPRODUCT(F32:I32,$M$37:$P$37) -> 0.0086209084 | L32: stdev | M32: =M27*SQRT(250) -> 0.22637176 | N32: =N27*SQRT(250) -> 0.1330458 | O32: =O27*SQRT(250) -> 0.18405757 | P32: =P27*SQRT(250) -> 0.21183372
A33: 45198 | B33: 170.33836 | C33: 54.67284 | D33: 141.46191 | E33: 14.057176 | F33: =LN(B33/B32) -> 0.0030418118 | G33: =LN(C33/C32) -> 0.0030412832 | H33: =LN(D33/D32) -> -0.017566588 | I33: =LN(E33/E32) -> 0.00066600268 | J33: =SUMPRODUCT(F33:I33,$M$37:$P$37) -> -0.0067410009 | L33: sharpe | M33: =M30/M32 -> 1.2547801 | N33: =N30/N32 -> 1.3444379 | O33: =O30/O32 -> 2.4758609 | P33: =P30/P32 -> 2.1749118
A34: 45201 | B34: 172.86543 | C34: 54.184517 | D34: 140.2426 | E34: 13.729611 | F34: =LN(B34/B33) -> 0.014726613 | G34: =LN(C34/C33) -> -0.0089718562 | H34: =LN(D34/D33) -> -0.0086567489 | I34: =LN(E34/E33) -> -0.023578125 | J34: =SUMPRODUCT(F34:I34,$M$37:$P$37) -> -0.0088179369
A35: 45202 | B35: 171.52229 | C35: 53.59853 | D35: 139.20862 | E35: 13.832561 | F35: =LN(B35/B34) -> -0.0078002014 | G35: =LN(C35/C34) -> -0.010873561 | H35: =LN(D35/D34) -> -0.0074001161 | I35: =LN(E35/E34) -> 0.0074704184 | J35: =SUMPRODUCT(F35:I35,$M$37:$P$37) -> -0.0028289856
A36: 45203 | B36: 172.77589 | C36: 53.754795 | D36: 139.83289 | E36: 13.710893 | F36: =LN(B36/B35) -> 0.0072820978 | G36: =LN(C36/C35) -> 0.00291123 | H36: =LN(D36/D35) -> 0.0044743813 | I36: =LN(E36/E35) -> -0.0088346793 | J36: =SUMPRODUCT(F36:I36,$M$37:$P$37) -> 0.00068071291 | L36: ponderador | M36: ="w_"&B1 -> w_Apple | N36: ="w_"&C1 -> w_Coca-Cola | O36: ="w_"&D1 -> w_JPMorgan | P36: ="w_"&E1 -> w_AT&T
A37: 45204 | B37: 174.01953 | C37: 51.156906 | D37: 140.42248 | E37: 13.879355 | F37: =LN(B37/B36) -> 0.0071721957 | G37: =LN(C37/C36) -> -0.049535374 | H37: =LN(D37/D36) -> 0.0042075902 | I37: =LN(E37/E36) -> 0.012211858 | J37: =SUMPRODUCT(F37:I37,$M$37:$P$37) -> 0.0051834638 | L37: wi | M37: 0.19932092 | N37: 0.040838545 | O37: 0.4375437 | P37: 0.32229684 | Q37: =SUM(M37:P37) -> 1
A38: 45205 | B38: 176.58641 | C38: 51.899158 | D38: 142.58435 | E38: 13.78207 | F38: =LN(B38/B37) -> 0.014642797 | G38: =LN(C38/C37) -> 0.014405069 | H38: =LN(D38/D37) -> 0.015278133 | I38: =LN(E38/E37) -> -0.0070340122 | J38: =SUMPRODUCT(F38:I38,$M$37:$P$37) -> 0.0079247087
A39: 45208 | B39: 178.07875 | C39: 51.645233 | D39: 142.26009 | E39: 14.049127 | F39: =LN(B39/B38) -> 0.0084155365 | G39: =LN(C39/C38) -> -0.0049046695 | H39: =LN(D39/D38) -> -0.0022767876 | I39: =LN(E39/E38) -> 0.019191787 | J39: =SUMPRODUCT(F39:I39,$M$37:$P$37) -> 0.006666351 | L39: promedio | M39: =AVERAGE(J3:J254) -> 0.0013728677 | N39: =((1+M39)^250)-1 -> 0.40914277 | P39: Treasury 1term | Q39: 0.0452
A40: 45209 | B40: 177.48181 | C40: 52.768375 | D40: 143.1248 | E40: 14.268497 | F40: =LN(B40/B39) -> -0.0033577377 | G40: =LN(C40/C39) -> 0.021514156 | H40: =LN(D40/D39) -> 0.0060600171 | I40: =LN(E40/E39) -> 0.015493841 | J40: =SUMPRODUCT(F40:I40,$M$37:$P$37) -> 0.0078544779 | L40: riesgo | M40: {=SQRT(MMULT(MMULT(M37:P37,M44:P47),TRANSPOSE(M37:P37)))} -> 0.0079850612 | N40: =M40*SQRT(250) -> 0.1262549 | P40: diario | Q40: =((1+Q39)^(1/250))-1 -> 0.00017684865
A41: 45210 | B41: 178.88463 | C41: 52.455849 | D41: 143.61615 | E41: 14.087278 | F41: =LN(B41/B40) -> 0.0078729257 | G41: =LN(C41/C40) -> -0.0059402086 | H41: =LN(D41/D40) -> 0.0034271246 | I41: =LN(E41/E40) -> -0.012781979 | J41: =SUMPRODUCT(F41:I41,$M$37:$P$37) -> -0.0012934256 | L41: sharpe | M41: =(M39-Q40)/M40 -> 0.14978208 | N41: =(N39-Q39)/N40 -> 2.882603
A42: 45211 | B42: 179.79001 | C42: 51.576866 | D42: 143.28203 | E42: 13.78207 | F42: =LN(B42/B41) -> 0.0050484915 | G42: =LN(C42/C41) -> -0.016898606 | H42: =LN(D42/D41) -> -0.0023292037 | I42: =LN(E42/E41) -> -0.021903649 | J42: =SUMPRODUCT(F42:I42,$M$37:$P$37) -> -0.0077624497
A43: 45212 | B43: 177.93947 | C43: 51.654995 | D43: 145.43408 | E43: 13.696229 | F43: =LN(B43/B42) -> -0.010346128 | G43: =LN(C43/C42) -> 0.0015136609 | H43: =LN(D43/D42) -> 0.014908028 | I43: =LN(E43/E42) -> -0.0062479325 | J43: =SUMPRODUCT(F43:I43,$M$37:$P$37) -> 0.0025088405 | L43: matriz_cov | M43: =M29 -> Apple | N43: =N29 -> Coca-Cola | O43: =O29 -> JPMorgan | P43: =P29 -> AT&T
A44: 45215 | B44: 177.81014 | C44: 52.182384 | D44: 145.28668 | E44: 13.743919 | F44: =LN(B44/B43) -> -0.00072710134 | G44: =LN(C44/C43) -> 0.010158067 | H44: =LN(D44/D43) -> -0.0010140315 | I44: =LN(E44/E43) -> 0.0034759323 | J44: =SUMPRODUCT(F44:I44,$M$37:$P$37) -> 0.00094651306 | L44: =M43 -> Apple | M44: =VARP(Portafolio!$F$3:$F$254) -> 0.00020416329 | N44: =M45 -> 1.1148374e-05 | O44: =M46 -> 7.9387037e-06 | P44: =M47 -> -2.200623e-06
A45: 45216 | B45: 176.24811 | C45: 52.807446 | D45: 144.97221 | E45: 13.906061 | F45: =LN(B45/B44) -> -0.0088236168 | G45: =LN(C45/C44) -> 0.011907237 | H45: =LN(D45/D44) -> -0.0021668113 | I45: =LN(E45/E44) -> 0.011728317 | J45: =SUMPRODUCT(F45:I45,$M$37:$P$37) -> 0.0015594676 | L45: =N43 -> Coca-Cola | M45: =_xlfn.COVARIANCE.P($F$3:$F$254,G3:G254) -> 1.1148374e-05 | N45: =VARP(Portafolio!$G$3:$G$254) -> 7.0523772e-05 | O45: =N46 -> 1.8170256e-05 | P45: =N47 -> 3.916336e-05
A46: 45217 | B46: 174.94478 | C46: 52.78791 | D46: 143.38032 | E46: 13.658078 | F46: =LN(B46/B45) -> -0.007422337 | G46: =LN(C46/C45) -> -0.00037001628 | H46: =LN(D46/D45) -> -0.011041381 | I46: =LN(E46/E45) -> -0.017993647 | J46: =SUMPRODUCT(F46:I46,$M$37:$P$37) -> -0.01212492 | L46: =O43 -> JPMorgan | M46: =_xlfn.COVARIANCE.P($F$3:$F$254,H3:H254) -> 7.9387037e-06 | N46: =_xlfn.COVARIANCE.P($G$3:$G$254,H3:H254) -> 1.8170256e-05 | O46: =VARP(Portafolio!$H$3:$H$254) -> 0.00013497102 | P46: =O47 -> 2.8925886e-05
A47: 45218 | B47: 174.56674 | C47: 53.080902 | D47: 142.77106 | E47: 14.554628 | F47: =LN(B47/B46) -> -0.0021632257 | G47: =LN(C47/C46) -> 0.0055350153 | H47: =LN(D47/D46) -> -0.0042583678 | I47: =LN(E47/E46) -> 0.063577877 | J47: =SUMPRODUCT(F47:I47,$M$37:$P$37) -> 0.018422593 | L47: =P43 -> AT&T | M47: =_xlfn.COVARIANCE.P($F$3:$F$254,I5:I256) -> -2.200623e-06 | N47: =_xlfn.COVARIANCE.P($G$3:$G$254,I3:I254) -> 3.916336e-05 | O47: =_xlfn.COVARIANCE.P($H$3:$H$254,I3:I254) -> 2.8925886e-05 | P47: =VARP(Portafolio!$I$3:$I$254) -> 0.00017878183
A48: 45219 | B48: 171.99986 | C48: 53.295769 | D48: 140.47163 | E48: 14.669083 | F48: =LN(B48/B47) -> -0.014813464 | G48: =LN(C48/C47) -> 0.0040397446 | H48: =LN(D48/D47) -> -0.016236772 | I48: =LN(E48/E47) -> 0.007833063 | J48: =SUMPRODUCT(F48:I48,$M$37:$P$37) -> -0.0073673817
A49: 45222 | B49: 172.11925 | C49: 52.817211 | D49: 138.55543 | E49: 14.258959 | F49: =LN(B49/B48) -> 0.0006938528 | G49: =LN(C49/C48) -> -0.0090198437 | H49: =LN(D49/D48) -> -0.013735077 | I49: =LN(E49/E48) -> -0.028356671 | J49: =SUMPRODUCT(F49:I49,$M$37:$P$37) -> -0.01537902
A50: 45223 | B50: 172.55702 | C50: 54.340782 | D50: 138.72249 | E50: 14.812148 | F50: =LN(B50/B49) -> 0.0025402111 | G50: =LN(C50/C49) -> 0.028437891 | H50: =LN(D50/D49) -> 0.00120495 | I50: =LN(E50/E49) -> 0.038062244 | J50: =SUMPRODUCT(F50:I50,$M$37:$P$37) -> 0.014462239
A51: 45224 | B51: 170.22893 | C51: 54.809574 | D51: 137.96582 | E51: 14.487864 | F51: =LN(B51/B50) -> -0.013583578 | G51: =LN(C51/C50) -> 0.008589892 | H51: =LN(D51/D50) -> -0.005469475 | I51: =LN(E51/E50) -> -0.022136321 | J51: =SUMPRODUCT(F51:I51,$M$37:$P$37) -> -0.011884293
A52: 45225 | B52: 166.04038 | C52: 54.477512 | D52: 138.31959 | E52: 14.4211 | F52: =LN(B52/B51) -> -0.024913185 | G52: =LN(C52/C51) -> -0.0060768941 | H52: =LN(D52/D51) -> 0.0025609401 | I52: =LN(E52/E51) -> -0.0046189216 | J52: =SUMPRODUCT(F52:I52,$M$37:$P$37) -> -0.005582031
A53: 45226 | B53: 167.36359 | C53: 53.950127 | D53: 133.33751 | E53: 14.134968 | F53: =LN(B53/B52) -> 0.0079376258 | G53: =LN(C53/C52) -> -0.0097279469 | H53: =LN(D53/D52) -> -0.036683338 | I53: =LN(E53/E52) -> -0.020040685 | J53: =SUMPRODUCT(F53:I53,$M$37:$P$37) -> -0.021324753
A54: 45229 | B54: 169.42303 | C54: 54.838875 | D54: 135.03751 | E54: 14.554628 | F54: =LN(B54/B53) -> 0.012230145 | G54: =LN(C54/C53) -> 0.016339295 | H54: =LN(D54/D53) -> 0.012668987 | I54: =LN(E54/E53) -> 0.029257291 | J54: =SUMPRODUCT(F54:I54,$M$37:$P$37) -> 0.018077765
A55: 45230 | B55: 169.9006 | C55: 55.170937 | D55: 136.64908 | E55: 14.688157 | F55: =LN(B55/B54) -> 0.0028148308 | G55: =LN(C55/C54) -> 0.0060369707 | H55: =LN(D55/D54) -> 0.011863603 | I55: =LN(E55/E54) -> 0.0091325042 | J55: =SUMPRODUCT(F55:I55,$M$37:$P$37) -> 0.0089418178
A56: 45231 | B56: 173.08432 | C56: 55.122101 | D56: 136.53116 | E56: 14.859838 | F56: =LN(B56/B55) -> 0.018565291 | G56: =LN(C56/C55) -> -0.00088556819 | H56: =LN(D56/D55) -> -0.00086331287 | I56: =LN(E56/E55) -> 0.011620615 | J56: =SUMPRODUCT(F56:I56,$M$37:$P$37) -> 0.0070318358
A57: 45232 | B57: 176.666 | C57: 55.756924 | D57: 138.96814 | E57: 15.002904 | F57: =LN(B57/B56) -> 0.02048207 | G57: =LN(C57/C56) -> 0.011450857 | H57: =LN(D57/D56) -> 0.017691846 | I57: =LN(E57/E56) -> 0.0095816449 | J57: =SUMPRODUCT(F57:I57,$M$37:$P$37) -> 0.015379231
A58: 45233 | B58: 175.75066 | C58: 55.415096 | D58: 140.52077 | E58: 15.14597 | F58: =LN(B58/B57) -> -0.005194681 | G58: =LN(C58/C57) -> -0.0061495523 | H58: =LN(D58/D57) -> 0.011110587 | I58: =LN(E58/E57) -> 0.0094907076 | J58: =SUMPRODUCT(F58:I58,$M$37:$P$37) -> 0.0066336452
A59: 45236 | B59: 178.31753 | C59: 55.639729 | D59: 141.58205 | E59: 15.021978 | F59: =LN(B59/B58) -> 0.014499602 | G59: =LN(C59/C58) -> 0.0040454488 | H59: =LN(D59/D58) -> 0.0075241008 | I59: =LN(E59/E58) -> -0.0082201612 | J59: =SUMPRODUCT(F59:I59,$M$37:$P$37) -> 0.0036980751
... A254: 45520 | B254: 226.05 | C254: 69.18 | D254: 213.97 | E254: 19.34 | F254: =LN(B254/B253) -> 0.0059010398 | G254: =LN(C254/C253) -> 0.0076906422 | H254: =LN(D254/D253) -> 0.011374432 | I254: =LN(E254/E253) -> 0.013010852 | J254: =SUMPRODUCT(F254:I254,$M$37:$P$37) -> 0.010660443

Sheet VaR (Volt. Hist)
A1: Rentabilidad
A2: =Portafolio!F2 -> r_Apple | B2: =Portafolio!G2 -> r_Coca-Cola | C2: =Portafolio!H2 -> r_JPMorgan | D2: =Portafolio!I2 -> r_AT&T | E2: =Portafolio!J2 -> Portafolio | G2: Volatilidad Historica (Desviación Estandar)
A3: =Portafolio!F3 -> -0.014662185 | B3: =Portafolio!G3 -> 0.0021472312 | C3: =Portafolio!H3 -> -0.010441079 | D3: =Portafolio!I3 -> -0.0064035323 | E3: =Portafolio!J3 -> -0.009467057
A4: =Portafolio!F4 -> 0.0028121206 | B4: =Portafolio!G4 -> 0.0055939922 | C4: =Portafolio!H4 -> 0.0022848848 | D4: =Portafolio!I4 -> 0.0028511962 | E4: =Portafolio!J4 -> 0.0027076334
A5: =Portafolio!F5 -> 0.00770704 | B5: =Portafolio!G5 -> -0.0085681807 | C5: =Portafolio!H5 -> 0.0034177361 | D5: =Portafolio!I5 -> 0.0035523361 | E5: =Portafolio!J5 -> 0.0038265778 | G5: Activos | H5: =A2 -> r_Apple | I5: =B2 -> r_Coca-Cola | J5: =C2 -> r_JPMorgan | K5: =D2 -> r_AT&T | L5: =E2 -> Portafolio
A6: =Portafolio!F6 -> 0.0078738144 | B6: =Portafolio!G6 -> -0.0061416255 | C6: =Portafolio!H6 -> -0.020956622 | D6: =Portafolio!I6 -> 0.011283651 | E6: =Portafolio!J6 -> -0.004214152 | G6: Desv. Estad. | H6: =_xlfn.STDEV.S(A3:A254) -> 0.014317007 | I6: =_xlfn.STDEV.S(B3:B254) -> 0.0084145555 | J6: =_xlfn.STDEV.S(C3:C254) -> 0.011640823 | K6: =_xlfn.STDEV.S(D3:D254) -> 0.013397541 | L6: =_xlfn.STDEV.S(E3:E254) -> 0.0079881271
A7: =Portafolio!F7 -> 0.02171154 | B7: =Portafolio!G7 -> 0.0034904215 | C7: =Portafolio!H7 -> 0.0067403655 | D7: =Portafolio!I7 -> -0.0070373474 | E7: =Portafolio!J7 -> 0.0051511975 | G7: t día(s) | H7: 1
A8: =Portafolio!F8 -> -0.026519109 | B8: =Portafolio!G8 -> -0.0026582344 | C8: =Portafolio!H8 -> -0.00095044775 | D8: =Portafolio!I8 -> -0.00070654177 | E8: =Portafolio!J8 -> -0.0060379501 | G8: Nivel de Confianza | H8: 0.95
A9: =Portafolio!F9 -> 0.012564053 | B9: =Portafolio!G9 -> 0.0046472363 | C9: =Portafolio!H9 -> -0.0012233202 | D9: =Portafolio!I9 -> -0.0028308668 | E9: =Portafolio!J9 -> 0.0012464294 | G9: Normal Estandar | H9: =NORMSINV(H8) -> 1.6448536
A10: =Portafolio!F10 -> 0.0088072128 | B10: =Portafolio!G10 -> 0.0028110715 | C10: =Portafolio!H10 -> 0.0034622836 | D10: =Portafolio!I10 -> 0.0070621976 | E10: =Portafolio!J10 -> 0.0056612861
A11: =Portafolio!F11 -> 0.021575763 | B11: =Portafolio!G11 -> -0.00099121473 | C11: =Portafolio!H11 -> 0.0080993211 | D11: =Portafolio!I11 -> 0.038652124 | E11: =Portafolio!J11 -> 0.020261285 | G11: No-Diversificado
A12: =Portafolio!F12 -> 0.018990782 | B12: =Portafolio!G12 -> -0.00049597605 | C12: =Portafolio!H12 -> -0.0040415126 | D12: =Portafolio!I12 -> -0.0027118018 | E12: =Portafolio!J12 -> 0.0011226617 | G12: VaR Diario 95% (%) | H12: =H6*SQRT($H$7)*$H$9 -> 0.023549381 | I12: =I6*SQRT($H$7)*$H$9 -> 0.013840712 | J12: =J6*SQRT($H$7)*$H$9 -> 0.01914745 | K12: =K6*SQRT($H$7)*$H$9 -> 0.022036994
A13: =Portafolio!F13 -> 0.0011717517 | B13: =Portafolio!G13 -> -0.01064012 | C13: =Portafolio!H13 -> -0.012428386 | D13: =Portafolio!I13 -> 0.0040649861 | E13: =Portafolio!J13 -> -0.0043288022 | G13: Exposición ($) | H13: 100000
A14: =Portafolio!F14 -> 0.0084277858 | B14: =Portafolio!G14 -> -0.008729346 | C14: =Portafolio!H14 -> 0.003343024 | D14: =Portafolio!I14 -> -0.0095109703 | E14: =Portafolio!J14 -> -0.00027929642 | G14: Perdida ($) al 95% | H14: =SUM(H12:K12)*H13 -> 7857.4537
A15: =Portafolio!F15 -> 0.0012659132 | B15: =Portafolio!G15 -> -0.0082960032 | C15: =Portafolio!H15 -> -0.011095406 | D15: =Portafolio!I15 -> -0.011671911 | E15: =Portafolio!J15 -> -0.0087030184
A16: =Portafolio!F16 -> -0.036449648 | B16: =Portafolio!G16 -> -0.00068026368 | C16: =Portafolio!H16 -> -0.0016539663 | D16: =Portafolio!I16 -> 0.0089378657 | E16: =Portafolio!J16 -> -0.0051359948 | G16: Diversificado
A17: =Portafolio!F17 -> -0.029685687 | B17: =Portafolio!G17 -> -0.0076850863 | C17: =Portafolio!H17 -> -0.0085911179 | D17: =Portafolio!I17 -> 0 | E17: =Portafolio!J17 -> -0.0099898157 | G17: VaR Diario 95% (%) | H17: =SQRT($H$7)*H9*L6 -> 0.0131393
A18: =Portafolio!F18 -> 0.0034855737 | B18: =Portafolio!G18 -> 0 | C18: =Portafolio!H18 -> 0.00076518324 | D18: =Portafolio!I18 -> -0.014477989 | E18: =Portafolio!J18 -> -0.0036366612 | G18: Exposición ($) | H18: 100000
A19: =Portafolio!F19 -> 0.006600704 | B19: =Portafolio!G19 -> 0.0093849136 | C19: =Portafolio!H19 -> 0.0043706423 | D19: =Portafolio!I19 -> 0.0082988273 | E19: =Portafolio!J19 -> 0.0062859574 | G19: Perdida ($) al 95% | H19: =H17*H18 -> 1313.93
A20: =Portafolio!F20 -> -0.017207767 | B20: =Portafolio!G20 -> -0.0098994166 | C20: =Portafolio!H20 -> 0.012930049 | D20: =Portafolio!I20 -> -0.0041408788 | E20: =Portafolio!J20 -> 0.00048872381
A21: =Portafolio!F21 -> -0.011925629 | B21: =Portafolio!G21 -> 0.0023984991 | C21: =Portafolio!H21 -> 0.00047822692 | D21: =Portafolio!I21 -> 0.011004271 | E21: =Portafolio!J21 -> 0.0014768109 | G21: Beneficio Diversificación | H21: =H14-H19 -> 6543.5237
A22: =Portafolio!F22 -> 0.0087441923 | B22: =Portafolio!G22 -> 0.0082446925 | C22: =Portafolio!H22 -> 0.019211775 | D22: =Portafolio!I22 -> 0.029651714 | E22: =Portafolio!J22 -> 0.020042246 | G22: Beneficio Diversificación | H22: =1-(H17/H12) -> 0.44205329
A23: =Portafolio!F23 -> -0.0041626265 | B23: =Portafolio!G23 -> -0.0089348416 | C23: =Portafolio!H23 -> -0.0029524998 | D23: =Portafolio!I23 -> 0.011224979 | E23: =Portafolio!J23 -> 0.001131343
A24: =Portafolio!F24 -> 0.016771886 | B24: =Portafolio!G24 -> 0.0061940864 | C24: =Portafolio!H24 -> 0.0020810602 | D24: =Portafolio!I24 -> -0.0092349221 | E24: =Portafolio!J24 -> 0.0015301137
A25: =Portafolio!F25 -> 0.006161829 | B25: =Portafolio!G25 -> -0.0020603885 | C25: =Portafolio!H25 -> -0.0012750275 | D25: =Portafolio!I25 -> 0.0079209278 | E25: =Portafolio!J25 -> 0.0031390479
A26: =Portafolio!F26 -> -0.02019469 | B26: =Portafolio!G26 -> 0.0044589358 | C26: =Portafolio!H26 -> -0.0042389693 | D26: =Portafolio!I26 -> 0.022107528 | E26: =Portafolio!J26 -> 0.0014273245
A27: =Portafolio!F27 -> -0.0089290842 | B27: =Portafolio!G27 -> -0.015520182 | C27: =Portafolio!H27 -> -0.007852781 | D27: =Portafolio!I27 -> -0.015554405 | E27: =Portafolio!J27 -> -0.010862645
A28: =Portafolio!F28 -> 0.0049321571 | B28: =Portafolio!G28 -> 0.0010421744 | C28: =Portafolio!H28 -> -0.009629071 | D28: =Portafolio!I28 -> -0.012488017 | E28: =Portafolio!J28 -> -0.0072123448
A29: =Portafolio!F29 -> 0.0073532672 | B29: =Portafolio!G29 -> -0.01047125 | C29: =Portafolio!H29 -> 0.0049286703 | D29: =Portafolio!I29 -> -0.0039760898 | E29: =Portafolio!J29 -> 0.0019130568
A30: =Portafolio!F30 -> -0.02367657 | B30: =Portafolio!G30 -> -0.0082798818 | C30: =Portafolio!H30 -> -0.010433243 | D30: =Portafolio!I30 -> -0.002659513 | E30: =Portafolio!J30 -> -0.010479527
A31: =Portafolio!F31 -> -0.0089372741 | B31: =Portafolio!G31 -> -0.010313022 | C31: =Portafolio!H31 -> 0.0058476761 | D31: =Portafolio!I31 -> -0.010036916 | E31: =Portafolio!J31 -> -0.002878807
A32: =Portafolio!F32 -> 0.0015245124 | B32: =Portafolio!G32 -> -0.0025052794 | C32: =Portafolio!H32 -> 0.012339653 | D32: =Portafolio!I32 -> 0.0093709133 | E32: =Portafolio!J32 -> 0.0086209084
A33: =Portafolio!F33 -> 0.0030418118 | B33: =Portafolio!G33 -> 0.0030412832 | C33: =Portafolio!H33 -> -0.017566588 | D33: =Portafolio!I33 -> 0.00066600268 | E33: =Portafolio!J33 -> -0.0067410009
A34: =Portafolio!F34 -> 0.014726613 | B34: =Portafolio!G34 -> -0.0089718562 | C34: =Portafolio!H34 -> -0.0086567489 | D34: =Portafolio!I34 -> -0.023578125 | E34: =Portafolio!J34 -> -0.0088179369
... A254: =Portafolio!F254 -> 0.0059010398 | B254: =Portafolio!G254 -> 0.0076906422 | C254: =Portafolio!H254 -> 0.011374432 | D254: =Portafolio!I254 -> 0.013010852 | E254: =Portafolio!J254 -> 0.010660443

Sheet VaR (No-Param) 
A1: Rentabilidad
A2: =Portafolio!F2 -> r_Apple | B2: =Portafolio!G2 -> r_Coca-Cola | C2: =Portafolio!H2 -> r_JPMorgan | D2: =Portafolio!I2 -> r_AT&T | E2: =Portafolio!J2 -> Portafolio | G2: Volatilidad No parámetrica
A3: =Portafolio!F3 -> -0.014662185 | B3: =Portafolio!G3 -> 0.0021472312 | C3: =Portafolio!H3 -> -0.010441079 | D3: =Portafolio!I3 -> -0.0064035323 | E3: =Portafolio!J3 -> -0.009467057
A4: =Portafolio!F4 -> 0.0028121206 | B4: =Portafolio!G4 -> 0.0055939922 | C4: =Portafolio!H4 -> 0.0022848848 | D4: =Portafolio!I4 -> 0.0028511962 | E4: =Portafolio!J4 -> 0.0027076334
A5: =Portafolio!F5 -> 0.00770704 | B5: =Portafolio!G5 -> -0.0085681807 | C5: =Portafolio!H5 -> 0.0034177361 | D5: =Portafolio!I5 -> 0.0035523361 | E5: =Portafolio!J5 -> 0.0038265778 | G5: Activos | H5: =A2 -> r_Apple | I5: =B2 -> r_Coca-Cola | J5: =C2 -> r_JPMorgan | K5: =D2 -> r_AT&T | L5: =E2 -> Portafolio
A6: =Portafolio!F6 -> 0.0078738144 | B6: =Portafolio!G6 -> -0.0061416255 | C6: =Portafolio!H6 -> -0.020956622 | D6: =Portafolio!I6 -> 0.011283651 | E6: =Portafolio!J6 -> -0.004214152 | G6: percentíl 5% | H6: =_xlfn.PERCENTILE.INC(A3:A254,1-$H$8) -> -0.022730961 | I6: =_xlfn.PERCENTILE.INC(B3:B254,1-$H$8) -> -0.010745168 | J6: =_xlfn.PERCENTILE.INC(C3:C254,1-$H$8) -> -0.014154741 | K6: =_xlfn.PERCENTILE.INC(D3:D254,1-$H$8) -> -0.018590929 | L6: =_xlfn.PERCENTILE.INC(E3:E254,1-$H$8) -> -0.011444323
A7: =Portafolio!F7 -> 0.02171154 | B7: =Portafolio!G7 -> 0.0034904215 | C7: =Portafolio!H7 -> 0.0067403655 | D7: =Portafolio!I7 -> -0.0070373474 | E7: =Portafolio!J7 -> 0.0051511975 | G7: t día(s) | H7: 1
A8: =Portafolio!F8 -> -0.026519109 | B8: =Portafolio!G8 -> -0.0026582344 | C8: =Portafolio!H8 -> -0.00095044775 | D8: =Portafolio!I8 -> -0.00070654177 | E8: =Portafolio!J8 -> -0.0060379501 | G8: Nivel de Confianza | H8: 0.95
A9: =Portafolio!F9 -> 0.012564053 | B9: =Portafolio!G9 -> 0.0046472363 | C9: =Portafolio!H9 -> -0.0012233202 | D9: =Portafolio!I9 -> -0.0028308668 | E9: =Portafolio!J9 -> 0.0012464294
A10: =Portafolio!F10 -> 0.0088072128 | B10: =Portafolio!G10 -> 0.0028110715 | C10: =Portafolio!H10 -> 0.0034622836 | D10: =Portafolio!I10 -> 0.0070621976 | E10: =Portafolio!J10 -> 0.0056612861
A11: =Portafolio!F11 -> 0.021575763 | B11: =Portafolio!G11 -> -0.00099121473 | C11: =Portafolio!H11 -> 0.0080993211 | D11: =Portafolio!I11 -> 0.038652124 | E11: =Portafolio!J11 -> 0.020261285 | G11: No-Diversificado
A12: =Portafolio!F12 -> 0.018990782 | B12: =Portafolio!G12 -> -0.00049597605 | C12: =Portafolio!H12 -> -0.0040415126 | D12: =Portafolio!I12 -> -0.0027118018 | E12: =Portafolio!J12 -> 0.0011226617 | G12: VaR Diario 95% (%) | H12: =-(H6*SQRT($H$7)) -> 0.022730961 | I12: =-(I6*SQRT($H$7)) -> 0.010745168 | J12: =-(J6*SQRT($H$7)) -> 0.014154741 | K12: =-(K6*SQRT($H$7)) -> 0.018590929
A13: =Portafolio!F13 -> 0.0011717517 | B13: =Portafolio!G13 -> -0.01064012 | C13: =Portafolio!H13 -> -0.012428386 | D13: =Portafolio!I13 -> 0.0040649861 | E13: =Portafolio!J13 -> -0.0043288022 | G13: Exposición ($) | H13: 100000
A14: =Portafolio!F14 -> 0.0084277858 | B14: =Portafolio!G14 -> -0.008729346 | C14: =Portafolio!H14 -> 0.003343024 | D14: =Portafolio!I14 -> -0.0095109703 | E14: =Portafolio!J14 -> -0.00027929642 | G14: Perdida ($) al 95% | H14: =SUM(H12:K12)*H13 -> 6622.18
A15: =Portafolio!F15 -> 0.0012659132 | B15: =Portafolio!G15 -> -0.0082960032 | C15: =Portafolio!H15 -> -0.011095406 | D15: =Portafolio!I15 -> -0.011671911 | E15: =Portafolio!J15 -> -0.0087030184
A16: =Portafolio!F16 -> -0.036449648 | B16: =Portafolio!G16 -> -0.00068026368 | C16: =Portafolio!H16 -> -0.0016539663 | D16: =Portafolio!I16 -> 0.0089378657 | E16: =Portafolio!J16 -> -0.0051359948 | G16: Diversificado
A17: =Portafolio!F17 -> -0.029685687 | B17: =Portafolio!G17 -> -0.0076850863 | C17: =Portafolio!H17 -> -0.0085911179 | D17: =Portafolio!I17 -> 0 | E17: =Portafolio!J17 -> -0.0099898157 | G17: VaR Diario 95% (%) | H17: =-(SQRT($H$7)*$L$6) -> 0.011444323
A18: =Portafolio!F18 -> 0.0034855737 | B18: =Portafolio!G18 -> 0 | C18: =Portafolio!H18 -> 0.00076518324 | D18: =Portafolio!I18 -> -0.014477989 | E18: =Portafolio!J18 -> -0.0036366612 | G18: Exposición ($) | H18: 100000
A19: =Portafolio!F19 -> 0.006600704 | B19: =Portafolio!G19 -> 0.0093849136 | C19: =Portafolio!H19 -> 0.0043706423 | D19: =Portafolio!I19 -> 0.0082988273 | E19: =Portafolio!J19 -> 0.0062859574 | G19: Perdida ($) al 95% | H19: =H17*H18 -> 1144.4323
A20: =Portafolio!F20 -> -0.017207767 | B20: =Portafolio!G20 -> -0.0098994166 | C20: =Portafolio!H20 -> 0.012930049 | D20: =Portafolio!I20 -> -0.0041408788 | E20: =Portafolio!J20 -> 0.00048872381
A21: =Portafolio!F21 -> -0.011925629 | B21: =Portafolio!G21 -> 0.0023984991 | C21: =Portafolio!H21 -> 0.00047822692 | D21: =Portafolio!I21 -> 0.011004271 | E21: =Portafolio!J21 -> 0.0014768109 | G21: Beneficio Diversificación | H21: =H14-H19 -> 5477.7477
A22: =Portafolio!F22 -> 0.0087441923 | B22: =Portafolio!G22 -> 0.0082446925 | C22: =Portafolio!H22 -> 0.019211775 | D22: =Portafolio!I22 -> 0.029651714 | E22: =Portafolio!J22 -> 0.020042246 | G22: Beneficio Diversificación | H22: =1-(H17/H12) -> 0.49653149
A23: =Portafolio!F23 -> -0.0041626265 | B23: =Portafolio!G23 -> -0.0089348416 | C23: =Portafolio!H23 -> -0.0029524998 | D23: =Portafolio!I23 -> 0.011224979 | E23: =Portafolio!J23 -> 0.001131343
A24: =Portafolio!F24 -> 0.016771886 | B24: =Portafolio!G24 -> 0.0061940864 | C24: =Portafolio!H24 -> 0.0020810602 | D24: =Portafolio!I24 -> -0.0092349221 | E24: =Portafolio!J24 -> 0.0015301137
A25: =Portafolio!F25 -> 0.006161829 | B25: =Portafolio!G25 -> -0.0020603885 | C25: =Portafolio!H25 -> -0.0012750275 | D25: =Portafolio!I25 -> 0.0079209278 | E25: =Portafolio!J25 -> 0.0031390479
A26: =Portafolio!F26 -> -0.02019469 | B26: =Portafolio!G26 -> 0.0044589358 | C26: =Portafolio!H26 -> -0.0042389693 | D26: =Portafolio!I26 -> 0.022107528 | E26: =Portafolio!J26 -> 0.0014273245
A27: =Portafolio!F27 -> -0.0089290842 | B27: =Portafolio!G27 -> -0.015520182 | C27: =Portafolio!H27 -> -0.007852781 | D27: =Portafolio!I27 -> -0.015554405 | E27: =Portafolio!J27 -> -0.010862645
A28: =Portafolio!F28 -> 0.0049321571 | B28: =Portafolio!G28 -> 0.0010421744 | C28: =Portafolio!H28 -> -0.009629071 | D28: =Portafolio!I28 -> -0.012488017 | E28: =Portafolio!J28 -> -0.0072123448
A29: =Portafolio!F29 -> 0.0073532672 | B29: =Portafolio!G29 -> -0.01047125 | C29: =Portafolio!H29 -> 0.0049286703 | D29: =Portafolio!I29 -> -0.0039760898 | E29: =Portafolio!J29 -> 0.0019130568
A30: =Portafolio!F30 -> -0.02367657 | B30: =Portafolio!G30 -> -0.0082798818 | C30: =Portafolio!H30 -> -0.010433243 | D30: =Portafolio!I30 -> -0.002659513 | E30: =Portafolio!J30 -> -0.010479527
A31: =Portafolio!F31 -> -0.0089372741 | B31: =Portafolio!G31 -> -0.010313022 | C31: =Portafolio!H31 -> 0.0058476761 | D31: =Portafolio!I31 -> -0.010036916 | E31: =Portafolio!J31 -> -0.002878807
A32: =Portafolio!F32 -> 0.0015245124 | B32: =Portafolio!G32 -> -0.0025052794 | C32: =Portafolio!H32 -> 0.012339653 | D32: =Portafolio!I32 -> 0.0093709133 | E32: =Portafolio!J32 -> 0.0086209084
A33: =Portafolio!F33 -> 0.0030418118 | B33: =Portafolio!G33 -> 0.0030412832 | C33: =Portafolio!H33 -> -0.017566588 | D33: =Portafolio!I33 -> 0.00066600268 | E33: =Portafolio!J33 -> -0.0067410009
A34: =Portafolio!F34 -> 0.014726613 | B34: =Portafolio!G34 -> -0.0089718562 | C34: =Portafolio!H34 -> -0.0086567489 | D34: =Portafolio!I34 -> -0.023578125 | E34: =Portafolio!J34 -> -0.0088179369
... A254: =Portafolio!F254 -> 0.0059010398 | B254: =Portafolio!G254 -> 0.0076906422 | C254: =Portafolio!H254 -> 0.011374432 | D254: =Portafolio!I254 -> 0.013010852 | E254: =Portafolio!J254 -> 0.010660443

Sheet VaR (Montecarlos)
A1: Rentabilidad
A2: =Portafolio!F2 -> r_Apple | B2: =Portafolio!G2 -> r_Coca-Cola | C2: =Portafolio!H2 -> r_JPMorgan | D2: =Portafolio!I2 -> r_AT&T | E2: =Portafolio!J2 -> Portafolio | G2: Volatilidad Simulación Montecarlos
A3: =Portafolio!F3 -> -0.014662185 | B3: =Portafolio!G3 -> 0.0021472312 | C3: =Portafolio!H3 -> -0.010441079 | D3: =Portafolio!I3 -> -0.0064035323 | E3: =Portafolio!J3 -> -0.009467057
A4: =Portafolio!F4 -> 0.0028121206 | B4: =Portafolio!G4 -> 0.0055939922 | C4: =Portafolio!H4 -> 0.0022848848 | D4: =Portafolio!I4 -> 0.0028511962 | E4: =Portafolio!J4 -> 0.0027076334
A5: =Portafolio!F5 -> 0.00770704 | B5: =Portafolio!G5 -> -0.0085681807 | C5: =Portafolio!H5 -> 0.0034177361 | D5: =Portafolio!I5 -> 0.0035523361 | E5: =Portafolio!J5 -> 0.0038265778 | G5: Activos | H5: =A2 -> r_Apple | I5: =B2 -> r_Coca-Cola | J5: =C2 -> r_JPMorgan | K5: =D2 -> r_AT&T | L5: =E2 -> Portafolio
A6: =Portafolio!F6 -> 0.0078738144 | B6: =Portafolio!G6 -> -0.0061416255 | C6: =Portafolio!H6 -> -0.020956622 | D6: =Portafolio!I6 -> 0.011283651 | E6: =Portafolio!J6 -> -0.004214152 | G6: entrada | H6: 0.0010005668 | I6: 0.00065844829 | J6: 0.0015030786
A7: =Portafolio!F7 -> 0.02171154 | B7: =Portafolio!G7 -> 0.0034904215 | C7: =Portafolio!H7 -> 0.0067403655 | D7: =Portafolio!I7 -> -0.0070373474 | E7: =Portafolio!J7 -> 0.0051511975 | G7: salida | H7: =H6 -> 0.0010005668 | I7: =I6 -> 0.00065844829 | J7: =J6 -> 0.0015030786 | K7: =K6 -> 0 | L7: =L6 -> 0
A8: =Portafolio!F8 -> -0.026519109 | B8: =Portafolio!G8 -> -0.0026582344 | C8: =Portafolio!H8 -> -0.00095044775 | D8: =Portafolio!I8 -> -0.00070654177 | E8: =Portafolio!J8 -> -0.0060379501 | G8: t día(s) | H8: 1
A9: =Portafolio!F9 -> 0.012564053 | B9: =Portafolio!G9 -> 0.0046472363 | C9: =Portafolio!H9 -> -0.0012233202 | D9: =Portafolio!I9 -> -0.0028308668 | E9: =Portafolio!J9 -> 0.0012464294
A10: =Portafolio!F10 -> 0.0088072128 | B10: =Portafolio!G10 -> 0.0028110715 | C10: =Portafolio!H10 -> 0.0034622836 | D10: =Portafolio!I10 -> 0.0070621976 | E10: =Portafolio!J10 -> 0.0056612861
A11: =Portafolio!F11 -> 0.021575763 | B11: =Portafolio!G11 -> -0.00099121473 | C11: =Portafolio!H11 -> 0.0080993211 | D11: =Portafolio!I11 -> 0.038652124 | E11: =Portafolio!J11 -> 0.020261285 | G11: No-Diversificado
A12: =Portafolio!F12 -> 0.018990782 | B12: =Portafolio!G12 -> -0.00049597605 | C12: =Portafolio!H12 -> -0.0040415126 | D12: =Portafolio!I12 -> -0.0027118018 | E12: =Portafolio!J12 -> 0.0011226617 | G12: VaR Diario 95% (%) | H12: {=_xll.ROV.RiskSim.RSFunctions.RSForecastStatistic(H7,"Percentile0.05")*SQRT($H$8)} -> -0.018754889 | I12: {=_xll.ROV.RiskSim.RSFunctions.RSForecastStatistic(I7,"Percentile0.05")*SQRT($H$8)} -> -0.013878689 | J12: {=_xll.ROV.RiskSim.RSFunctions.RSForecastStatistic(J7,"Percentile0.05")*SQRT($H$8)} -> -0.015062499 | K12: {=_xll.ROV.RiskSim.RSFunctions.RSForecastStatistic(K7,"Percentile0.05")*SQRT($H$8)} -> -0.019501455
A13: =Portafolio!F13 -> 0.0011717517 | B13: =Portafolio!G13 -> -0.01064012 | C13: =Portafolio!H13 -> -0.012428386 | D13: =Portafolio!I13 -> 0.0040649861 | E13: =Portafolio!J13 -> -0.0043288022 | G13: Exposición ($) | H13: 100000
A14: =Portafolio!F14 -> 0.0084277858 | B14: =Portafolio!G14 -> -0.008729346 | C14: =Portafolio!H14 -> 0.003343024 | D14: =Portafolio!I14 -> -0.0095109703 | E14: =Portafolio!J14 -> -0.00027929642 | G14: Perdida ($) al 95% | H14: =SUM(H12:K12)*H13 -> -6719.7532
A15: =Portafolio!F15 -> 0.0012659132 | B15: =Portafolio!G15 -> -0.0082960032 | C15: =Portafolio!H15 -> -0.011095406 | D15: =Portafolio!I15 -> -0.011671911 | E15: =Portafolio!J15 -> -0.0087030184
A16: =Portafolio!F16 -> -0.036449648 | B16: =Portafolio!G16 -> -0.00068026368 | C16: =Portafolio!H16 -> -0.0016539663 | D16: =Portafolio!I16 -> 0.0089378657 | E16: =Portafolio!J16 -> -0.0051359948 | G16: Diversificado
A17: =Portafolio!F17 -> -0.029685687 | B17: =Portafolio!G17 -> -0.0076850863 | C17: =Portafolio!H17 -> -0.0085911179 | D17: =Portafolio!I17 -> 0 | E17: =Portafolio!J17 -> -0.0099898157 | G17: VaR Diario 95% (%) | H17: {=_xll.ROV.RiskSim.RSFunctions.RSForecastStatistic(L7,"Percentile0.05")*SQRT($H$8)} -> -0.010906381
A18: =Portafolio!F18 -> 0.0034855737 | B18: =Portafolio!G18 -> 0 | C18: =Portafolio!H18 -> 0.00076518324 | D18: =Portafolio!I18 -> -0.014477989 | E18: =Portafolio!J18 -> -0.0036366612 | G18: Exposición ($) | H18: 100000
A19: =Portafolio!F19 -> 0.006600704 | B19: =Portafolio!G19 -> 0.0093849136 | C19: =Portafolio!H19 -> 0.0043706423 | D19: =Portafolio!I19 -> 0.0082988273 | E19: =Portafolio!J19 -> 0.0062859574 | G19: Perdida ($) al 95% | H19: =H17*H18 -> -1090.6381
A20: =Portafolio!F20 -> -0.017207767 | B20: =Portafolio!G20 -> -0.0098994166 | C20: =Portafolio!H20 -> 0.012930049 | D20: =Portafolio!I20 -> -0.0041408788 | E20: =Portafolio!J20 -> 0.00048872381
A21: =Portafolio!F21 -> -0.011925629 | B21: =Portafolio!G21 -> 0.0023984991 | C21: =Portafolio!H21 -> 0.00047822692 | D21: =Portafolio!I21 -> 0.011004271 | E21: =Portafolio!J21 -> 0.0014768109 | G21: Beneficio Diversificación | H21: =H14-H19 -> -5629.1152
A22: =Portafolio!F22 -> 0.0087441923 | B22: =Portafolio!G22 -> 0.0082446925 | C22: =Portafolio!H22 -> 0.019211775 | D22: =Portafolio!I22 -> 0.029651714 | E22: =Portafolio!J22 -> 0.020042246 | G22: Beneficio Diversificación | H22: =1-(H17/H12) -> 0.41847801
A23: =Portafolio!F23 -> -0.0041626265 | B23: =Portafolio!G23 -> -0.0089348416 | C23: =Portafolio!H23 -> -0.0029524998 | D23: =Portafolio!I23 -> 0.011224979 | E23: =Portafolio!J23 -> 0.001131343
A24: =Portafolio!F24 -> 0.016771886 | B24: =Portafolio!G24 -> 0.0061940864 | C24: =Portafolio!H24 -> 0.0020810602 | D24: =Portafolio!I24 -> -0.0092349221 | E24: =Portafolio!J24 -> 0.0015301137
A25: =Portafolio!F25 -> 0.006161829 | B25: =Portafolio!G25 -> -0.0020603885 | C25: =Portafolio!H25 -> -0.0012750275 | D25: =Portafolio!I25 -> 0.0079209278 | E25: =Portafolio!J25 -> 0.0031390479
A26: =Portafolio!F26 -> -0.02019469 | B26: =Portafolio!G26 -> 0.0044589358 | C26: =Portafolio!H26 -> -0.0042389693 | D26: =Portafolio!I26 -> 0.022107528 | E26: =Portafolio!J26 -> 0.0014273245
A27: =Portafolio!F27 -> -0.0089290842 | B27: =Portafolio!G27 -> -0.015520182 | C27: =Portafolio!H27 -> -0.007852781 | D27: =Portafolio!I27 -> -0.015554405 | E27: =Portafolio!J27 -> -0.010862645
A28: =Portafolio!F28 -> 0.0049321571 | B28: =Portafolio!G28 -> 0.0010421744 | C28: =Portafolio!H28 -> -0.009629071 | D28: =Portafolio!I28 -> -0.012488017 | E28: =Portafolio!J28 -> -0.0072123448
A29: =Portafolio!F29 -> 0.0073532672 | B29: =Portafolio!G29 -> -0.01047125 | C29: =Portafolio!H29 -> 0.0049286703 | D29: =Portafolio!I29 -> -0.0039760898 | E29: =Portafolio!J29 -> 0.0019130568
A30: =Portafolio!F30 -> -0.02367657 | B30: =Portafolio!G30 -> -0.0082798818 | C30: =Portafolio!H30 -> -0.010433243 | D30: =Portafolio!I30 -> -0.002659513 | E30: =Portafolio!J30 -> -0.010479527
A31: =Portafolio!F31 -> -0.0089372741 | B31: =Portafolio!G31 -> -0.010313022 | C31: =Portafolio!H31 -> 0.0058476761 | D31: =Portafolio!I31 -> -0.010036916 | E31: =Portafolio!J31 -> -0.002878807
A32: =Portafolio!F32 -> 0.0015245124 | B32: =Portafolio!G32 -> -0.0025052794 | C32: =Portafolio!H32 -> 0.012339653 | D32: =Portafolio!I32 -> 0.0093709133 | E32: =Portafolio!J32 -> 0.0086209084
A33: =Portafolio!F33 -> 0.0030418118 | B33: =Portafolio!G33 -> 0.0030412832 | C33: =Portafolio!H33 -> -0.017566588 | D33: =Portafolio!I33 -> 0.00066600268 | E33: =Portafolio!J33 -> -0.0067410009
A34: =Portafolio!F34 -> 0.014726613 | B34: =Portafolio!G34 -> -0.0089718562 | C34: =Portafolio!H34 -> -0.0086567489 | D34: =Portafolio!I34 -> -0.023578125 | E34: =Portafolio!J34 -> -0.0088179369
... A254: =Portafolio!F254 -> 0.0059010398 | B254: =Portafolio!G254 -> 0.0076906422 | C254: =Portafolio!H254 -> 0.011374432 | D254: =Portafolio!I254 -> 0.013010852 | E254: =Portafolio!J254 -> 0.010660443

Sheet Ajuste Distr. All
B1: Ajuste de Distribución de Variables Múltiples
B3: Resumen Estadístico
D5: Nombre de la Variable | E5: r_Apple | H5: Nombre de la Variable | I5: r_Coca-Cola | L5: Nombre de la Variable | M5: r_JPMorgan
D6: Mejor Supuesto Ajustado | E6: 0.0010005668 | H6: Mejor Supuesto Ajustado | I6: 0.00065844829 | L6: Mejor Supuesto Ajustado | M6: 0.0015030786
D8: Distribución Ajustada | E8: Logística | H8: Distribución Ajustada | I8: Laplace | L8: Distribución Ajustada | M8: Logística
D9: Alfa | E9: 0.0011662155 | H9: Alfa | I9: 0.00071065012 | L9: Alfa | M9: 0.0021559095
D10: Beta | E10: 0.007085894 | H10: Beta | I10: 0.0066101084 | L10: Beta | M10: 0.0058226002
D13: Estadístico Kolmogorov-Smirnov | E13: 0.036662742 | H13: Estadístico Kolmogorov-Smirnov | I13: 0.039623139 | L13: Estadístico Kolmogorov-Smirnov | M13: 0.026056959
D14: Prueba Estadística de P-Value | E14: 0.8814423 | H14: Prueba Estadística de P-Value | I14: 0.81628649 | L14: Prueba Estadística de P-Value | M14: 0.99502222
D16: Real | E16: Teórica | H16: Real | I16: Teórica | L16: Real | M16: Teórica
C17: Media | D17: 0.0010005668 | E17: 0.0011662155 | G17: Media | H17: 0.00065844829 | I17: 0.00071065012 | K17: Media | L17: 0.0015030786 | M17: 0.0021559095
C18: Desviación Estándar | D18: 0.014317007 | E18: 0.01285239 | G18: Desviación Estándar | H18: 0.0084145555 | I18: 0.0093481049 | K18: Desviación Estándar | L18: 0.011640823 | M18: 0.010561029
C19: Asimetría | D19: 0.26385726 | E19: 0 | G19: Asimetría | H19: -0.51847268 | I19: 0 | K19: Asimetría | L19: -1.4361975 | M19: 0
C20: Curtosis | D20: 3.1993752 | E20: 1.2 | G20: Curtosis | H20: 5.0354703 | I20: 3 | K20: Curtosis | L20: 5.9450521 | M20: 1.2
D23: Nombre de la Variable | E23: r_AT&T | H23: Nombre de la Variable | I23: Portafolio
D24: Mejor Supuesto Ajustado | E24: 0.0015168662 | H24: Mejor Supuesto Ajustado | I24: 0.0013728677
D26: Distribución Ajustada | E26: Logística | H26: Distribución Ajustada | I26: Logística
D27: Alfa | E27: 0.0011863003 | H27: Alfa | I27: 0.0016732413
D28: Beta | E28: 0.0070112117 | H28: Beta | I28: 0.0044005701
D31: Estadístico Kolmogorov-Smirnov | E31: 0.021326251 | H31: Estadístico Kolmogorov-Smirnov | I31: 0.029193076
D32: Prueba Estadística de P-Value | E32: 0.99981589 | H32: Prueba Estadística de P-Value | I32: 0.98119453
D34: Real | E34: Teórica | H34: Real | I34: Teórica
C35: Media | D35: 0.0015168662 | E35: 0.0011863003 | G35: Media | H35: 0.0013728677 | I35: 0.0016732413
C36: Desviación Estándar | D36: 0.013397541 | E36: 0.012716931 | G36: Desviación Estándar | H36: 0.0079881271 | I36: 0.0079817513
C37: Asimetría | D37: 0.55654666 | E37: 0 | G37: Asimetría | H37: -0.47644938 | I37: 0
C38: Curtosis | D38: 2.3858239 | E38: 1.2 | G38: Curtosis | H38: 1.1779333 | I38: 1.2
B40: Matriz de Correlación
C42: r_Apple | D42: r_Coca-Cola | E42: r_JPMorgan | F42: r_AT&T | G42: Portafolio
B43: r_Apple | C43: 1
B44: r_Coca-Cola | C44: 0.092908388 | D44: 1
B45: r_JPMorgan | C45: 0.047823405 | D45: 0.18624002 | E45: 1
B46: r_AT&T | C46: -0.019839153 | D46: 0.34877913 | E46: 0.18621074 | F46: 1
B47: Portafolio | C47: 0.38100582 | D47: 0.38349178 | E47: 0.76336989 | F47: 0.66719824 | G47: 1

Sheet VaR (GARCH)
A1: Fecha | B1: Apple | C1: Coca-Cola | D1: JPMorgan | E1: AT&T | F1: Portafolio | G1: Rentabilidad
A2: 45154 | B2: 175.67108 | C2: 58.602821 | D2: 146.50507 | E2: 13.196151 | F2: =SUMPRODUCT(Portafolio!B2:E2,Portafolio!$M$37:$P$37) -> 105.76362 | G2: =Portafolio!F2 -> r_Apple | H2: =Portafolio!G2 -> r_Coca-Cola | I2: =Portafolio!H2 -> r_JPMorgan | J2: =Portafolio!I2 -> r_AT&T | K2: =Portafolio!J2 -> Portafolio | M2: Volatilidad Simulación Montecarlos
A3: 45155 | B3: 173.11415 | C3: 58.72879 | D3: 144.98335 | E3: 13.111919 | F3: =SUMPRODUCT(Portafolio!B3:E3,Portafolio!$M$37:$P$37) -> 104.56615 | G3: =Portafolio!F3 -> -0.014662185 | H3: =Portafolio!G3 -> 0.0021472312 | I3: =Portafolio!H3 -> -0.010441079 | J3: =Portafolio!I3 -> -0.0064035323 | K3: =Portafolio!J3 -> -0.009467057
A4: 45156 | B4: 173.60165 | C4: 59.058239 | D4: 145.315 | E4: 13.149357 | F4: =SUMPRODUCT(Portafolio!B4:E4,Portafolio!$M$37:$P$37) -> 104.83395 | G4: =Portafolio!F4 -> 0.0028121206 | H4: =Portafolio!G4 -> 0.0055939922 | I4: =Portafolio!H4 -> 0.0022848848 | J4: =Portafolio!I4 -> 0.0028511962 | K4: =Portafolio!J4 -> 0.0027076334
A5: 45159 | B5: 174.94478 | C5: 58.554379 | D5: 145.8125 | E5: 13.196151 | F5: =SUMPRODUCT(Portafolio!B5:E5,Portafolio!$M$37:$P$37) -> 105.31385 | G5: =Portafolio!F5 -> 0.00770704 | H5: =Portafolio!G5 -> -0.0085681807 | I5: =Portafolio!H5 -> 0.0034177361 | J5: =Portafolio!I5 -> 0.0035523361 | K5: =Portafolio!J5 -> 0.0038265778 | M5: Activos | N5: =G2 -> r_Apple | O5: =H2 -> r_Coca-Cola | P5: =I2 -> r_JPMorgan | Q5: =J2 -> r_AT&T | R5: =K2 -> Portafolio
A6: 45160 | B6: 176.3277 | C6: 58.195862 | D6: 142.78856 | E6: 13.345895 | F6: =SUMPRODUCT(Portafolio!B6:E6,Portafolio!$M$37:$P$37) -> 104.30001 | G6: =Portafolio!F6 -> 0.0078738144 | H6: =Portafolio!G6 -> -0.0061416255 | I6: =Portafolio!H6 -> -0.020956622 | J6: =Portafolio!I6 -> 0.011283651 | K6: =Portafolio!J6 -> -0.004214152 | M6: GARCH(1,1) | N6: ='GARCH-Apple'!D$270*SQRT(1/252) -> 0.014318456 | O6: ='GARCH-CC'!$D$270*SQRT(1/252) -> 0.0082348977 | P6: ='GARCH-JPMorgan'!D270*SQRT(1/252) -> 0.014116495 | Q6: ='GARCH-AT&T'!$D$270*SQRT(1/252) -> 0.014435525 | R6: ='GARCH-Portafolio'!$D$270*SQRT(1/252) -> 0.0088504911
A7: 45161 | B7: 180.19791 | C7: 58.399345 | D7: 143.75426 | E7: 13.252305 | F7: =SUMPRODUCT(Portafolio!B7:E7,Portafolio!$M$37:$P$37) -> 105.4721 | G7: =Portafolio!F7 -> 0.02171154 | H7: =Portafolio!G7 -> 0.0034904215 | I7: =Portafolio!H7 -> 0.0067403655 | J7: =Portafolio!I7 -> -0.0070373474 | K7: =Portafolio!J7 -> 0.0051511975 | M7: t día(s) | N7: 1
A8: 45162 | B8: 175.48202 | C8: 58.244312 | D8: 143.61769 | E8: 13.242945 | F8: =SUMPRODUCT(Portafolio!B8:E8,Portafolio!$M$37:$P$37) -> 104.46303 | G8: =Portafolio!F8 -> -0.026519109 | H8: =Portafolio!G8 -> -0.0026582344 | I8: =Portafolio!H8 -> -0.00095044775 | J8: =Portafolio!I8 -> -0.00070654177 | K8: =Portafolio!J8 -> -0.0060379501 | M8: Nivel de Confianza | N8: 0.95
A9: 45163 | B9: 177.7007 | C9: 58.515617 | D9: 143.44211 | E9: 13.205509 | F9: =SUMPRODUCT(Portafolio!B9:E9,Portafolio!$M$37:$P$37) -> 104.82744 | G9: =Portafolio!F9 -> 0.012564053 | H9: =Portafolio!G9 -> 0.0046472363 | I9: =Portafolio!H9 -> -0.0012233202 | J9: =Portafolio!I9 -> -0.0028308668 | K9: =Portafolio!J9 -> 0.0012464294 | M9: Normal Estandar | N9: =NORMSINV(N8) -> 1.6448536
A10: 45166 | B10: 179.27266 | C10: 58.68034 | D10: 143.93961 | E10: 13.299099 | F10: =SUMPRODUCT(Portafolio!B10:E10,Portafolio!$M$37:$P$37) -> 105.39534 | G10: =Portafolio!F10 -> 0.0088072128 | H10: =Portafolio!G10 -> 0.0028110715 | I10: =Portafolio!H10 -> 0.0034622836 | J10: =Portafolio!I10 -> 0.0070621976 | K10: =Portafolio!J10 -> 0.0056612861
A11: 45167 | B11: 183.18263 | C11: 58.622204 | D11: 145.11015 | E11: 13.823201 | F11: =SUMPRODUCT(Portafolio!B11:E11,Portafolio!$M$37:$P$37) -> 106.85338 | G11: =Portafolio!F11 -> 0.021575763 | H11: =Portafolio!G11 -> -0.00099121473 | I11: =Portafolio!H11 -> 0.0080993211 | J11: =Portafolio!I11 -> 0.038652124 | K11: =Portafolio!J11 -> 0.020261285 | M11: No-Diversificado
A12: 45168 | B12: 186.69466 | C12: 58.593136 | D12: 144.52487 | E12: 13.785766 | F12: =SUMPRODUCT(Portafolio!B12:E12,Portafolio!$M$37:$P$37) -> 107.28406 | G12: =Portafolio!F12 -> 0.018990782 | H12: =Portafolio!G12 -> -0.00049597605 | I12: =Portafolio!H12 -> -0.0040415126 | J12: =Portafolio!I12 -> -0.0027118018 | K12: =Portafolio!J12 -> 0.0011226617 | M12: VaR Diario 95% (%) | N12: =+N6*SQRT($N$7)*$N$9 -> 0.023551764 | O12: =+O6*SQRT($N$7)*$N$9 -> 0.013545201 | P12: =+P6*SQRT($N$7)*$N$9 -> 0.023219567 | Q12: =+Q6*SQRT($N$7)*$N$9 -> 0.023744326
A13: 45169 | B13: 186.91354 | C13: 57.973003 | D13: 142.73978 | E13: 13.841919 | F13: =SUMPRODUCT(Portafolio!B13:E13,Portafolio!$M$37:$P$37) -> 106.53941 | G13: =Portafolio!F13 -> 0.0011717517 | H13: =Portafolio!G13 -> -0.01064012 | I13: =Portafolio!H13 -> -0.012428386 | J13: =Portafolio!I13 -> 0.0040649861 | K13: =Portafolio!J13 -> -0.0043288022 | M13: Exposición ($) | N13: 100000
A14: 45170 | B14: 188.49547 | C14: 57.469139 | D14: 143.21776 | E14: 13.710893 | F14: =SUMPRODUCT(Portafolio!B14:E14,Portafolio!$M$37:$P$37) -> 107.00105 | G14: =Portafolio!F14 -> 0.0084277858 | H14: =Portafolio!G14 -> -0.008729346 | I14: =Portafolio!H14 -> 0.003343024 | J14: =Portafolio!I14 -> -0.0095109703 | K14: =Portafolio!J14 -> -0.00027929642 | M14: Perdida ($) al 95% | N14: =SUM(N12:Q12)*N13 -> 8406.0858
A15: 45174 | B15: 188.73424 | C15: 56.994347 | D15: 141.63748 | E15: 13.551791 | F15: =SUMPRODUCT(Portafolio!B15:E15,Portafolio!$M$37:$P$37) -> 106.28653 | G15: =Portafolio!F15 -> 0.0012659132 | H15: =Portafolio!G15 -> -0.0082960032 | I15: =Portafolio!H15 -> -0.011095406 | J15: =Portafolio!I15 -> -0.011671911 | K15: =Portafolio!J15 -> -0.0087030184
A16: 45175 | B16: 181.97881 | C16: 56.955589 | D16: 141.40341 | E16: 13.673458 | F16: =SUMPRODUCT(Portafolio!B16:E16,Portafolio!$M$37:$P$37) -> 104.87525 | G16: =Portafolio!F16 -> -0.036449648 | H16: =Portafolio!G16 -> -0.00068026368 | I16: =Portafolio!H16 -> -0.0016539663 | J16: =Portafolio!I16 -> 0.0089378657 | K16: =Portafolio!J16 -> -0.0051359948 | M16: Diversificado
A17: 45176 | B17: 176.65604 | C17: 56.519558 | D17: 140.1938 | E17: 13.673458 | F17: =SUMPRODUCT(Portafolio!B17:E17,Portafolio!$M$37:$P$37) -> 103.26725 | G17: =Portafolio!F17 -> -0.029685687 | H17: =Portafolio!G17 -> -0.0076850863 | I17: =Portafolio!H17 -> -0.0085911179 | J17: =Portafolio!I17 -> 0 | K17: =Portafolio!J17 -> -0.0099898157 | M17: VaR Diario 95% (%) | N17: =+R6*SQRT($N$7)*N9 -> 0.014557762
A18: 45177 | B18: 177.27286 | C18: 56.519558 | D18: 140.30112 | E18: 13.47692 | F18: =SUMPRODUCT(Portafolio!B18:E18,Portafolio!$M$37:$P$37) -> 103.3738 | G18: =Portafolio!F18 -> 0.0034855737 | H18: =Portafolio!G18 -> 0 | I18: =Portafolio!H18 -> 0.00076518324 | J18: =Portafolio!I18 -> -0.014477989 | K18: =Portafolio!J18 -> -0.0036366612 | M18: Exposición ($) | N18: 100000
A19: 45180 | B19: 178.44685 | C19: 57.052486 | D19: 140.91566 | E19: 13.589228 | F19: =SUMPRODUCT(Portafolio!B19:E19,Portafolio!$M$37:$P$37) -> 103.93466 | G19: =Portafolio!F19 -> 0.006600704 | H19: =Portafolio!G19 -> 0.0093849136 | I19: =Portafolio!H19 -> 0.0043706423 | J19: =Portafolio!I19 -> 0.0082988273 | K19: =Portafolio!J19 -> 0.0062859574 | M19: Perdida ($) al 95% | N19: =N17*N18 -> 1455.7762
A20: 45181 | B20: 175.40245 | C20: 56.490486 | D20: 142.74954 | E20: 13.533073 | F20: =SUMPRODUCT(Portafolio!B20:E20,Portafolio!$M$37:$P$37) -> 104.0892 | G20: =Portafolio!F20 -> -0.017207767 | H20: =Portafolio!G20 -> -0.0098994166 | I20: =Portafolio!H20 -> 0.012930049 | J20: =Portafolio!I20 -> -0.0041408788 | K20: =Portafolio!J20 -> 0.00048872381
A21: 45182 | B21: 173.32309 | C21: 56.626141 | D21: 142.81782 | E21: 13.682817 | F21: =SUMPRODUCT(Portafolio!B21:E21,Portafolio!$M$37:$P$37) -> 103.75841 | G21: =Portafolio!F21 -> -0.011925629 | H21: =Portafolio!G21 -> 0.0023984991 | I21: =Portafolio!H21 -> 0.00047822692 | J21: =Portafolio!I21 -> 0.011004271 | K21: =Portafolio!J21 -> 0.0014768109 | M21: Beneficio Diversificación | N21: =N14-N19 -> 6950.3096
A22: 45183 | B22: 174.84531 | C22: 57.094936 | D22: 145.58813 | E22: 14.094611 | F22: =SUMPRODUCT(Portafolio!B22:E22,Portafolio!$M$37:$P$37) -> 105.42582 | G22: =Portafolio!F22 -> 0.0087441923 | H22: =Portafolio!G22 -> 0.0082446925 | I22: =Portafolio!H22 -> 0.019211775 | J22: =Portafolio!I22 -> 0.029651714 | K22: =Portafolio!J22 -> 0.020042246 | M22: Beneficio Diversificación | N22: =1-(N17/N12) -> 0.38188229
A23: 45184 | B23: 174.119 | C23: 56.587074 | D23: 145.15892 | E23: 14.253714 | F23: =SUMPRODUCT(Portafolio!B23:E23,Portafolio!$M$37:$P$37) -> 105.12379 | G23: =Portafolio!F23 -> -0.0041626265 | H23: =Portafolio!G23 -> -0.0089348416 | I23: =Portafolio!H23 -> -0.0029524998 | J23: =Portafolio!I23 -> 0.011224979 | K23: =Portafolio!J23 -> 0.001131343
A24: 45187 | B24: 177.06393 | C24: 56.938667 | D24: 145.46132 | E24: 14.122688 | F24: =SUMPRODUCT(Portafolio!B24:E24,Portafolio!$M$37:$P$37) -> 105.81522 | G24: =Portafolio!F24 -> 0.016771886 | H24: =Portafolio!G24 -> 0.0061940864 | I24: =Portafolio!H24 -> 0.0020810602 | J24: =Portafolio!I24 -> -0.0092349221 | K24: =Portafolio!J24 -> 0.0015301137
A25: 45188 | B25: 178.15834 | C25: 56.821472 | D25: 145.27597 | E25: 14.234997 | F25: =SUMPRODUCT(Portafolio!B25:E25,Portafolio!$M$37:$P$37) -> 105.98367 | G25: =Portafolio!F25 -> 0.006161829 | H25: =Portafolio!G25 -> -0.0020603885 | I25: =Portafolio!H25 -> -0.0012750275 | J25: =Portafolio!I25 -> 0.0079209278 | K25: =Portafolio!J25 -> 0.0031390479
A26: 45189 | B26: 174.59657 | C26: 57.075401 | D26: 144.66145 | E26: 14.553202 | F26: =SUMPRODUCT(Portafolio!B26:E26,Portafolio!$M$37:$P$37) -> 105.11778 | G26: =Portafolio!F26 -> -0.02019469 | H26: =Portafolio!G26 -> 0.0044589358 | I26: =Portafolio!H26 -> -0.0042389693 | J26: =Portafolio!I26 -> 0.022107528 | K26: =Portafolio!J26 -> 0.0014273245
A27: 45190 | B27: 173.04452 | C27: 56.196419 | D27: 143.52991 | E27: 14.328587 | F27: =SUMPRODUCT(Portafolio!B27:E27,Portafolio!$M$37:$P$37) -> 104.20504 | G27: =Portafolio!F27 -> -0.0089290842 | H27: =Portafolio!G27 -> -0.015520182 | I27: =Portafolio!H27 -> -0.007852781 | J27: =Portafolio!I27 -> -0.015554405 | K27: =Portafolio!J27 -> -0.010862645
A28: 45191 | B28: 173.90012 | C28: 56.255016 | D28: 142.15448 | E28: 14.150764 | F28: =SUMPRODUCT(Portafolio!B28:E28,Portafolio!$M$37:$P$37) -> 103.71885 | G28: =Portafolio!F28 -> 0.0049321571 | H28: =Portafolio!G28 -> 0.0010421744 | I28: =Portafolio!H28 -> -0.009629071 | J28: =Portafolio!I28 -> -0.012488017 | K28: =Portafolio!J28 -> -0.0072123448
A29: 45194 | B29: 175.18356 | C29: 55.669029 | D29: 142.85684 | E29: 14.094611 | F29: =SUMPRODUCT(Portafolio!B29:E29,Portafolio!$M$37:$P$37) -> 104.23995 | G29: =Portafolio!F29 -> 0.0073532672 | H29: =Portafolio!G29 -> -0.01047125 | I29: =Portafolio!H29 -> 0.0049286703 | J29: =Portafolio!I29 -> -0.0039760898 | K29: =Portafolio!J29 -> 0.0019130568
A30: 45195 | B30: 171.08453 | C30: 55.209999 | D30: 141.37413 | E30: 14.057176 | F30: =SUMPRODUCT(Portafolio!B30:E30,Portafolio!$M$37:$P$37) -> 102.74337 | G30: =Portafolio!F30 -> -0.02367657 | H30: =Portafolio!G30 -> -0.0082798818 | I30: =Portafolio!H30 -> -0.010433243 | J30: =Portafolio!I30 -> -0.002659513 | K30: =Portafolio!J30 -> -0.010479527
A31: 45196 | B31: 169.56232 | C31: 54.643543 | D31: 142.20326 | E31: 13.916791 | F31: =SUMPRODUCT(Portafolio!B31:E31,Portafolio!$M$37:$P$37) -> 102.73436 | G31: =Portafolio!F31 -> -0.0089372741 | H31: =Portafolio!G31 -> -0.010313022 | I31: =Portafolio!H31 -> 0.0058476761 | J31: =Portafolio!I31 -> -0.010036916 | K31: =Portafolio!J31 -> -0.002878807
A32: 45197 | B32: 169.82101 | C32: 54.506817 | D32: 143.96887 | E32: 14.047817 | F32: =SUMPRODUCT(Portafolio!B32:E32,Portafolio!$M$37:$P$37) -> 103.5951 | G32: =Portafolio!F32 -> 0.0015245124 | H32: =Portafolio!G32 -> -0.0025052794 | I32: =Portafolio!H32 -> 0.012339653 | J32: =Portafolio!I32 -> 0.0093709133 | K32: =Portafolio!J32 -> 0.0086209084
A33: 45198 | B33: 170.33836 | C33: 54.67284 | D33: 141.46191 | E33: 14.057176 | F33: =SUMPRODUCT(Portafolio!B33:E33,Portafolio!$M$37:$P$37) -> 102.61111 | G33: =Portafolio!F33 -> 0.0030418118 | H33: =Portafolio!G33 -> 0.0030412832 | I33: =Portafolio!H33 -> -0.017566588 | J33: =Portafolio!I33 -> 0.00066600268 | K33: =Portafolio!J33 -> -0.0067410009
A34: 45201 | B34: 172.86543 | C34: 54.184517 | D34: 140.2426 | E34: 13.729611 | F34: =SUMPRODUCT(Portafolio!B34:E34,Portafolio!$M$37:$P$37) -> 102.45579 | G34: =Portafolio!F34 -> 0.014726613 | H34: =Portafolio!G34 -> -0.0089718562 | I34: =Portafolio!H34 -> -0.0086567489 | J34: =Portafolio!I34 -> -0.023578125 | K34: =Portafolio!J34 -> -0.0088179369
... A254: 45520 | B254: 226.05 | C254: 69.18 | D254: 213.97 | E254: 19.34 | F254: =SUMPRODUCT(Portafolio!B254:E254,Portafolio!$M$37:$P$37) -> 147.73615 | G254: =Portafolio!F254 -> 0.0059010398 | H254: =Portafolio!G254 -> 0.0076906422 | I254: =Portafolio!H254 -> 0.011374432 | J254: =Portafolio!I254 -> 0.013010852 | K254: =Portafolio!J254 -> 0.010660443

Sheet GARCH-Apple
B1: GARCH: Proceso General Autorregresivo de Heterocedasticidad Condicional (Pronóstico de la Volatililidad)
B4: GARCH es un término que incorpora una familia de modelos que toman una variedad de formas de acuerdo a sus enfoques (GARCH, T-GARCH, I-GARCH, etc.); específicamente un GARCH (P,Q), es un modelo donde P y Q son enteros positivos que definen el modelo resultante; en este caso, P corresponde al rezago de la varianza condicionada y Q corresponde al rezago de los errores al cuadrado. Los procesos GARCH se utilizan principalmente para calcular la inestabilidad o volatilidad en el precio de un activo financiero, como acciones, opciones financieras, bonos; aunque este modelo también se usa también para modelar otros productos comerciales como el precio del aceite, electricidad, combustibles, productos básicos etc. En términos estadísticos un proceso GARCH busca modelar la volatilidad de la varianza, debido a que esta no es homocedastica, es decir, presenta heterocedasticidad o cambios sistemáticos en la varianza a través del tiempo. Uno de los inconvenientes para construir modelos GARCH es que se requieren muchos datos para hacer funcional el análisis, además de necesitar algo de pericia en modelación econométrica avanzada, y por tanto este enfoque es sumamente susceptible a la manipulación del usuario. El beneficio en la realización de este riguroso análisis econométrico y estadístico esta en encontrar el mejor modelo que ajuste a los datos, dada la inestabilidad de los mismos, permitiendo pronosticar la volatilidad de la varianza. En la mayoría de los casos para instrumentos financieros, un GARCH (1,1) es suficiente y es generalmente muy utilizado.
B11: GARCH Modelo (P,Q) | E11: 1,1 | G11: Periodicidad (Períodos/Año) | J11: 252
B12: Optimización Alfa | E12: 0.22094584 | G12: Base Predictiva | J12: 252
B13: Optimización Beta | E13: 0 | G13: Pronostique Períodos | J13: 1
B14: Optimización Omega | E14: 0.00015968795 | G14: Variación Targeting | J14: TRUE
B16: Período | C16: Datos | D16: Volatilidad | F16: Los modelos GARCH son generalmente usados para pronosticar la inestabilidad de instrumentos financieros al usar los precios de si mismo. Solo pueden utilizarse valores positivos para pronosticar la volatilidad en un modelo GARCH. La periodicidad es el número de periodos por año (por ejemplo, 12 para datos mensuales, 252 para días hábiles, 365 para datos diarios, etc.) Es indispensable cerciorarse de tener los valores a modelar en orden cronológico. La Base Predictiva es el número de periodos base, es decir, el número de periodos rezagados que va a usar como una base de pronóstico para predecir la volatilidad futura, se ubica típicamente entre 1 y 12. Varianza Targeting es un método de estimación que consiste en asignarle a la varianza promedio a largo plazo un valor igual a la varianza muestral. Para finalizar debe estar seguro que sus datos originales estén organizados en orden cronológico.
B17: 0 | C17: 175.67108
B18: 1 | C18: 173.11415
B19: 2 | C19: 173.60165 | D19: 0.22849743
B20: 3 | C20: 174.94478 | D20: 0.20169697
B21: 4 | C21: 176.3277 | D21: 0.20868294
B22: 5 | C22: 180.19791 | D22: 0.20902931
B23: 6 | C23: 175.48202 | D23: 0.25785196
B24: 7 | C24: 177.7007 | D24: 0.28177632
B25: 8 | C25: 179.27266 | D25: 0.2214283
B26: 9 | C26: 183.18263 | D26: 0.21109279
B27: 10 | C27: 186.69466 | D27: 0.25721662
B28: 11 | C28: 186.91354 | D28: 0.24560487
B29: 12 | C29: 188.49547 | D29: 0.20079295
B30: 13 | C30: 188.73424 | D30: 0.21022859
... B269: 252 | C269: 226.05 | D269: 0.22427334
D270: 0.22729844

Sheet GARCH-CC
B1: GARCH: Proceso General Autorregresivo de Heterocedasticidad Condicional (Pronóstico de la Volatililidad)
B4: GARCH es un término que incorpora una familia de modelos que toman una variedad de formas de acuerdo a sus enfoques (GARCH, T-GARCH, I-GARCH, etc.); específicamente un GARCH (P,Q), es un modelo donde P y Q son enteros positivos que definen el modelo resultante; en este caso, P corresponde al rezago de la varianza condicionada y Q corresponde al rezago de los errores al cuadrado. Los procesos GARCH se utilizan principalmente para calcular la inestabilidad o volatilidad en el precio de un activo financiero, como acciones, opciones financieras, bonos; aunque este modelo también se usa también para modelar otros productos comerciales como el precio del aceite, electricidad, combustibles, productos básicos etc. En términos estadísticos un proceso GARCH busca modelar la volatilidad de la varianza, debido a que esta no es homocedastica, es decir, presenta heterocedasticidad o cambios sistemáticos en la varianza a través del tiempo. Uno de los inconvenientes para construir modelos GARCH es que se requieren muchos datos para hacer funcional el análisis, además de necesitar algo de pericia en modelación econométrica avanzada, y por tanto este enfoque es sumamente susceptible a la manipulación del usuario. El beneficio en la realización de este riguroso análisis econométrico y estadístico esta en encontrar el mejor modelo que ajuste a los datos, dada la inestabilidad de los mismos, permitiendo pronosticar la volatilidad de la varianza. En la mayoría de los casos para instrumentos financieros, un GARCH (1,1) es suficiente y es generalmente muy utilizado.
B11: GARCH Modelo (P,Q) | E11: 1,1 | G11: Periodicidad (Períodos/Año) | J11: 252
B12: Optimización Alfa | E12: 0.042500729 | G12: Base Predictiva | J12: 252
B13: Optimización Beta | E13: 0.81757747 | G13: Pronostique Períodos | J13: 1
B14: Optimización Omega | E14: 9.9071272e-06 | G14: Variación Targeting | J14: TRUE
B16: Período | C16: Datos | D16: Volatilidad | F16: Los modelos GARCH son generalmente usados para pronosticar la inestabilidad de instrumentos financieros al usar los precios de si mismo. Solo pueden utilizarse valores positivos para pronosticar la volatilidad en un modelo GARCH. La periodicidad es el número de periodos por año (por ejemplo, 12 para datos mensuales, 252 para días hábiles, 365 para datos diarios, etc.) Es indispensable cerciorarse de tener los valores a modelar en orden cronológico. La Base Predictiva es el número de periodos base, es decir, el número de periodos rezagados que va a usar como una base de pronóstico para predecir la volatilidad futura, se ubica típicamente entre 1 y 12. Varianza Targeting es un método de estimación que consiste en asignarle a la varianza promedio a largo plazo un valor igual a la varianza muestral. Para finalizar debe estar seguro que sus datos originales estén organizados en orden cronológico.
B17: 0 | C17: 58.602821
B18: 1 | C18: 58.72879
B19: 2 | C19: 59.058239 | D19: 0.13089631
B20: 3 | C20: 58.554379 | D20: 0.12976899
B21: 4 | C21: 58.195862 | D21: 0.13057897
B22: 5 | C22: 58.399345 | D22: 0.12977282
B23: 6 | C23: 58.244312 | D23: 0.12804643
B24: 7 | C24: 58.515617 | D24: 0.12640089
B25: 8 | C25: 58.68034 | D25: 0.12566021
B26: 9 | C26: 58.622204 | D26: 0.12446356
B27: 10 | C27: 58.593136 | D27: 0.12317612
B28: 11 | C28: 57.973003 | D28: 0.12208115
B29: 12 | C29: 57.469139 | D29: 0.12607195
B30: 13 | C30: 56.994347 | D30: 0.12770049
... B269: 252 | C269: 69.18 | D269: 0.13007238
D270: 0.13072495

Sheet GARCH-JPMorgan
B1: GARCH: Proceso General Autorregresivo de Heterocedasticidad Condicional (Pronóstico de la Volatililidad)
B4: GARCH es un término que incorpora una familia de modelos que toman una variedad de formas de acuerdo a sus enfoques (GARCH, T-GARCH, I-GARCH, etc.); específicamente un GARCH (P,Q), es un modelo donde P y Q son enteros positivos que definen el modelo resultante; en este caso, P corresponde al rezago de la varianza condicionada y Q corresponde al rezago de los errores al cuadrado. Los procesos GARCH se utilizan principalmente para calcular la inestabilidad o volatilidad en el precio de un activo financiero, como acciones, opciones financieras, bonos; aunque este modelo también se usa también para modelar otros productos comerciales como el precio del aceite, electricidad, combustibles, productos básicos etc. En términos estadísticos un proceso GARCH busca modelar la volatilidad de la varianza, debido a que esta no es homocedastica, es decir, presenta heterocedasticidad o cambios sistemáticos en la varianza a través del tiempo. Uno de los inconvenientes para construir modelos GARCH es que se requieren muchos datos para hacer funcional el análisis, además de necesitar algo de pericia en modelación econométrica avanzada, y por tanto este enfoque es sumamente susceptible a la manipulación del usuario. El beneficio en la realización de este riguroso análisis econométrico y estadístico esta en encontrar el mejor modelo que ajuste a los datos, dada la inestabilidad de los mismos, permitiendo pronosticar la volatilidad de la varianza. En la mayoría de los casos para instrumentos financieros, un GARCH (1,1) es suficiente y es generalmente muy utilizado.
B11: GARCH Modelo (P,Q) | E11: 1,1 | G11: Periodicidad (Períodos/Año) | J11: 252
B12: Optimización Alfa | E12: 0.0056135251 | G12: Base Predictiva | J12: 252
B13: Optimización Beta | E13: 0.99438647 | G13: Pronostique Períodos | J13: 1
B14: Optimización Omega | E14: 3.3081757e-07 | G14: Variación Targeting | J14: FALSE
B16: Período | C16: Datos | D16: Volatilidad | F16: Los modelos GARCH son generalmente usados para pronosticar la inestabilidad de instrumentos financieros al usar los precios de si mismo. Solo pueden utilizarse valores positivos para pronosticar la volatilidad en un modelo GARCH. La periodicidad es el número de periodos por año (por ejemplo, 12 para datos mensuales, 252 para días hábiles, 365 para datos diarios, etc.) Es indispensable cerciorarse de tener los valores a modelar en orden cronológico. La Base Predictiva es el número de periodos base, es decir, el número de periodos rezagados que va a usar como una base de pronóstico para predecir la volatilidad futura, se ubica típicamente entre 1 y 12. Varianza Targeting es un método de estimación que consiste en asignarle a la varianza promedio a largo plazo un valor igual a la varianza muestral. Para finalizar debe estar seguro que sus datos originales estén organizados en orden cronológico.
B17: 0 | C17: 146.50507
B18: 1 | C18: 144.98335
B19: 2 | C19: 145.315 | D19: 0.18491646
B20: 3 | C20: 145.8125 | D20: 0.18464262
B21: 4 | C21: 142.78856 | D21: 0.1843947
B22: 5 | C22: 143.75426 | D22: 0.18578259
B23: 6 | C23: 143.61769 | D23: 0.18565844
B24: 7 | C24: 143.44211 | D24: 0.18536506
B25: 8 | C25: 143.93961 | D25: 0.18507514
B26: 9 | C26: 145.11015 | D26: 0.18482655
B27: 10 | C27: 144.52487 | D27: 0.18478434
B28: 11 | C28: 142.73978 | D28: 0.18455365
B29: 12 | C29: 143.21776 | D29: 0.18485325
B30: 13 | C30: 141.63748 | D30: 0.1846025
... B269: 252 | C269: 213.97 | D269: 0.22410229
D270: 0.22409241

Sheet GARCH-AT&T
B1: GARCH: Proceso General Autorregresivo de Heterocedasticidad Condicional (Pronóstico de la Volatililidad)
B4: GARCH es un término que incorpora una familia de modelos que toman una variedad de formas de acuerdo a sus enfoques (GARCH, T-GARCH, I-GARCH, etc.); específicamente un GARCH (P,Q), es un modelo donde P y Q son enteros positivos que definen el modelo resultante; en este caso, P corresponde al rezago de la varianza condicionada y Q corresponde al rezago de los errores al cuadrado. Los procesos GARCH se utilizan principalmente para calcular la inestabilidad o volatilidad en el precio de un activo financiero, como acciones, opciones financieras, bonos; aunque este modelo también se usa también para modelar otros productos comerciales como el precio del aceite, electricidad, combustibles, productos básicos etc. En términos estadísticos un proceso GARCH busca modelar la volatilidad de la varianza, debido a que esta no es homocedastica, es decir, presenta heterocedasticidad o cambios sistemáticos en la varianza a través del tiempo. Uno de los inconvenientes para construir modelos GARCH es que se requieren muchos datos para hacer funcional el análisis, además de necesitar algo de pericia en modelación econométrica avanzada, y por tanto este enfoque es sumamente susceptible a la manipulación del usuario. El beneficio en la realización de este riguroso análisis econométrico y estadístico esta en encontrar el mejor modelo que ajuste a los datos, dada la inestabilidad de los mismos, permitiendo pronosticar la volatilidad de la varianza. En la mayoría de los casos para instrumentos financieros, un GARCH (1,1) es suficiente y es generalmente muy utilizado.
B11: GARCH Modelo (P,Q) | E11: 1,1 | G11: Periodicidad (Períodos/Año) | J11: 252
B12: Optimización Alfa | E12: 0.29566917 | G12: Base Predictiva | J12: 252
B13: Optimización Beta | E13: 0.11263462 | G13: Pronostique Períodos | J13: 1
B14: Optimización Omega | E14: 0.00011429552 | G14: Variación Targeting | J14: FALSE
B16: Período | C16: Datos | D16: Volatilidad | F16: Los modelos GARCH son generalmente usados para pronosticar la inestabilidad de instrumentos financieros al usar los precios de si mismo. Solo pueden utilizarse valores positivos para pronosticar la volatilidad en un modelo GARCH. La periodicidad es el número de periodos por año (por ejemplo, 12 para datos mensuales, 252 para días hábiles, 365 para datos diarios, etc.) Es indispensable cerciorarse de tener los valores a modelar en orden cronológico. La Base Predictiva es el número de periodos base, es decir, el número de periodos rezagados que va a usar como una base de pronóstico para predecir la volatilidad futura, se ubica típicamente entre 1 y 12. Varianza Targeting es un método de estimación que consiste en asignarle a la varianza promedio a largo plazo un valor igual a la varianza muestral. Para finalizar debe estar seguro que sus datos originales estén organizados en orden cronológico.
B17: 0 | C17: 13.196151
B18: 1 | C18: 13.111919
B19: 2 | C19: 13.149357 | D19: 0.19223023
B20: 3 | C20: 13.196151 | D20: 0.183222
B21: 4 | C21: 13.345895 | D21: 0.18309528
B22: 5 | C22: 13.252305 | D22: 0.20509734
B23: 6 | C23: 13.242945 | D23: 0.19295186
B24: 7 | C24: 13.205509 | D24: 0.18175011
B25: 8 | C25: 13.299099 | D25: 0.18198967
B26: 9 | C26: 13.823201 | D26: 0.19039183
B27: 10 | C27: 13.785766 | D27: 0.37973711
B28: 11 | C28: 13.841919 | D28: 0.21352363
B29: 12 | C29: 13.710893 | D29: 0.18753383
B30: 13 | C30: 13.551791 | D30: 0.19875526
... B269: 252 | C269: 19.34 | D269: 0.30119696
D270: 0.22915686

Sheet GARCH-Portafolio
B1: GARCH: Proceso General Autorregresivo de Heterocedasticidad Condicional (Pronóstico de la Volatililidad)
B4: GARCH es un término que incorpora una familia de modelos que toman una variedad de formas de acuerdo a sus enfoques (GARCH, T-GARCH, I-GARCH, etc.); específicamente un GARCH (P,Q), es un modelo donde P y Q son enteros positivos que definen el modelo resultante; en este caso, P corresponde al rezago de la varianza condicionada y Q corresponde al rezago de los errores al cuadrado. Los procesos GARCH se utilizan principalmente para calcular la inestabilidad o volatilidad en el precio de un activo financiero, como acciones, opciones financieras, bonos; aunque este modelo también se usa también para modelar otros productos comerciales como el precio del aceite, electricidad, combustibles, productos básicos etc. En términos estadísticos un proceso GARCH busca modelar la volatilidad de la varianza, debido a que esta no es homocedastica, es decir, presenta heterocedasticidad o cambios sistemáticos en la varianza a través del tiempo. Uno de los inconvenientes para construir modelos GARCH es que se requieren muchos datos para hacer funcional el análisis, además de necesitar algo de pericia en modelación econométrica avanzada, y por tanto este enfoque es sumamente susceptible a la manipulación del usuario. El beneficio en la realización de este riguroso análisis econométrico y estadístico esta en encontrar el mejor modelo que ajuste a los datos, dada la inestabilidad de los mismos, permitiendo pronosticar la volatilidad de la varianza. En la mayoría de los casos para instrumentos financieros, un GARCH (1,1) es suficiente y es generalmente muy utilizado.
B11: GARCH Modelo (P,Q) | E11: 1,1 | G11: Periodicidad (Períodos/Año) | J11: 252
B12: Optimización Alfa | E12: 0.13964271 | G12: Base Predictiva | J12: 252
B13: Optimización Beta | E13: 0.54952261 | G13: Pronostique Períodos | J13: 1
B14: Optimización Omega | E14: 2.4783151e-05 | G14: Variación Targeting | J14: TRUE
B16: Período | C16: Datos | D16: Volatilidad | F16: Los modelos GARCH son generalmente usados para pronosticar la inestabilidad de instrumentos financieros al usar los precios de si mismo. Solo pueden utilizarse valores positivos para pronosticar la volatilidad en un modelo GARCH. La periodicidad es el número de periodos por año (por ejemplo, 12 para datos mensuales, 252 para días hábiles, 365 para datos diarios, etc.) Es indispensable cerciorarse de tener los valores a modelar en orden cronológico. La Base Predictiva es el número de periodos base, es decir, el número de periodos rezagados que va a usar como una base de pronóstico para predecir la volatilidad futura, se ubica típicamente entre 1 y 12. Varianza Targeting es un método de estimación que consiste en asignarle a la varianza promedio a largo plazo un valor igual a la varianza muestral. Para finalizar debe estar seguro que sus datos originales estén organizados en orden cronológico.
B17: 0 | C17: 105.76362
B18: 1 | C18: 104.56615
B19: 2 | C19: 104.83395 | D19: 0.14781443
B20: 3 | C20: 105.31385 | D20: 0.13594909
B21: 4 | C21: 104.30001 | D21: 0.13090363
B22: 5 | C22: 105.4721 | D22: 0.1376764
B23: 6 | C23: 104.46303 | D23: 0.14510694
B24: 7 | C24: 104.82744 | D24: 0.1451489
B25: 8 | C25: 105.39534 | D25: 0.13509094
B26: 9 | C26: 106.85338 | D26: 0.13153364
B27: 10 | C27: 107.28406 | D27: 0.14965096
B28: 11 | C28: 106.53941 | D28: 0.1382806
B29: 12 | C29: 107.00105 | D29: 0.13586853
B30: 13 | C30: 106.28653 | D30: 0.13056622
... B269: 252 | C269: 147.73615 | D269: 0.13913272
D270: 0.14049719

Sheet VaR Dinámico
A1: Fecha | B1: Rentabilidad | G1: VaR delta-normal | H1: VaR Simulación Historica | I1: VaR Dinámico Montecarlo | M1: Backtesting. Semáforo
A2: 45154 | B2: =Portafolio!F2 -> r_Apple | C2: =Portafolio!G2 -> r_Coca-Cola | D2: =Portafolio!H2 -> r_JPMorgan | E2: =Portafolio!I2 -> r_AT&T | F2: =Portafolio!J2 -> Portafolio | I2: Entrada | J2: Salida | K2: VaR MC | M2: VaR D-N | N2: VaR SH | O2: VaR MC
A3: 45155 | B3: =Portafolio!F3 -> -0.014662185 | C3: =Portafolio!G3 -> 0.0021472312 | D3: =Portafolio!H3 -> -0.010441079 | E3: =Portafolio!I3 -> -0.0064035323 | F3: =Portafolio!J3 -> -0.009467057
A4: 45156 | B4: =Portafolio!F4 -> 0.0028121206 | C4: =Portafolio!G4 -> 0.0055939922 | D4: =Portafolio!H4 -> 0.0022848848 | E4: =Portafolio!I4 -> 0.0028511962 | F4: =Portafolio!J4 -> 0.0027076334 | Q4: Semáforo | U4: VaR's | V4: Semáforo BIS | Y4: Test de Kupiec
A5: 45159 | B5: =Portafolio!F5 -> 0.00770704 | C5: =Portafolio!G5 -> -0.0085681807 | D5: =Portafolio!H5 -> 0.0034177361 | E5: =Portafolio!I5 -> 0.0035523361 | F5: =Portafolio!J5 -> 0.0038265778 | Q5: Zona | R5: N° Excepciones | S5: Inc. Capital | V5: Excepciones | W5: Zona | Y5: H0 | Z5: P | AA5: Pgorro | AB5: N° Obs. | AC5: LR_ numerador | AD5: LR_Denominador | AE5: LR | AF5: Chi2
A6: 45160 | B6: =Portafolio!F6 -> 0.0078738144 | C6: =Portafolio!G6 -> -0.0061416255 | D6: =Portafolio!H6 -> -0.020956622 | E6: =Portafolio!I6 -> 0.011283651 | F6: =Portafolio!J6 -> -0.004214152 | Q6: Verde | R6: 0 | S6: 0 | U6: VaR D-N | V6: =SUM(M3:M254) -> 4 | W6: Verde | Y6: p = 5% | Z6: 0.05 | AA6: =V6/AB6 -> 0.053333333 | AB6: =COUNT(M3:M254) -> 75 | AC6: =+(($Z$6^V6)*(1-$Z$6)^(AB6-V6)) -> 1.6377816e-07 | AD6: =+(1-AA6)^(AB6-V6)*(AA6^V6) -> 1.651916e-07 | AE6: =-2*LN(AC6/AD6) -> 0.01718639 | AF6: =_xlfn.CHISQ.DIST.RT(AE6,2) -> 0.99144362
A7: 45161 | B7: =Portafolio!F7 -> 0.02171154 | C7: =Portafolio!G7 -> 0.0034904215 | D7: =Portafolio!H7 -> 0.0067403655 | E7: =Portafolio!I7 -> -0.0070373474 | F7: =Portafolio!J7 -> 0.0051511975 | R7: 1 | S7: 0 | U7: VaR SH | V7: =SUM(N3:N254) -> 4 | W7: Verde | AA7: =V7/AB7 -> 0.053333333 | AB7: =COUNT(N3:N254) -> 75 | AC7: =+(($Z$6^V7)*(1-$Z$6)^(AB7-V7)) -> 1.6377816e-07 | AD7: =+(1-AA7)^(AB7-V7)*(AA7^V7) -> 1.651916e-07 | AE7: =-2*LN(AC7/AD7) -> 0.01718639 | AF7: =_xlfn.CHISQ.DIST.RT(AE7,2) -> 0.99144362
A8: 45162 | B8: =Portafolio!F8 -> -0.026519109 | C8: =Portafolio!G8 -> -0.0026582344 | D8: =Portafolio!H8 -> -0.00095044775 | E8: =Portafolio!I8 -> -0.00070654177 | F8: =Portafolio!J8 -> -0.0060379501 | R8: 2 | S8: 0 | U8: VaR MC | V8: =SUM(O3:O254) -> #VALUE! | W8: Verde | AA8: =V8/AB8 -> #VALUE! | AB8: =COUNT(O3:O254) -> 0 | AC8: =+(($Z$6^V8)*(1-$Z$6)^(AB8-V8)) -> #VALUE! | AD8: =+(1-AA8)^(AB8-V8)*(AA8^V8) -> #VALUE! | AE8: =-2*LN(AC8/AD8) -> #VALUE! | AF8: =_xlfn.CHISQ.DIST.RT(AE8,2) -> #VALUE!
A9: 45163 | B9: =Portafolio!F9 -> 0.012564053 | C9: =Portafolio!G9 -> 0.0046472363 | D9: =Portafolio!H9 -> -0.0012233202 | E9: =Portafolio!I9 -> -0.0028308668 | F9: =Portafolio!J9 -> 0.0012464294 | R9: 3 | S9: 0
A10: 45166 | B10: =Portafolio!F10 -> 0.0088072128 | C10: =Portafolio!G10 -> 0.0028110715 | D10: =Portafolio!H10 -> 0.0034622836 | E10: =Portafolio!I10 -> 0.0070621976 | F10: =Portafolio!J10 -> 0.0056612861 | R10: 4 | S10: 0
A11: 45167 | B11: =Portafolio!F11 -> 0.021575763 | C11: =Portafolio!G11 -> -0.00099121473 | D11: =Portafolio!H11 -> 0.0080993211 | E11: =Portafolio!I11 -> 0.038652124 | F11: =Portafolio!J11 -> 0.020261285 | Q11: Amarillo | R11: 5 | S11: 0.4 | V11: VaR D-N | W11: VaR SH | X11: VaR MC
A12: 45168 | B12: =Portafolio!F12 -> 0.018990782 | C12: =Portafolio!G12 -> -0.00049597605 | D12: =Portafolio!H12 -> -0.0040415126 | E12: =Portafolio!I12 -> -0.0027118018 | F12: =Portafolio!J12 -> 0.0011226617 | R12: 6 | S12: 0.5 | U12: Peor Escenarios | V12: =MIN(G181:G255) -> -0.013198 | W12: =MIN(H181:H255) -> -0.011804299 | X12: =MIN(K180:K254) -> #VALUE!
A13: 45169 | B13: =Portafolio!F13 -> 0.0011717517 | C13: =Portafolio!G13 -> -0.01064012 | D13: =Portafolio!H13 -> -0.012428386 | E13: =Portafolio!I13 -> 0.0040649861 | F13: =Portafolio!J13 -> -0.0043288022 | R13: 7 | S13: 0.65 | U13: Liquidez | V13: =STDEV($F$3:$F$254)*NORMSINV(5%)*SQRT(1) -> -0.0131393 | W13: =STDEV($F$3:$F$254)*NORMSINV(5%)*SQRT(1) -> -0.0131393 | X13: =STDEV($F$3:$F$254)*NORMSINV(5%)*SQRT(1) -> -0.0131393
A14: 45170 | B14: =Portafolio!F14 -> 0.0084277858 | C14: =Portafolio!G14 -> -0.008729346 | D14: =Portafolio!H14 -> 0.003343024 | E14: =Portafolio!I14 -> -0.0095109703 | F14: =Portafolio!J14 -> -0.00027929642 | R14: 8 | S14: 0.75 | U14: Nivel de Confianza | V14: =+STDEV($F$3:$F$254)*NORMSINV(1%)*SQRT(1) -> -0.018583162 | W14: =+STDEV($F$3:$F$254)*NORMSINV(1%)*SQRT(1) -> -0.018583162 | X14: =+STDEV($F$3:$F$254)*NORMSINV(1%)*SQRT(1) -> -0.018583162
A15: 45174 | B15: =Portafolio!F15 -> 0.0012659132 | C15: =Portafolio!G15 -> -0.0082960032 | D15: =Portafolio!H15 -> -0.011095406 | E15: =Portafolio!I15 -> -0.011671911 | F15: =Portafolio!J15 -> -0.0087030184 | R15: 9 | S15: 0.85 | U15: Peor Crisis | V15: =-MIN($F$3:$F$254)*NORMSINV(5%)*SQRT(1) -> -0.049750846 | W15: =-MIN($F$3:$F$254)*NORMSINV(5%)*SQRT(1) -> -0.049750846 | X15: =-MIN($F$3:$F$254)*NORMSINV(5%)*SQRT(1) -> -0.049750846
A16: 45175 | B16: =Portafolio!F16 -> -0.036449648 | C16: =Portafolio!G16 -> -0.00068026368 | D16: =Portafolio!H16 -> -0.0016539663 | E16: =Portafolio!I16 -> 0.0089378657 | F16: =Portafolio!J16 -> -0.0051359948 | Q16: Rojo | R16: +10 | S16: 1
A17: 45176 | B17: =Portafolio!F17 -> -0.029685687 | C17: =Portafolio!G17 -> -0.0076850863 | D17: =Portafolio!H17 -> -0.0085911179 | E17: =Portafolio!I17 -> 0 | F17: =Portafolio!J17 -> -0.0099898157
A18: 45177 | B18: =Portafolio!F18 -> 0.0034855737 | C18: =Portafolio!G18 -> 0 | D18: =Portafolio!H18 -> 0.00076518324 | E18: =Portafolio!I18 -> -0.014477989 | F18: =Portafolio!J18 -> -0.0036366612
A19: 45180 | B19: =Portafolio!F19 -> 0.006600704 | C19: =Portafolio!G19 -> 0.0093849136 | D19: =Portafolio!H19 -> 0.0043706423 | E19: =Portafolio!I19 -> 0.0082988273 | F19: =Portafolio!J19 -> 0.0062859574
A20: 45181 | B20: =Portafolio!F20 -> -0.017207767 | C20: =Portafolio!G20 -> -0.0098994166 | D20: =Portafolio!H20 -> 0.012930049 | E20: =Portafolio!I20 -> -0.0041408788 | F20: =Portafolio!J20 -> 0.00048872381
A21: 45182 | B21: =Portafolio!F21 -> -0.011925629 | C21: =Portafolio!G21 -> 0.0023984991 | D21: =Portafolio!H21 -> 0.00047822692 | E21: =Portafolio!I21 -> 0.011004271 | F21: =Portafolio!J21 -> 0.0014768109
A22: 45183 | B22: =Portafolio!F22 -> 0.0087441923 | C22: =Portafolio!G22 -> 0.0082446925 | D22: =Portafolio!H22 -> 0.019211775 | E22: =Portafolio!I22 -> 0.029651714 | F22: =Portafolio!J22 -> 0.020042246
A23: 45184 | B23: =Portafolio!F23 -> -0.0041626265 | C23: =Portafolio!G23 -> -0.0089348416 | D23: =Portafolio!H23 -> -0.0029524998 | E23: =Portafolio!I23 -> 0.011224979 | F23: =Portafolio!J23 -> 0.001131343
A24: 45187 | B24: =Portafolio!F24 -> 0.016771886 | C24: =Portafolio!G24 -> 0.0061940864 | D24: =Portafolio!H24 -> 0.0020810602 | E24: =Portafolio!I24 -> -0.0092349221 | F24: =Portafolio!J24 -> 0.0015301137
A25: 45188 | B25: =Portafolio!F25 -> 0.006161829 | C25: =Portafolio!G25 -> -0.0020603885 | D25: =Portafolio!H25 -> -0.0012750275 | E25: =Portafolio!I25 -> 0.0079209278 | F25: =Portafolio!J25 -> 0.0031390479
A26: 45189 | B26: =Portafolio!F26 -> -0.02019469 | C26: =Portafolio!G26 -> 0.0044589358 | D26: =Portafolio!H26 -> -0.0042389693 | E26: =Portafolio!I26 -> 0.022107528 | F26: =Portafolio!J26 -> 0.0014273245
A27: 45190 | B27: =Portafolio!F27 -> -0.0089290842 | C27: =Portafolio!G27 -> -0.015520182 | D27: =Portafolio!H27 -> -0.007852781 | E27: =Portafolio!I27 -> -0.015554405 | F27: =Portafolio!J27 -> -0.010862645
A28: 45191 | B28: =Portafolio!F28 -> 0.0049321571 | C28: =Portafolio!G28 -> 0.0010421744 | D28: =Portafolio!H28 -> -0.009629071 | E28: =Portafolio!I28 -> -0.012488017 | F28: =Portafolio!J28 -> -0.0072123448
... A179: 45412 | B179: =Portafolio!F179 -> -0.018439791 | C179: =Portafolio!G179 -> -0.0043615431 | D179: =Portafolio!H179 -> -0.0079996022 | E179: =Portafolio!I179 -> -0.0076674125 | F179: =Portafolio!J179 -> -0.0098249134
A180: 45413 | B180: =Portafolio!F180 -> -0.0060654683 | C180: =Portafolio!G180 -> 0.0025869042 | D180: =Portafolio!H180 -> 0.00062565312 | E180: =Portafolio!I180 -> 0.0017746003 | F180: =Portafolio!J180 -> -0.00025763063 | G180: =STDEV($F$3:F179)*NORMSINV(5%)*SQRT(1) -> -0.012903226 | H180: =PERCENTILE($F$3:F179,5%)*SQRT(1) -> -0.011244337 | I180: -0.0031282027 | J180: =I180 -> -0.0031282027 | K180: {=_xll.ROV.RiskSim.RSFunctions.RSForecastStatistic(J180,"Percentile0.05")*SQRT(1)} -> #VALUE! | M180: =IF(F180<=G180,1,0) -> 0 | N180: =IF(F180<=H180,1,0) -> 0 | O180: =IF(F180<=K180,1,0) -> #VALUE!
A181: 45414 | B181: =Portafolio!F181 -> 0.021792613 | C181: =Portafolio!G181 -> 0.0009683989 | D181: =Portafolio!H181 -> -0.0010429763 | E181: =Portafolio!I181 -> -0.0059277433 | F181: =Portafolio!J181 -> 0.002016431 | G181: =STDEV($F$3:F180)*NORMSINV(5%)*SQRT(1) -> -0.012867729 | H181: =PERCENTILE($F$3:F180,5%)*SQRT(1) -> -0.011204339 | I181: 0.031372116 | J181: =I181 -> 0.031372116 | K181: {=_xll.ROV.RiskSim.RSFunctions.RSForecastStatistic(J181,"Percentile0.05")*SQRT(1)} -> #VALUE! | M181: =IF(F181<=G181,1,0) -> 0 | N181: =IF(F181<=H181,1,0) -> 0 | O181: =IF(F181<=K181,1,0) -> #VALUE!
A182: 45415 | B182: =Portafolio!F182 -> 0.058095545 | C182: =Portafolio!G182 -> 0.0028994529 | D182: =Portafolio!H182 -> -0.0060183515 | E182: =Portafolio!I182 -> 0.0017820997 | F182: =Portafolio!J182 -> 0.00963914 | G182: =STDEV($F$3:F181)*NORMSINV(5%)*SQRT(1) -> -0.012832095 | H182: =PERCENTILE($F$3:F181,5%)*SQRT(1) -> -0.011164342 | I182: 0.0031085425 | J182: =I182 -> 0.0031085425 | K182: {=_xll.ROV.RiskSim.RSFunctions.RSForecastStatistic(J182,"Percentile0.05")*SQRT(1)} -> #VALUE! | M182: =IF(F182<=G182,1,0) -> 0 | N182: =IF(F182<=H182,1,0) -> 0 | O182: =IF(F182<=K182,1,0) -> #VALUE!
A183: 45418 | B183: =Portafolio!F183 -> -0.0091483674 | C183: =Portafolio!G183 -> 0.0028910542 | D183: =Portafolio!H183 -> 0.007790721 | E183: =Portafolio!I183 -> 0.0082741717 | F183: =Portafolio!J183 -> 0.0043701257 | G183: =STDEV($F$3:F182)*NORMSINV(5%)*SQRT(1) -> -0.01283951 | H183: =PERCENTILE($F$3:F182,5%)*SQRT(1) -> -0.011124345 | I183: 0.0042511307 | J183: =I183 -> 0.0042511307 | K183: {=_xll.ROV.RiskSim.RSFunctions.RSForecastStatistic(J183,"Percentile0.05")*SQRT(1)} -> #VALUE! | M183: =IF(F183<=G183,1,0) -> 0 | N183: =IF(F183<=H183,1,0) -> 0 | O183: =IF(F183<=K183,1,0) -> #VALUE!
A184: 45419 | B184: =Portafolio!F184 -> 0.0037898713 | C184: =Portafolio!G184 -> 0.0043210584 | D184: =Portafolio!H184 -> -0.0013029561 | E184: =Portafolio!I184 -> 0.0052832441 | F184: =Portafolio!J184 -> 0.002064539 | G184: =STDEV($F$3:F183)*NORMSINV(5%)*SQRT(1) -> -0.012810064 | H184: =PERCENTILE($F$3:F183,5%)*SQRT(1) -> -0.011084348 | I184: -0.0051213462 | J184: =I184 -> -0.0051213462 | K184: {=_xll.ROV.RiskSim.RSFunctions.RSForecastStatistic(J184,"Percentile0.05")*SQRT(1)} -> #VALUE! | M184: =IF(F184<=G184,1,0) -> 0 | N184: =IF(F184<=H184,1,0) -> 0 | O184: =IF(F184<=K184,1,0) -> #VALUE!
A185: 45420 | B185: =Portafolio!F185 -> 0.0018624378 | C185: =Portafolio!G185 -> 0.0036662178 | D185: =Portafolio!H185 -> 0.020134915 | E185: =Portafolio!I185 -> 0.0017549956 | F185: =Portafolio!J185 -> 0.0098964805 | G185: =STDEV($F$3:F184)*NORMSINV(5%)*SQRT(1) -> -0.012775158 | H185: =PERCENTILE($F$3:F184,5%)*SQRT(1) -> -0.011073263 | I185: 0.0040985333 | J185: =I185 -> 0.0040985333 | K185: {=_xll.ROV.RiskSim.RSFunctions.RSForecastStatistic(J185,"Percentile0.05")*SQRT(1)} -> #VALUE! | M185: =IF(F185<=G185,1,0) -> 0 | N185: =IF(F185<=H185,1,0) -> 0 | O185: =IF(F185<=K185,1,0) -> #VALUE!
A186: 45421 | B186: =Portafolio!F186 -> 0.0099644209 | C186: =Portafolio!G186 -> 0.00047729305 | D186: =Portafolio!H186 -> 0.0094112743 | E186: =Portafolio!I186 -> 0.0040827757 | F186: =Portafolio!J186 -> 0.0074393189 | G186: =STDEV($F$3:F185)*NORMSINV(5%)*SQRT(1) -> -0.012784671 | H186: =PERCENTILE($F$3:F185,5%)*SQRT(1) -> -0.011062177 | I186: 0.0092068779 | J186: =I186 -> 0.0092068779 | K186: {=_xll.ROV.RiskSim.RSFunctions.RSForecastStatistic(J186,"Percentile0.05")*SQRT(1)} -> #VALUE! | M186: =IF(F186<=G186,1,0) -> 0 | N186: =IF(F186<=H186,1,0) -> 0 | O186: =IF(F186<=K186,1,0) -> #VALUE!
A187: 45422 | B187: =Portafolio!F187 -> -0.0069140778 | C187: =Portafolio!G187 -> 0.0060250353 | D187: =Portafolio!H187 -> 0.0064097849 | E187: =Portafolio!I187 -> -0.00058223411 | F187: =Portafolio!J187 -> 0.0014848421 | G187: =STDEV($F$3:F186)*NORMSINV(5%)*SQRT(1) -> -0.012772382 | H187: =PERCENTILE($F$3:F186,5%)*SQRT(1) -> -0.011051092 | I187: -0.00062611479 | J187: =I187 -> -0.00062611479 | K187: {=_xll.ROV.RiskSim.RSFunctions.RSForecastStatistic(J187,"Percentile0.05")*SQRT(1)} -> #VALUE! | M187: =IF(F187<=G187,1,0) -> 0 | N187: =IF(F187<=H187,1,0) -> 0 | O187: =IF(F187<=K187,1,0) -> #VALUE!
A188: 45425 | B188: =Portafolio!F188 -> 0.017491613 | C188: =Portafolio!G188 -> 0.0050457832 | D188: =Portafolio!H188 -> -0.00020125494 | E188: =Portafolio!I188 -> 0.005228002 | F188: =Portafolio!J188 -> 0.0052894175 | G188: =STDEV($F$3:F187)*NORMSINV(5%)*SQRT(1) -> -0.012737675 | H188: =PERCENTILE($F$3:F187,5%)*SQRT(1) -> -0.011040007 | I188: 0.0062587809 | J188: =I188 -> 0.0062587809 | K188: {=_xll.ROV.RiskSim.RSFunctions.RSForecastStatistic(J188,"Percentile0.05")*SQRT(1)} -> #VALUE! | M188: =IF(F188<=G188,1,0) -> 0 | N188: =IF(F188<=H188,1,0) -> 0 | O188: =IF(F188<=K188,1,0) -> #VALUE!
A189: 45426 | B189: =Portafolio!F189 -> 0.0061545058 | C189: =Portafolio!G189 -> -0.0075782305 | D189: =Portafolio!H189 -> 0.01389188 | E189: =Portafolio!I189 -> 0.0023147859 | F189: =Portafolio!J189 -> 0.0077415906 | G189: =STDEV($F$3:F188)*NORMSINV(5%)*SQRT(1) -> -0.012712776 | H189: =PERCENTILE($F$3:F188,5%)*SQRT(1) -> -0.011028922 | I189: -0.0069808145 | J189: =I189 -> -0.0069808145 | K189: {=_xll.ROV.RiskSim.RSFunctions.RSForecastStatistic(J189,"Percentile0.05")*SQRT(1)} -> #VALUE! | M189: =IF(F189<=G189,1,0) -> 0 | N189: =IF(F189<=H189,1,0) -> 0 | O189: =IF(F189<=K189,1,0) -> #VALUE!
A190: 45427 | B190: =Portafolio!F190 -> 0.012143862 | C190: =Portafolio!G190 -> 0.00047533861 | D190: =Portafolio!H190 -> 0.0029731023 | E190: =Portafolio!I190 -> 0.0017325799 | F190: =Portafolio!J190 -> 0.004299205 | G190: =STDEV($F$3:F189)*NORMSINV(5%)*SQRT(1) -> -0.012702789 | H190: =PERCENTILE($F$3:F189,5%)*SQRT(1) -> -0.011017837 | I190: 0.010576056 | J190: =I190 -> 0.010576056 | K190: {=_xll.ROV.RiskSim.RSFunctions.RSForecastStatistic(J190,"Percentile0.05")*SQRT(1)} -> #VALUE! | M190: =IF(F190<=G190,1,0) -> 0 | N190: =IF(F190<=H190,1,0) -> 0 | O190: =IF(F190<=K190,1,0) -> #VALUE!
A191: 45428 | B191: =Portafolio!F191 -> 0.00063229391 | C191: =Portafolio!G191 -> 0.0030051414 | D191: =Portafolio!H191 -> 0.0017796278 | E191: =Portafolio!I191 -> -0.0017325799 | F191: =Portafolio!J191 -> 0.00046901489 | G191: =STDEV($F$3:F190)*NORMSINV(5%)*SQRT(1) -> -0.012674037 | H191: =PERCENTILE($F$3:F190,5%)*SQRT(1) -> -0.011006752 | I191: -0.019094344 | J191: =I191 -> -0.019094344 | K191: {=_xll.ROV.RiskSim.RSFunctions.RSForecastStatistic(J191,"Percentile0.05")*SQRT(1)} -> #VALUE! | M191: =IF(F191<=G191,1,0) -> 0 | N191: =IF(F191<=H191,1,0) -> 0 | O191: =IF(F191<=K191,1,0) -> #VALUE!
... A254: 45520 | B254: =Portafolio!F254 -> 0.0059010398 | C254: =Portafolio!G254 -> 0.0076906422 | D254: =Portafolio!H254 -> 0.011374432 | E254: =Portafolio!I254 -> 0.013010852 | F254: =Portafolio!J254 -> 0.010660443 | G254: =STDEV($F$3:F253)*NORMSINV(5%)*SQRT(1) -> -0.01312991 | H254: =PERCENTILE($F$3:F253,5%)*SQRT(1) -> -0.01148432 | I254: 0.00076356229 | J254: =I254 -> 0.00076356229 | K254: {=_xll.ROV.RiskSim.RSFunctions.RSForecastStatistic(J254,"Percentile0.05")*SQRT(1)} -> #VALUE! | M254: =IF(F254<=G254,1,0) -> 0 | N254: =IF(F254<=H254,1,0) -> 0 | O254: =IF(F254<=K254,1,0) -> #VALUE!

Sheet Ajuste Distr. Portf
B1: Ajuste de Distribución para Variables Únicas
B3: Resumen Estadístico
E6: Supuesto Ajustado | F6: -0.00081347476
E8: Distribución Ajustada | F8: Laplace
E9: Alfa | F9: 0.0011248191
E10: Beta | F10: 0.0064303889
E13: Estadístico Kolmogorov-Smirnov | F13: 0.037856997
E14: Prueba Estadística para P-Value | F14: 0.95823926
E16: Real | F16: Teórica
D17: Media | E17: 0.0010465304 | F17: 0.0011248191
D18: Desviación Estándar | E18: 0.0078446041 | F18: 0.0090939432
D19: Asimetría | E19: -0.24975823 | F19: 0
D20: Curtosis | E20: 1.0999228 | F20: 3
B23: Datos Originales Ajustados
B24: -0.030246367 | C24: -0.021324753 | D24: -0.01537902 | E24: -0.015219799 | F24: -0.012460628 | G24: -0.01212492 | H24: -0.012066854 | I24: -0.011933324 | J24: -0.011884293 | K24: -0.011084348 | L24: -0.010862645 | M24: -0.010479527 | N24: -0.0099898157
B25: -0.0098249134 | C25: -0.0097864092 | D25: -0.009467057 | E25: -0.009183857 | F25: -0.0088179369 | G25: -0.0087030184 | H25: -0.0086054087 | I25: -0.0077624497 | J25: -0.0077257882 | K25: -0.0073673817 | L25: -0.0072123448 | M25: -0.0071796819 | N25: -0.0071565942
B26: -0.0068451409 | C26: -0.0067410009 | D26: -0.0065141749 | E26: -0.006462677 | F26: -0.0062770724 | G26: -0.0060379501 | H26: -0.0060153742 | I26: -0.0060135883 | J26: -0.0057440566 | K26: -0.0056513112 | L26: -0.005582031 | M26: -0.0054155994 | N26: -0.0051359948
B27: -0.005097462 | C27: -0.0047527673 | D27: -0.0043288022 | E27: -0.004214152 | F27: -0.0041921114 | G27: -0.0039729829 | H27: -0.003687658 | I27: -0.0036366612 | J27: -0.0033990215 | K27: -0.0030997758 | L27: -0.002878807 | M27: -0.0028289856 | N27: -0.0026385457
B28: -0.002634355 | C28: -0.002564761 | D28: -0.0025467238 | E28: -0.0024608275 | F28: -0.0024044345 | G28: -0.0023818341 | H28: -0.0015660624 | I28: -0.0012934256 | J28: -0.0012900359 | K28: -0.0012758432 | L28: -0.0012641891 | M28: -0.00077469154 | N28: -0.00070412794
B29: -0.00067657508 | C29: -0.00063215212 | D29: -0.0004824164 | E29: -0.00027929642 | F29: -7.9846074e-05 | G29: -7.4265127e-05 | H29: 3.2148997e-05 | I29: 5.6874136e-05 | J29: 9.8798186e-05 | K29: 0.00048305978 | L29: 0.00048872381 | M29: 0.00060853637 | N29: 0.00063525157
B30: 0.00066043807 | C30: 0.00068071291 | D30: 0.00094651306 | E30: 0.00095814517 | F30: 0.0011226617 | G30: 0.0011247795 | H30: 0.001131343 | I30: 0.0011536596 | J30: 0.0012464294 | K30: 0.0013013706 | L30: 0.0013329689 | M30: 0.0014273245 | N30: 0.0014768109
B31: 0.0015301137 | C31: 0.0015379715 | D31: 0.0015594676 | E31: 0.0016028666 | F31: 0.0016239461 | G31: 0.0016465946 | H31: 0.0018892832 | I31: 0.0019130568 | J31: 0.0019266765 | K31: 0.0022833408 | L31: 0.0024028454 | M31: 0.0024157821 | N31: 0.0024514515
B32: 0.0025088405 | C32: 0.0025699359 | D32: 0.0027076334 | E32: 0.0028658701 | F32: 0.0028851977 | G32: 0.0029608312 | H32: 0.0030186769 | I32: 0.0031390479 | J32: 0.0032728032 | K32: 0.003408047 | L32: 0.0036101131 | M32: 0.0036659483 | N32: 0.0036980751
B33: 0.0038265778 | C33: 0.0042214622 | D33: 0.0042707165 | E33: 0.0043675221 | F33: 0.0044033721 | G33: 0.0046337447 | H33: 0.0051511975 | I33: 0.0051834638 | J33: 0.0052883446 | K33: 0.0054249516 | L33: 0.005432835 | M33: 0.0056612861 | N33: 0.0057223787
B34: 0.0057442634 | C34: 0.005760814 | D34: 0.0058848997 | E34: 0.0059026453 | F34: 0.0060108026 | G34: 0.0060193596 | H34: 0.0061410743 | I34: 0.0062859574 | J34: 0.0062910674 | K34: 0.0066336452 | L34: 0.006666351 | M34: 0.0070318358 | N34: 0.0071686436
B35: 0.0071709389 | C35: 0.0072850621 | D35: 0.0072886194 | E35: 0.0073128801 | F35: 0.0073153277 | G35: 0.0078544779 | H35: 0.0079247087 | I35: 0.0083824327 | J35: 0.0086209084 | K35: 0.0089418178 | L35: 0.0091643905 | M35: 0.0096623755 | N35: 0.009709149
B36: 0.0097610369 | C36: 0.01030866 | D36: 0.011258669 | E36: 0.011266351 | F36: 0.011323065 | G36: 0.011324814 | H36: 0.011337205 | I36: 0.011520549 | J36: 0.011893495 | K36: 0.01261639 | L36: 0.012796457 | M36: 0.014462239 | N36: 0.014817472
B37: 0.015379231 | C37: 0.015570911 | D37: 0.015598901 | E37: 0.018077765 | F37: 0.018422593 | G37: 0.019771976 | H37: 0.020042246 | I37: 0.020261285
