Workbook

Sheet Salida Modelo
B2: Obj. Encontrar el punto de umbral en la probabilidad para definir si un cliente es fraudulento vs no-fraudulento. Normal vs Caso de Negocio.
B5: Umbral p* | C5: Sensibilidad (Recall %) | D5: Especif. (%) | F5: Matríz de Confusión | H5: Realidad
B6: 0.05 | C6: 0.97 | D6: 0.60895495 | H6: No Fraude | I6: Fraude
B7: 0.1 | C7: 0.94528239 | D7: 0.64577259 | F7: Modelo | G7: No Fraude | H7: Verdadero Negativo (VN) | I7: Falso Negativo (FN) (¿Perder Plata?)
B8: 0.15 | C8: 0.91321384 | D8: 0.67720527 | G8: Fraude | H8: Falso Positivo (FP) (¿Bloqeo?) | I8: Verdadero Positivo (VP)
B9: 0.2 | C9: 0.87762552 | D9: 0.70558303
B10: 0.25 | C10: 0.83953966 | D10: 0.73188599 | F10: Recall (%) | H10: De todos los Fraude, ¿Cuántos el modelo logro identificar como Fraude?
B11: 0.3 | C11: 0.79948189 | D11: 0.75664558 | F11: Especificidad (%) | H11: De todos los No-Fraude, ¿Cuántos el modelo logro identificar como No-Fraude?
B12: 0.35 | C12: 0.75777917 | D12: 0.78019128 | F12: Precisión (%) | H12: De todos los fraudes, ¿Cuántos eran realmente positivos?
B13: 0.4 | C13: 0.71465688 | D13: 0.80274538
B14: 0.45 | C14: 0.67028085 | D14: 0.82446691
B15: 0.5 | C15: 0.62477875 | D15: 0.84547466
B16: 0.55 | C16: 0.57825225 | D16: 0.86586036
B17: 0.6 | C17: 0.53078442 | D17: 0.88569673
B18: 0.65 | C18: 0.48244456 | D18: 0.9050427
B19: 0.7 | C19: 0.43329142 | D19: 0.92394684
B20: 0.75 | C20: 0.38337555 | D20: 0.94244981
B21: 0.8 | C21: 0.33274093 | D21: 0.96058609
B22: 0.85 | C22: 0.2814262 | D22: 0.97838523
B23: 0.9 | C23: 0.22946563 | D23: 0.99587281
B24: 0.95 | C24: 0.17688983 | D24: 0.999

Sheet Caso de Negocio
B2: CdN. Evaluación financiera de un Modelo para Detección temprana en Fraude | G2: (X) | H2: (Y) | I2: (Z) | K2: (A) | L2: (B) | M2: (C) | O2: (D) | P2: (F) | Q2: (G) | R2: (H) | T2: (I)
G3: Entregadas por el Modelo | K3: (Y) * (3) | L3: (1 - Z)*(1 - 3) | M3: (A) - (3) | O3: (A)*(5)*(12) | P3: [(A+B)*(6)] + (7+8) | Q3: (D)+(13)+(14) | R3: (F) + (C*5) | T3: (C) - (D)
B5: Item | C5: Volumen Transacional | G5: Umbral p* | H5: Sensibilidad (Recall %) | I5: Especif. (%) | K5: VP (Fraude detectados) | L5: FP (Falsas Alertas) | M5: FN (Fraudes no-detectado) | O5: Pérdida Evitada ($) | P5: Costo Operativo ($) | Q5: Ingreso Total ($) | R5: Egreso Total ($) | T5: Beneficio Neto ($)
B6: 1 | C6: Total transacciones procesadas (uds.) | D6: 500000 | E6: Fuente: Core Bancario 2024 | G6: 0.05 | H6: 0.97 | I6: 0.60895495 | K6: =+H6*$D$8 -> 5820 | L6: =+(1-I6)*($D$6-$D$8) -> 193176.26 | M6: =+$D$8-K6 -> 180 | O6: =+K6*$D$10*$D$21 -> 1173312 | P6: =+((K6+L6)*$D$13)+($D$14+$D$15) -> 2418455.1 | Q6: =+O6+$D$22+$D$23 -> 1181512 | R6: =+P6+(M6*$D$10) -> 2468855.1 | T6: =+Q6-R6 -> -1287343.1
B7: 2 | C7: Tasa real de fraude (%) | D7: 0.012 | E7: Benchmarking industria | G7: 0.1 | H7: 0.94528239 | I7: 0.64577259 | K7: =+H7*$D$8 -> 5671.6943 | L7: =+(1-I7)*($D$6-$D$8) -> 174988.34 | M7: =+$D$8-K7 -> 328.30567 | O7: =+K7*$D$10*$D$21 -> 1143413.6 | P7: =+((K7+L7)*$D$13)+($D$14+$D$15) -> 2198420.4 | Q7: =+O7+$D$22+$D$23 -> 1151613.6 | R7: =+P7+(M7*$D$10) -> 2290346 | T7: =+Q7-R7 -> -1138732.4 | U7: =+T7-T6 -> 148610.66
B8: 3 | C8: Transacciones fraudulentas reales (uds.) | D8: =D6*D7 -> 6000 | E8: Calculado | G8: 0.15 | H8: 0.91321384 | I8: 0.67720527 | K8: =+H8*$D$8 -> 5479.283 | L8: =+(1-I8)*($D$6-$D$8) -> 159460.59 | M8: =+$D$8-K8 -> 520.71697 | O8: =+K8*$D$10*$D$21 -> 1104623.5 | P8: =+((K8+L8)*$D$13)+($D$14+$D$15) -> 2009778.5 | Q8: =+O8+$D$22+$D$23 -> 1112823.5 | R8: =+P8+(M8*$D$10) -> 2155579.3 | T8: =+Q8-R8 -> -1042755.8 | U8: =+T8-T7 -> 95976.603
B9: 4 | C9: Ticket promedio transacción ($) | D9: 320 | E9: Fuente: Core Bancario 2024 | G9: 0.2 | H9: 0.87762552 | I9: 0.70558303 | K9: =+H9*$D$8 -> 5265.7531 | L9: =+(1-I9)*($D$6-$D$8) -> 145441.98 | M9: =+$D$8-K9 -> 734.2469 | O9: =+K9*$D$10*$D$21 -> 1061575.8 | P9: =+((K9+L9)*$D$13)+($D$14+$D$15) -> 1838992.8 | Q9: =+O9+$D$22+$D$23 -> 1069775.8 | R9: =+P9+(M9*$D$10) -> 2044581.9 | T9: =+Q9-R9 -> -974806.12 | U9: =+T9-T8 -> 67949.7
B10: 5 | C10: Pérdida promedio por fraude no detectado ($) | D10: 280 | E10: Área de Riesgos | G10: 0.25 | H10: 0.83953966 | I10: 0.73188599 | K10: =+H10*$D$8 -> 5037.238 | L10: =+(1-I10)*($D$6-$D$8) -> 132448.32 | M10: =+$D$8-K10 -> 962.76204 | O10: =+K10*$D$10*$D$21 -> 1015507.2 | P10: =+((K10+L10)*$D$13)+($D$14+$D$15) -> 1680326.7 | Q10: =+O10+$D$22+$D$23 -> 1023707.2 | R10: =+P10+(M10*$D$10) -> 1949900.1 | T10: =+Q10-R10 -> -926192.92 | U10: =+T10-T9 -> 48613.206
G11: 0.3 | H11: 0.79948189 | I11: 0.75664558 | K11: =+H11*$D$8 -> 4796.8913 | L11: =+(1-I11)*($D$6-$D$8) -> 120217.08 | M11: =+$D$8-K11 -> 1203.1087 | O11: =+K11*$D$10*$D$21 -> 967053.29 | P11: =+((K11+L11)*$D$13)+($D$14+$D$15) -> 1530667.7 | Q11: =+O11+$D$22+$D$23 -> 975253.29 | R11: =+P11+(M11*$D$10) -> 1867538.1 | T11: =+Q11-R11 -> -892284.85 | U11: =+T11-T10 -> 33908.063
B12: Item | C12: Costos Operacionales | G12: 0.35 | H12: 0.75777917 | I12: 0.78019128 | K12: =+H12*$D$8 -> 4546.675 | L12: =+(1-I12)*($D$6-$D$8) -> 108585.51 | M12: =+$D$8-K12 -> 1453.325 | O12: =+K12*$D$10*$D$21 -> 916609.68 | P12: =+((K12+L12)*$D$13)+($D$14+$D$15) -> 1388086.2 | Q12: =+O12+$D$22+$D$23 -> 924809.68 | R12: =+P12+(M12*$D$10) -> 1795017.2 | T12: =+Q12-R12 -> -870207.51 | U12: =+T12-T11 -> 22077.343
B13: 6 | C13: Costo revisión manual por alerta ($) | D13: 12 | E13: RRHH / Operaciones | G13: 0.4 | H13: 0.71465688 | I13: 0.80274538 | K13: =+H13*$D$8 -> 4287.9413 | L13: =+(1-I13)*($D$6-$D$8) -> 97443.781 | M13: =+$D$8-K13 -> 1712.0587 | O13: =+K13*$D$10*$D$21 -> 864448.96 | P13: =+((K13+L13)*$D$13)+($D$14+$D$15) -> 1251280.7 | Q13: =+O13+$D$22+$D$23 -> 872648.96 | R13: =+P13+(M13*$D$10) -> 1730657.1 | T13: =+Q13-R13 -> -858008.15 | U13: =+T13-T12 -> 12199.363
B14: 7 | C14: Costo tecnología modelo (mensual $) | D14: 8500 | E14: TI / Proveedor | G14: 0.45 | H14: 0.67028085 | I14: 0.82446691 | K14: =+H14*$D$8 -> 4021.6851 | L14: =+(1-I14)*($D$6-$D$8) -> 86713.345 | M14: =+$D$8-K14 -> 1978.3149 | O14: =+K14*$D$10*$D$21 -> 810771.71 | P14: =+((K14+L14)*$D$13)+($D$14+$D$15) -> 1119320.4 | Q14: =+O14+$D$22+$D$23 -> 818971.71 | R14: =+P14+(M14*$D$10) -> 1673248.5 | T14: =+Q14-R14 -> -854276.83 | U14: =+T14-T13 -> 3731.3139
B15: 8 | C15: Costo analistas fraude FTE (mensual $) | D15: 22000 | E15: RRHH | G15: 0.5 | H15: 0.62477875 | I15: 0.84547466 | K15: =+H15*$D$8 -> 3748.6725 | L15: =+(1-I15)*($D$6-$D$8) -> 76335.518 | M15: =+$D$8-K15 -> 2251.3275 | O15: =+K15*$D$10*$D$21 -> 755732.37 | P15: =+((K15+L15)*$D$13)+($D$14+$D$15) -> 991510.29 | Q15: =+O15+$D$22+$D$23 -> 763932.37 | R15: =+P15+(M15*$D$10) -> 1621882 | T15: =+Q15-R15 -> -857949.63 | U15: =+T15-T14 -> -3672.7934
B16: 9 | C16: Inversión inicial implementación ($) | D16: 150000 | E16: Proyecto BI-2024 | G16: 0.55 | H16: 0.57825225 | I16: 0.86586036 | K16: =+H16*$D$8 -> 3469.5135 | L16: =+(1-I16)*($D$6-$D$8) -> 66264.984 | M16: =+$D$8-K16 -> 2530.4865 | O16: =+K16*$D$10*$D$21 -> 699453.92 | P16: =+((K16+L16)*$D$13)+($D$14+$D$15) -> 867313.97 | Q16: =+O16+$D$22+$D$23 -> 707653.92 | R16: =+P16+(M16*$D$10) -> 1575850.2 | T16: =+Q16-R16 -> -868196.28 | U16: =+T16-T15 -> -10246.656
B17: 10 | C17: Vida útil del proyecto (meses) | D17: 12 | E17: Dirección de Proyectos | G17: 0.6 | H17: 0.53078442 | I17: 0.88569673 | K17: =+H17*$D$8 -> 3184.7065 | L17: =+(1-I17)*($D$6-$D$8) -> 56465.815 | M17: =+$D$8-K17 -> 2815.2935 | O17: =+K17*$D$10*$D$21 -> 642036.83 | P17: =+((K17+L17)*$D$13)+($D$14+$D$15) -> 746306.25 | Q17: =+O17+$D$22+$D$23 -> 650236.83 | R17: =+P17+(M17*$D$10) -> 1534588.4 | T17: =+Q17-R17 -> -884351.59 | U17: =+T17-T16 -> -16155.312
B18: 11 | C18: Tasa de descuento mensual (%) | D18: 0.012 | E18: Finanzas Corporativas | G18: 0.65 | H18: 0.48244456 | I18: 0.9050427 | K18: =+H18*$D$8 -> 2894.6673 | L18: =+(1-I18)*($D$6-$D$8) -> 46908.906 | M18: =+$D$8-K18 -> 3105.3327 | O18: =+K18*$D$10*$D$21 -> 583564.94 | P18: =+((K18+L18)*$D$13)+($D$14+$D$15) -> 628142.89 | Q18: =+O18+$D$22+$D$23 -> 591764.94 | R18: =+P18+(M18*$D$10) -> 1497636 | T18: =+Q18-R18 -> -905871.1 | U18: =+T18-T17 -> -21519.502
G19: 0.7 | H19: 0.43329142 | I19: 0.92394684 | K19: =+H19*$D$8 -> 2599.7485 | L19: =+(1-I19)*($D$6-$D$8) -> 37570.262 | M19: =+$D$8-K19 -> 3400.2515 | O19: =+K19*$D$10*$D$21 -> 524109.3 | P19: =+((K19+L19)*$D$13)+($D$14+$D$15) -> 512540.13 | Q19: =+O19+$D$22+$D$23 -> 532309.3 | R19: =+P19+(M19*$D$10) -> 1464610.5 | T19: =+Q19-R19 -> -932301.24 | U19: =+T19-T18 -> -26430.141
B20: Item | C20: Ingresos y Recuperación | G20: 0.75 | H20: 0.38337555 | I20: 0.94244981 | K20: =+H20*$D$8 -> 2300.2533 | L20: =+(1-I20)*($D$6-$D$8) -> 28429.794 | M20: =+$D$8-K20 -> 3699.7467 | O20: =+K20*$D$10*$D$21 -> 463731.07 | P20: =+((K20+L20)*$D$13)+($D$14+$D$15) -> 399260.57 | Q20: =+O20+$D$22+$D$23 -> 471931.07 | R20: =+P20+(M20*$D$10) -> 1435189.6 | T20: =+Q20-R20 -> -963258.57 | U20: =+T20-T19 -> -30957.338
B21: 12 | C21: Tasa de recuperación fraude detectado (%) | D21: 0.72 | E21: Área Legal / Cobranza | G21: 0.8 | H21: 0.33274093 | I21: 0.96058609 | K21: =+H21*$D$8 -> 1996.4456 | L21: =+(1-I21)*($D$6-$D$8) -> 19470.473 | M21: =+$D$8-K21 -> 4003.5544 | O21: =+K21*$D$10*$D$21 -> 402483.43 | P21: =+((K21+L21)*$D$13)+($D$14+$D$15) -> 288103.03 | Q21: =+O21+$D$22+$D$23 -> 410683.43 | R21: =+P21+(M21*$D$10) -> 1409098.3 | T21: =+Q21-R21 -> -998414.84 | U21: =+T21-T20 -> -35156.261
B22: 13 | C22: Penalidad regulatoria evitada (mensual $) | D22: 5000 | E22: Cumplimiento | G22: 0.85 | H22: 0.2814262 | I22: 0.97838523 | K22: =+H22*$D$8 -> 1688.5572 | L22: =+(1-I22)*($D$6-$D$8) -> 10677.698 | M22: =+$D$8-K22 -> 4311.4428 | O22: =+K22*$D$10*$D$21 -> 340413.13 | P22: =+((K22+L22)*$D$13)+($D$14+$D$15) -> 178895.06 | Q22: =+O22+$D$22+$D$23 -> 348613.13 | R22: =+P22+(M22*$D$10) -> 1386099 | T22: =+Q22-R22 -> -1037485.9 | U22: =+T22-T21 -> -39071.078
B23: 14 | C23: Reducción chargeback por modelo ($) | D23: 3200 | E23: Ops. Tarjetas | G23: 0.9 | H23: 0.22946563 | I23: 0.99587281 | K23: =+H23*$D$8 -> 1376.7938 | L23: =+(1-I23)*($D$6-$D$8) -> 2038.8294 | M23: =+$D$8-K23 -> 4623.2062 | O23: =+K23*$D$10*$D$21 -> 277561.63 | P23: =+((K23+L23)*$D$13)+($D$14+$D$15) -> 71487.479 | Q23: =+O23+$D$22+$D$23 -> 285761.63 | R23: =+P23+(M23*$D$10) -> 1365985.2 | T23: =+Q23-R23 -> -1080223.6 | U23: =+T23-T22 -> -42737.681
B24: 15 | C24: Ingreso por licenciamiento datos ($) | D24: 0 | E24: Opcional / futuro | G24: 0.95 | H24: 0.17688983 | I24: 0.999 | K24: =+H24*$D$8 -> 1061.339 | L24: =+(1-I24)*($D$6-$D$8) -> 494 | M24: =+$D$8-K24 -> 4938.661 | O24: =+K24*$D$10*$D$21 -> 213965.93 | P24: =+((K24+L24)*$D$13)+($D$14+$D$15) -> 49164.068 | Q24: =+O24+$D$22+$D$23 -> 222165.93 | R24: =+P24+(M24*$D$10) -> 1431989.2 | T24: =+Q24-R24 -> -1209823.2 | U24: =+T24-T23 -> -129599.63

Sheet Flujo de Caja
B2: Flujo de Caja - 12 Meses
B4: Concepto | C4: Cálculo | D4: Tipo | F4: 0 | H4: 1 | I4: 2 | J4: 3 | K4: 4 | L4: 5 | M4: 6 | N4: 7 | O4: 8 | P4: 9 | Q4: 10 | R4: 11
B6: EGRESOS
B7: Inversión inicial (9) | C7: (9) | D7: Capex | F7: =+'Caso de Negocio'!$D$16 -> 150000 | H7: 0 | I7: 0 | J7: 0 | K7: 0 | L7: 0 | M7: 0 | N7: 0 | O7: 0 | P7: 0 | Q7: 0 | R7: 0
B8: Tecnología / Infraestructura | C8: (7) | D8: Opex | F8: 0 | H8: =+'Caso de Negocio'!$D$14 -> 8500 | I8: =+'Caso de Negocio'!$D$14 -> 8500 | J8: =+'Caso de Negocio'!$D$14 -> 8500 | K8: =+'Caso de Negocio'!$D$14 -> 8500 | L8: =+'Caso de Negocio'!$D$14 -> 8500 | M8: =+'Caso de Negocio'!$D$14 -> 8500 | N8: =+'Caso de Negocio'!$D$14 -> 8500 | O8: =+'Caso de Negocio'!$D$14 -> 8500 | ... R8: =+'Caso de Negocio'!$D$14 -> 8500
B9: Analistas de Fraude (FTE) | C9: (8) | D9: Opex | F9: 0 | H9: =+'Caso de Negocio'!$D$15 -> 22000 | I9: =+'Caso de Negocio'!$D$15 -> 22000 | J9: =+'Caso de Negocio'!$D$15 -> 22000 | K9: =+'Caso de Negocio'!$D$15 -> 22000 | L9: =+'Caso de Negocio'!$D$15 -> 22000 | M9: =+'Caso de Negocio'!$D$15 -> 22000 | N9: =+'Caso de Negocio'!$D$15 -> 22000 | O9: =+'Caso de Negocio'!$D$15 -> 22000 | ... R9: =+'Caso de Negocio'!$D$15 -> 22000
B10: Revisión manual alertas | C10: (A+B)*(6) | D10: Variable | F10: 0 | H10: =+('Caso de Negocio'!$K$14+'Caso de Negocio'!$L$14)*'Caso de Negocio'!$D$13 -> 1088820.4 | I10: =+('Caso de Negocio'!$K$14+'Caso de Negocio'!$L$14)*'Caso de Negocio'!$D$13 -> 1088820.4 | J10: =+('Caso de Negocio'!$K$14+'Caso de Negocio'!$L$14)*'Caso de Negocio'!$D$13 -> 1088820.4 | K10: =+('Caso de Negocio'!$K$14+'Caso de Negocio'!$L$14)*'Caso de Negocio'!$D$13 -> 1088820.4 | L10: =+('Caso de Negocio'!$K$14+'Caso de Negocio'!$L$14)*'Caso de Negocio'!$D$13 -> 1088820.4 | M10: =+('Caso de Negocio'!$K$14+'Caso de Negocio'!$L$14)*'Caso de Negocio'!$D$13 -> 1088820.4 | N10: =+('Caso de Negocio'!$K$14+'Caso de Negocio'!$L$14)*'Caso de Negocio'!$D$13 -> 1088820.4 | O10: =+('Caso de Negocio'!$K$14+'Caso de Negocio'!$L$14)*'Caso de Negocio'!$D$13 -> 1088820.4 | ... R10: =+('Caso de Negocio'!$K$14+'Caso de Negocio'!$L$14)*'Caso de Negocio'!$D$13 -> 1088820.4
B11: Pérdida residual (FN) | C11: (C)*(5) | D11: Variable | F11: 0 | H11: =+'Caso de Negocio'!$M$14*'Caso de Negocio'!$D$10 -> 553928.18 | I11: =+'Caso de Negocio'!$M$14*'Caso de Negocio'!$D$10 -> 553928.18 | J11: =+'Caso de Negocio'!$M$14*'Caso de Negocio'!$D$10 -> 553928.18 | K11: =+'Caso de Negocio'!$M$14*'Caso de Negocio'!$D$10 -> 553928.18 | L11: =+'Caso de Negocio'!$M$14*'Caso de Negocio'!$D$10 -> 553928.18 | M11: =+'Caso de Negocio'!$M$14*'Caso de Negocio'!$D$10 -> 553928.18 | N11: =+'Caso de Negocio'!$M$14*'Caso de Negocio'!$D$10 -> 553928.18 | O11: =+'Caso de Negocio'!$M$14*'Caso de Negocio'!$D$10 -> 553928.18 | ... R11: =+'Caso de Negocio'!$M$14*'Caso de Negocio'!$D$10 -> 553928.18
B12: TOTAL EGRESOS | F12: =+SUM(F7:F11) -> 150000 | H12: =+SUM(H7:H11) -> 1673248.5 | I12: =+SUM(I7:I11) -> 1673248.5 | J12: =+SUM(J7:J11) -> 1673248.5 | K12: =+SUM(K7:K11) -> 1673248.5 | L12: =+SUM(L7:L11) -> 1673248.5 | M12: =+SUM(M7:M11) -> 1673248.5 | N12: =+SUM(N7:N11) -> 1673248.5 | O12: =+SUM(O7:O11) -> 1673248.5 | ... R12: =+SUM(R7:R11) -> 1673248.5
B14: INGRESOS
B15: Pérdida evitada (recuperación) | C15: (D) | D15: Variable | F15: 0 | H15: =+'Caso de Negocio'!$O$14 -> 810771.71 | I15: =+'Caso de Negocio'!$O$14 -> 810771.71 | J15: =+'Caso de Negocio'!$O$14 -> 810771.71 | K15: =+'Caso de Negocio'!$O$14 -> 810771.71 | L15: =+'Caso de Negocio'!$O$14 -> 810771.71 | M15: =+'Caso de Negocio'!$O$14 -> 810771.71 | N15: =+'Caso de Negocio'!$O$14 -> 810771.71 | O15: =+'Caso de Negocio'!$O$14 -> 810771.71 | ... R15: =+'Caso de Negocio'!$O$14 -> 810771.71
B16: Penalidad regulatoria evitada | C16: (13) | D16: Fijo | F16: 0 | H16: =+'Caso de Negocio'!$D$22 -> 5000 | I16: =+'Caso de Negocio'!$D$22 -> 5000 | J16: =+'Caso de Negocio'!$D$22 -> 5000 | K16: =+'Caso de Negocio'!$D$22 -> 5000 | L16: =+'Caso de Negocio'!$D$22 -> 5000 | M16: =+'Caso de Negocio'!$D$22 -> 5000 | N16: =+'Caso de Negocio'!$D$22 -> 5000 | O16: =+'Caso de Negocio'!$D$22 -> 5000 | ... R16: =+'Caso de Negocio'!$D$22 -> 5000
B17: Reducción chargeback | C17: (14) | D17: Fijo | F17: 0 | H17: =+'Caso de Negocio'!$D$23 -> 3200 | I17: =+'Caso de Negocio'!$D$23 -> 3200 | J17: =+'Caso de Negocio'!$D$23 -> 3200 | K17: =+'Caso de Negocio'!$D$23 -> 3200 | L17: =+'Caso de Negocio'!$D$23 -> 3200 | M17: =+'Caso de Negocio'!$D$23 -> 3200 | N17: =+'Caso de Negocio'!$D$23 -> 3200 | O17: =+'Caso de Negocio'!$D$23 -> 3200 | ... R17: =+'Caso de Negocio'!$D$23 -> 3200
B18: TOTAL INGRESOS | F18: =SUM(F15:F17) -> 0 | H18: =SUM(H15:H17) -> 818971.71 | I18: =SUM(I15:I17) -> 818971.71 | J18: =SUM(J15:J17) -> 818971.71 | K18: =SUM(K15:K17) -> 818971.71 | L18: =SUM(L15:L17) -> 818971.71 | M18: =SUM(M15:M17) -> 818971.71 | N18: =SUM(N15:N17) -> 818971.71 | O18: =SUM(O15:O17) -> 818971.71 | ... R18: =SUM(R15:R17) -> 818971.71
B20: FLUJO NETO MENSUAL | F20: =F18-F12 -> -150000 | H20: =H18-H12 -> -854276.83 | I20: =I18-I12 -> -854276.83 | J20: =J18-J12 -> -854276.83 | K20: =K18-K12 -> -854276.83 | L20: =L18-L12 -> -854276.83 | M20: =M18-M12 -> -854276.83 | N20: =N18-N12 -> -854276.83 | O20: =O18-O12 -> -854276.83 | ... R20: =R18-R12 -> -854276.83
B21: FLUJO ACUMULADO | F21: =E21+F20 -> -150000 | H21: =F21+H20 -> -1004276.8 | I21: =H21+I20 -> -1858553.7 | J21: =I21+J20 -> -2712830.5 | K21: =J21+K20 -> -3567107.3 | L21: =K21+L20 -> -4421384.2 | M21: =L21+M20 -> -5275661 | N21: =M21+N20 -> -6129937.8 | O21: =N21+O20 -> -6984214.7 | P21: =O21+P20 -> -7838491.5 | ... R21: =Q21+R20 -> -9547045.2
B23: VAN ACUMULADO (descontado) | F23: =+F20 -> -150000 | H23: =H20/((1+'Caso de Negocio'!$D$18)^H4)+F23 -> -994147.07 | I23: =I20/((1+'Caso de Negocio'!$D$18)^I4)+H23 -> -1828284.5 | J23: =J20/((1+'Caso de Negocio'!$D$18)^J4)+I23 -> -2652530.9 | K23: =K20/((1+'Caso de Negocio'!$D$18)^K4)+J23 -> -3467003.7 | L23: =L20/((1+'Caso de Negocio'!$D$18)^L4)+K23 -> -4271818.7 | M23: =M20/((1+'Caso de Negocio'!$D$18)^M4)+L23 -> -5067090.5 | N23: =N20/((1+'Caso de Negocio'!$D$18)^N4)+M23 -> -5852932.1 | O23: =O20/((1+'Caso de Negocio'!$D$18)^O4)+N23 -> -6629455.5 | P23: =P20/((1+'Caso de Negocio'!$D$18)^P4)+O23 -> -7396771.1 | ... R23: =R20/((1+'Caso de Negocio'!$D$18)^R4)+Q23 -> -8904214.3
B25: Resumen Financiero
B26: VAN del Proyecto ($) | C26: =+R23 -> -8904214.3
B27: Beneficio neto total ($) | C27: =SUM(F20:R20) -> -9547045.2
