Workbook

Sheet Umbral
A1: ROC / Candidate Cutoffs + Economics (discrete optimization)
A2: Esta hoja proporciona una curva ROC inventada (TPR/FPR por punto de corte). Calcula la matriz de confusión + el beneficio neto mensual para cada punto de corte utilizando los mismos datos del caso de negocio. El punto de corte recomendado es la fila con el mayor beneficio neto mensual (y el mayor VPN implícito para un flujo mensual constante).
A6: Cutoff τ | B6: TPR | C6: FPR | D6: TP | E6: FN | F6: FP | G6: Fraud saved ($) | H6: FP cost ($) | I6: Net / mo ($) | J6: Accum
A7: 0.1 | B7: 0.95 | C7: 0.08 | D7: =Supuestos!$E$7*B7 -> 2375 | E7: =Supuestos!$E$7-D7 -> 125 | F7: =Supuestos!$E$8*C7 -> 79800 | G7: =D7*Supuestos!$B$9 -> 106875 | H7: =F7*Supuestos!$E$9 -> 57456 | I7: =G7-H7-Supuestos!$B$12 -> 34419 | J7: =+I7 -> 34419
A8: 0.15 | B8: 0.92 | C8: 0.06 | D8: =Supuestos!$E$7*B8 -> 2300 | E8: =Supuestos!$E$7-D8 -> 200 | F8: =Supuestos!$E$8*C8 -> 59850 | G8: =D8*Supuestos!$B$9 -> 103500 | H8: =F8*Supuestos!$E$9 -> 43092 | I8: =G8-H8-Supuestos!$B$12 -> 45408 | J8: =+J7+I8 -> 79827
A9: 0.2 | B9: 0.89 | C9: 0.045 | D9: =Supuestos!$E$7*B9 -> 2225 | E9: =Supuestos!$E$7-D9 -> 275 | F9: =Supuestos!$E$8*C9 -> 44887.5 | G9: =D9*Supuestos!$B$9 -> 100125 | H9: =F9*Supuestos!$E$9 -> 32319 | I9: =G9-H9-Supuestos!$B$12 -> 52806 | J9: =+J8+I9 -> 132633
A10: 0.25 | B10: 0.85 | C10: 0.033 | D10: =Supuestos!$E$7*B10 -> 2125 | E10: =Supuestos!$E$7-D10 -> 375 | F10: =Supuestos!$E$8*C10 -> 32917.5 | G10: =D10*Supuestos!$B$9 -> 95625 | H10: =F10*Supuestos!$E$9 -> 23700.6 | I10: =G10-H10-Supuestos!$B$12 -> 56924.4 | J10: =+J9+I10 -> 189557.4
A11: 0.3 | B11: 0.8 | C11: 0.024 | D11: =Supuestos!$E$7*B11 -> 2000 | E11: =Supuestos!$E$7-D11 -> 500 | F11: =Supuestos!$E$8*C11 -> 23940 | G11: =D11*Supuestos!$B$9 -> 90000 | H11: =F11*Supuestos!$E$9 -> 17236.8 | I11: =G11-H11-Supuestos!$B$12 -> 57763.2 | J11: =+J10+I11 -> 247320.6
A12: 0.35 | B12: 0.75 | C12: 0.017 | D12: =Supuestos!$E$7*B12 -> 1875 | E12: =Supuestos!$E$7-D12 -> 625 | F12: =Supuestos!$E$8*C12 -> 16957.5 | G12: =D12*Supuestos!$B$9 -> 84375 | H12: =F12*Supuestos!$E$9 -> 12209.4 | I12: =G12-H12-Supuestos!$B$12 -> 57165.6 | J12: =+J11+I12 -> 304486.2
A13: 0.4 | B13: 0.7 | C13: 0.01 | D13: =Supuestos!$E$7*B13 -> 1750 | E13: =Supuestos!$E$7-D13 -> 750 | F13: =Supuestos!$E$8*C13 -> 9975 | G13: =D13*Supuestos!$B$9 -> 78750 | H13: =F13*Supuestos!$E$9 -> 7182 | I13: =G13-H13-Supuestos!$B$12 -> 56568 | J13: =+J12+I13 -> 361054.2
A14: 0.45 | B14: 0.64 | C14: 0.0075 | D14: =Supuestos!$E$7*B14 -> 1600 | E14: =Supuestos!$E$7-D14 -> 900 | F14: =Supuestos!$E$8*C14 -> 7481.25 | G14: =D14*Supuestos!$B$9 -> 72000 | H14: =F14*Supuestos!$E$9 -> 5386.5 | I14: =G14-H14-Supuestos!$B$12 -> 51613.5 | J14: =+J13+I14 -> 412667.7
A15: 0.5 | B15: 0.58 | C15: 0.0055 | D15: =Supuestos!$E$7*B15 -> 1450 | E15: =Supuestos!$E$7-D15 -> 1050 | F15: =Supuestos!$E$8*C15 -> 5486.25 | G15: =D15*Supuestos!$B$9 -> 65250 | H15: =F15*Supuestos!$E$9 -> 3950.1 | I15: =G15-H15-Supuestos!$B$12 -> 46299.9 | J15: =+J14+I15 -> 458967.6
A16: 0.55 | B16: 0.51 | C16: 0.004 | D16: =Supuestos!$E$7*B16 -> 1275 | E16: =Supuestos!$E$7-D16 -> 1225 | F16: =Supuestos!$E$8*C16 -> 3990 | G16: =D16*Supuestos!$B$9 -> 57375 | H16: =F16*Supuestos!$E$9 -> 2872.8 | I16: =G16-H16-Supuestos!$B$12 -> 39502.2 | J16: =+J15+I16 -> 498469.8
A17: 0.6 | B17: 0.44 | C17: 0.003 | D17: =Supuestos!$E$7*B17 -> 1100 | E17: =Supuestos!$E$7-D17 -> 1400 | F17: =Supuestos!$E$8*C17 -> 2992.5 | G17: =D17*Supuestos!$B$9 -> 49500 | H17: =F17*Supuestos!$E$9 -> 2154.6 | I17: =G17-H17-Supuestos!$B$12 -> 32345.4 | J17: =+J16+I17 -> 530815.2
A18: 0.65 | B18: 0.36 | C18: 0.0022 | D18: =Supuestos!$E$7*B18 -> 900 | E18: =Supuestos!$E$7-D18 -> 1600 | F18: =Supuestos!$E$8*C18 -> 2194.5 | G18: =D18*Supuestos!$B$9 -> 40500 | H18: =F18*Supuestos!$E$9 -> 1580.04 | I18: =G18-H18-Supuestos!$B$12 -> 23919.96 | J18: =+J17+I18 -> 554735.16
A19: 0.7 | B19: 0.29 | C19: 0.0016 | D19: =Supuestos!$E$7*B19 -> 725 | E19: =Supuestos!$E$7-D19 -> 1775 | F19: =Supuestos!$E$8*C19 -> 1596 | G19: =D19*Supuestos!$B$9 -> 32625 | H19: =F19*Supuestos!$E$9 -> 1149.12 | I19: =G19-H19-Supuestos!$B$12 -> 16475.88 | J19: =+J18+I19 -> 571211.04
... A23: 0.9 | B23: 0.07 | C23: 0.0003 | D23: =Supuestos!$E$7*B23 -> 175 | E23: =Supuestos!$E$7-D23 -> 2325 | F23: =Supuestos!$E$8*C23 -> 299.25 | G23: =D23*Supuestos!$B$9 -> 7875 | H23: =F23*Supuestos!$E$9 -> 215.46 | I23: =G23-H23-Supuestos!$B$12 -> -7340.46 | J23: =+J22+I23 -> 572271.9
A25: Recommended (max net / mo)
A26: Max net / mo ($) | B26: =MAX(I7:I23) -> 57763.2
A27: Cutoff τ at max | B27: =INDEX(A7:A23, MATCH(B26, I7:I23, 0)) -> 0.3
A28: TPR at max | B28: =INDEX(B7:B23, MATCH(B26, I7:I23, 0)) -> 0.8
A29: FPR at max | B29: =INDEX(C7:C23, MATCH(B26, I7:I23, 0)) -> 0.024

Sheet Supuestos
A1: Fraud Cutoff Optimization (Example) — Inputs, Confusion Matrix & Economics
A2: How to use: 1) Edit BLUE input cells. 2) Choose a Cutoff in B18 (0–1). Metrics are interpolated via the ROC table on the next sheet. 3) The workbook computes the confusion matrix + monthly value + 12m NPV. 4) Go to 'Threshold_Table' to see the best cutoff from the discrete candidates.
A6: (1) Supuestos de Entrada (en azul modificar) | D6: (2) Cálculo
A7: Número de TRX por mes | B7: 1000000 | D7: Número de TRX fraude | E7: =B7*B8 -> 2500
A8: Ratio de Fraude | B8: 0.0025 | D8: Número de TRX No-Fraude | E8: =B7-E7 -> 997500
A9: Perdida ($) por TRX fraude | B9: 45 | D9: Costo por bloqueo de compra legetima | E9: =B11*B10 -> 0.72
A10: Margen ($) por TRX legitima | B10: 1.2 | D10: Perdida ($) baseline | E10: =E7*B9 -> 112500
A11: %TRX que abandona el cliente por bloqueo | B11: 0.6 | D11: Perdida ($) con el modelo | E11: =+(E7-E18)*B9 -> 5625 | F11: (FN*$45) = (2.500 - 2375)*$45
A12: Costo ($) Operacional | B12: 15000 | D12: Perdida Evitada (Beneficio) | E12: =+E10-E11 -> 106875
A13: Inversión ($) Implementación | B13: 120000
A14: Tasa de descuento mensual | B14: 0.01 | D14: El umbral “óptimo” NO maximiza “pérdida evitada”, sino valor neto
A15: Horizonte de evaluación | B15: 12 | D15: Si tu objetivo fuera solo evitar fraude, el “mejor” umbral sería bloquear todo (evitas 100% del fraude)
A17: (3) Selección de Umbral | D17: (4) Matriz de Confusión
A18: Umbral de corte en probabilidad de fraude | B18: 0.1 | D18: TP (real fraude vs modelo fraude) | E18: =E7*B19 -> 2375 | F18: Si aumenta el umbral disminuye número fraude detectado
A19: Recall / TPR at τ | B19: =VLOOKUP(B18,Umbral!$A$7:$C$23,2,TRUE) -> 0.95 | D19: FN (real fraude vs modelo no fraude (aprobado) | E19: =E7-E18 -> 125 | F19: FN ya se considera dentro TP (más FN menos TP) | J19: =+(E18+E19)*B9-(E19*B9)-(E20*E9)-B25 -> 34419
A20: FPR at τ | B20: =VLOOKUP(B18,Umbral!$A$7:$C$23,3,TRUE) -> 0.08 | D20: FP (real no fraude vs modelo fraude (bloqueo) | E20: =E8*B20 -> 79800 | J20: analogía
D21: TN (real no fraude vs modelo no fraude) | E21: =E8-E20 -> 917700
A22: (5) Indicadores Economicos | D22: (6) VPN a 12 meses
A23: Ganancia por fraude evitado ($) | B23: =E18*$B$9 -> 106875 | D23: Beneficio neto mensual | E23: =B26 -> 34419
A24: Margen Perdido por FP ($) (lo que perdimos x fuja de cliente) | B24: =E20*$E$9 -> 57456 | D24: Beneficio a valor presente | E24: =E23*(1-(1+$B$14)^(-$B$15))/$B$14 -> 387388.51
A25: Costo Operacional ($) | B25: =$B$12 -> 15000 | D25: VPN (descontando inversión) | E25: =E24-$B$13 -> 267388.51 | F25: Si aumenta el umbral aumenta el valor presente neto
A26: Beneficio neto por mes ($) | B26: =B23-B24-B25 -> 34419
A28: Usando Solver para resolver el mejor umbral: Datos ➜ Solver ➜ Objetivo: E25 (NPV) ➜ Máximizar ➜ Variable de Decisón: Umbral (B18) ➜ Restricciones: 0.10 ≤ B18 ≤ 0.90. Note: with VLOOKUP(TRUE), the objective is stepwise.
