Workbook

Sheet Portafolio
A1: fecha | B1: AAPL | C1: JPM | D1: MSFT | H1: SD | P1: VaR | X1: CVaR
A2: 2024-01-02 | B2: 184.93822 | C2: 168.0667 | D2: 368.8541 | E2: AAPL | F2: JPM | G2: MSFT | H2: Portafolio | P2: Portafolio | X2: Portafolio
A3: 2024-01-03 | B3: 183.55348 | C3: 167.33418 | D3: 368.58557 | E3: =LN(B3/B2) -> -0.0075157276 | F3: =LN(C3/C2) -> -0.0043679949 | G3: =LN(D3/D2) -> -0.00072826083 | H3: =SUMPRODUCT(E3:G3,$K$15:$M$15) -> -0.003193079 | K3: Matriz de Covarianza-Varianza | P3: =SUMPRODUCT(E3:G3,$S$15:$U$15) -> -0.0031914182 | S3: Matriz de Covarianza-Varianza | X3: =SUMPRODUCT(E3:G3,$AA$15:$AC$15) -> -0.0031384189 | AA3: Matriz de Covarianza-Varianza
A4: 2024-01-04 | B4: 181.22234 | C4: 168.44463 | D4: 365.94 | E4: =LN(B4/B3) -> -0.012781429 | F4: =LN(C4/C3) -> 0.0066141592 | G4: =LN(D4/D3) -> -0.0072035078 | H4: =SUMPRODUCT(E4:G4,$K$15:$M$15) -> -0.0015849665 | K4: AAPL | L4: JPM | M4: MSFT | P4: =SUMPRODUCT(E4:G4,$S$15:$U$15) -> -0.0015772476 | S4: AAPL | T4: JPM | U4: MSFT | X4: =SUMPRODUCT(E4:G4,$AA$15:$AC$15) -> -0.0036093691 | AA4: AAPL | AB4: JPM | AC4: MSFT
A5: 2024-01-05 | B5: 180.49507 | C5: 169.28975 | D5: 365.75107 | E5: =LN(B5/B4) -> -0.0040211799 | F5: =LN(C5/C4) -> 0.0050046725 | G5: =LN(D5/D4) -> -0.0005164319 | H5: =SUMPRODUCT(E5:G5,$K$15:$M$15) -> 0.0015763662 | J5: AAPL | K5: =VAR(E3:E125) -> 0.00022810696 | L5: =COVAR(E3:E125,F3:F125) -> -2.5044799e-05 | M5: =COVAR(E3:E125,G3:G125) -> 6.6909284e-05 | P5: =SUMPRODUCT(E5:G5,$S$15:$U$15) -> 0.0015800213 | R5: AAPL | S5: =VAR(E3:E125) -> 0.00022810696 | T5: =COVAR(E3:E125,F3:F125) -> -2.5044799e-05 | U5: =COVAR(E3:E125,G3:G125) -> 6.6909284e-05 | X5: =SUMPRODUCT(E5:G5,$AA$15:$AC$15) -> 0.00069351791 | Z5: AAPL | AA5: =VAR(E3:E125) -> 0.00022810696 | AB5: =COVAR(E3:E125,F3:F125) -> -2.5044799e-05 | AC5: =COVAR(E3:E125,G3:G125) -> 6.6909284e-05
A6: 2024-01-08 | B6: 184.85852 | C6: 169.04408 | D6: 372.65335 | E6: =LN(B6/B5) -> 0.023887306 | F6: =LN(C6/C5) -> -0.0014522139 | G6: =LN(D6/D5) -> 0.018695673 | H6: =SUMPRODUCT(E6:G6,$K$15:$M$15) -> 0.010152267 | J6: JPM | K6: =COVAR(E3:E125,F3:F125) -> -2.5044799e-05 | L6: =VAR(F3:F125) -> 0.00014318033 | M6: =COVAR(F3:F125,G3:G125) -> 1.7859878e-06 | P6: =SUMPRODUCT(E6:G6,$S$15:$U$15) -> 0.010142328 | R6: JPM | S6: =COVAR(E3:E125,F3:F125) -> -2.5044799e-05 | T6: =VAR(F3:F125) -> 0.00014318033 | U6: =COVAR(F3:F125,G3:G125) -> 1.7859878e-06 | X6: =SUMPRODUCT(E6:G6,$AA$15:$AC$15) -> 0.01293359 | Z6: JPM | AA6: =COVAR(E3:E125,F3:F125) -> -2.5044799e-05 | AB6: =VAR(F3:F125) -> 0.00014318033 | AC6: =COVAR(F3:F125,G3:G125) -> 1.7859878e-06
A7: 2024-01-09 | B7: 184.44011 | C7: 167.70761 | D7: 373.74734 | E7: =LN(B7/B6) -> -0.0022659785 | F7: =LN(C7/C6) -> -0.0079374717 | G7: =LN(D7/D6) -> 0.0029313879 | H7: =SUMPRODUCT(E7:G7,$K$15:$M$15) -> -0.0026313546 | J7: MSFT | K7: =COVAR(E3:E125,G3:G125) -> 6.6909284e-05 | L7: =COVAR(F3:F125,G3:G125) -> 1.7859878e-06 | M7: =VAR(G3:G125) -> 0.00014327713 | P7: =SUMPRODUCT(E7:G7,$S$15:$U$15) -> -0.0026331379 | R7: MSFT | S7: =COVAR(E3:E125,G3:G125) -> 6.6909284e-05 | T7: =COVAR(F3:F125,G3:G125) -> 1.7859878e-06 | U7: =VAR(G3:G125) -> 0.00014327713 | X7: =SUMPRODUCT(E7:G7,$AA$15:$AC$15) -> -0.0015945524 | Z7: MSFT | AA7: =COVAR(E3:E125,G3:G125) -> 6.6909284e-05 | AB7: =COVAR(F3:F125,G3:G125) -> 1.7859878e-06 | AC7: =VAR(G3:G125) -> 0.00014327713
A8: 2024-01-10 | B8: 185.48614 | C8: 168.06139 | D8: 380.68942 | E8: =LN(B8/B7) -> 0.0056553893 | F8: =LN(C8/C7) -> 0.0021072531 | G8: =LN(D8/D7) -> 0.018403858 | H8: =SUMPRODUCT(E8:G8,$K$15:$M$15) -> 0.0094720816 | P8: =SUMPRODUCT(E8:G8,$S$15:$U$15) -> 0.0094716249 | X8: =SUMPRODUCT(E8:G8,$AA$15:$AC$15) -> 0.010739402
A9: 2024-01-11 | B9: 184.88841 | C9: 167.35384 | D9: 382.53931 | E9: =LN(B9/B8) -> -0.0032277218 | F9: =LN(C9/C8) -> -0.0042189561 | G9: =LN(D9/D8) -> 0.0048475314 | H9: =SUMPRODUCT(E9:G9,$K$15:$M$15) -> -0.00023880911 | J9: Estadística | K9: AAPL | L9: JPM | M9: MSFT | P9: =SUMPRODUCT(E9:G9,$S$15:$U$15) -> -0.00023862353 | R9: Estadística | S9: AAPL | T9: JPM | U9: MSFT | X9: =SUMPRODUCT(E9:G9,$AA$15:$AC$15) -> 0.00040929129 | Z9: Estadística | AA9: AAPL | AB9: JPM | AC9: MSFT
A10: 2024-01-12 | B10: 185.21716 | C10: 166.12546 | D10: 386.35843 | E10: =LN(B10/B9) -> 0.0017765238 | F10: =LN(C10/C9) -> -0.0073670772 | G10: =LN(D10/D9) -> 0.0099341008 | H10: =SUMPRODUCT(E10:G10,$K$15:$M$15) -> 0.0010930566 | J10: Media | K10: =AVERAGE(E3:E125) -> 0.0010477795 | L10: =AVERAGE(F3:F125) -> 0.0014110405 | M10: =AVERAGE(G3:G125) -> 0.0015467058 | P10: =SUMPRODUCT(E10:G10,$S$15:$U$15) -> 0.0010901661 | R10: Media | S10: =AVERAGE(E3:E125) -> 0.0010477795 | T10: =AVERAGE(F3:F125) -> 0.0014110405 | U10: =AVERAGE(G3:G125) -> 0.0015467058 | X10: =SUMPRODUCT(E10:G10,$AA$15:$AC$15) -> 0.002750154 | Z10: Media | AA10: =AVERAGE(E3:E125) -> 0.0010477795 | AB10: =AVERAGE(F3:F125) -> 0.0014110405 | AC10: =AVERAGE(G3:G125) -> 0.0015467058
A11: 2024-01-16 | B11: 182.93582 | C11: 165.0838 | D11: 388.14865 | E11: =LN(B11/B10) -> -0.012393602 | F11: =LN(C11/C10) -> -0.0062900411 | G11: =LN(D11/D10) -> 0.0046228765 | H11: =SUMPRODUCT(E11:G11,$K$15:$M$15) -> -0.0023696334 | J11: Sd | K11: =STDEV(E3:E125) -> 0.01510321 | L11: =STDEV(F3:F125) -> 0.011965798 | M11: =STDEV(G3:G125) -> 0.011969843 | P11: =SUMPRODUCT(E11:G11,$S$15:$U$15) -> -0.0023661454 | R11: Sd | S11: =STDEV(E3:E125) -> 0.01510321 | T11: =STDEV(F3:F125) -> 0.011965798 | U11: =STDEV(G3:G125) -> 0.011969843 | X11: =SUMPRODUCT(E11:G11,$AA$15:$AC$15) -> -0.0020124852 | Z11: Sd | AA11: =STDEV(E3:E125) -> 0.01510321 | AB11: =STDEV(G3:G125) -> 0.011969843 | AC11: =STDEV(G3:G125) -> 0.011969843
A12: 2024-01-17 | B12: 181.98941 | C12: 164.19936 | D12: 387.353 | E12: =LN(B12/B11) -> -0.0051868884 | F12: =LN(C12/C11) -> -0.0053719561 | G12: =LN(D12/D11) -> -0.0020519739 | H12: =SUMPRODUCT(E12:G12,$K$15:$M$15) -> -0.0039357185 | J12: Sharpe | K12: =K10/K11 -> 0.069374623 | L12: =L10/L11 -> 0.1179228 | M12: =M10/M11 -> 0.12921688 | P12: =SUMPRODUCT(E12:G12,$S$15:$U$15) -> -0.003935571 | R12: Sharpe | S12: =S10/S11 -> 0.069374623 | T12: =T10/T11 -> 0.1179228 | U12: =U10/U11 -> 0.12921688 | X12: =SUMPRODUCT(E12:G12,$AA$15:$AC$15) -> -0.003708708 | Z12: Sharpe | AA12: =AA10/AA11 -> 0.069374623 | AB12: =AB10/AB11 -> 0.11788296 | AC12: =AC10/AC11 -> 0.12921688
A13: 2024-01-18 | B13: 187.91693 | C13: 164.52365 | D13: 391.72906 | E13: =LN(B13/B12) -> 0.032051509 | F13: =LN(C13/C12) -> 0.00197306 | G13: =LN(D13/D12) -> 0.011234026 | H13: =SUMPRODUCT(E13:G13,$K$15:$M$15) -> 0.0095054398 | P13: =SUMPRODUCT(E13:G13,$S$15:$U$15) -> 0.0094926251 | X13: =SUMPRODUCT(E13:G13,$AA$15:$AC$15) -> 0.011852209
A14: 2024-01-19 | B14: 190.83585 | C14: 167.36365 | D14: 396.50299 | E14: =LN(B14/B13) -> 0.015413603 | F14: =LN(C14/C13) -> 0.017114639 | G14: =LN(D14/D13) -> 0.012113144 | H14: =SUMPRODUCT(E14:G14,$K$15:$M$15) -> 0.014781335 | J14: Pesos | K14: AAPL | L14: JPM | M14: MSFT | N14: Total | P14: =SUMPRODUCT(E14:G14,$S$15:$U$15) -> 0.014781749 | R14: Pesos | S14: AAPL | T14: JPM | U14: MSFT | V14: Total | X14: =SUMPRODUCT(E14:G14,$AA$15:$AC$15) -> 0.014356909 | Z14: Pesos | AA14: AAPL | AB14: JPM | AC14: MSFT | AD14: Total
A15: 2024-01-22 | B15: 193.15703 | C15: 167.1671 | D15: 394.35477 | E15: =LN(B15/B14) -> 0.012089863 | F15: =LN(C15/C14) -> -0.00117507 | G15: =LN(D15/D14) -> -0.0054326563 | H15: =SUMPRODUCT(E15:G15,$K$15:$M$15) -> -0.0014064286 | J15: wi | K15: 0.11927555 | L15: 0.45476931 | M15: 0.42595514 | N15: =SUM(K15:M15) -> 1 | P15: =SUMPRODUCT(E15:G15,$S$15:$U$15) -> -0.0014126588 | R15: wi | S15: 0.11882815 | T15: 0.45514733 | U15: 0.42602453 | V15: =SUM(S15:U15) -> 1 | X15: =SUMPRODUCT(E15:G15,$AA$15:$AC$15) -> -0.00091491016 | Z15: wi | AA15: 0.17723913 | AB15: 0.33165978 | AC15: 0.49110109 | AD15: =SUM(AA15:AC15) -> 1
A16: 2024-01-23 | B16: 194.44215 | C16: 166.0665 | D16: 396.73175 | E16: =LN(B16/B15) -> 0.0066312339 | F16: =LN(C16/C15) -> -0.0066056077 | G16: =LN(D16/D15) -> 0.0060094334 | H16: =SUMPRODUCT(E16:G16,$K$15:$M$15) -> 0.0003466655 | P16: =SUMPRODUCT(E16:G16,$S$15:$U$15) -> 0.00034161855 | X16: =SUMPRODUCT(E16:G16,$AA$15:$AC$15) -> 0.0019357389
A17: 2024-01-24 | B17: 193.76472 | C17: 167.55037 | D17: 400.37183 | E17: =LN(B17/B16) -> -0.0034900458 | F17: =LN(C17/C16) -> 0.008895721 | G17: =LN(D17/D16) -> 0.00913332 | H17: =SUMPRODUCT(E17:G17,$K$15:$M$15) -> 0.0075196083 | J17: Retorno | K17: =AVERAGE(H3:H125) -> 0.0014254997 | M17: Rf | N17: 0.0452 | P17: =SUMPRODUCT(E17:G17,$S$15:$U$15) -> 0.0075251663 | R17: Retorno | S17: =AVERAGE(P3:P125) -> 0.0014256716 | X17: =SUMPRODUCT(E17:G17,$AA$15:$AC$15) -> 0.0068171636 | Z17: Retorno | AA17: =AVERAGE(X3:X125) -> 0.0014132818
A18: 2024-01-25 | B18: 193.43597 | C18: 169.94815 | D18: 402.66928 | E18: =LN(B18/B17) -> -0.0016980893 | F18: =LN(C18/C17) -> 0.014209376 | G18: =LN(D18/D17) -> 0.0057219015 | H18: =SUMPRODUCT(E18:G18,$K$15:$M$15) -> 0.0086967208 | J18: Riesgo SD | K18: {=SQRT(MMULT(MMULT(K15:M15,K5:M7),TRANSPOSE(K15:M15)))} -> 0.0079766322 | M18: Rf Diario | N18: =N17/250 -> 0.0001808 | P18: =SUMPRODUCT(E18:G18,$S$15:$U$15) -> 0.008703249 | R18: Riesgo SD | S18: {=MMULT(MMULT(S15:U15,S5:U7),TRANSPOSE(S15:U15))} -> 6.3644311e-05 | X18: =SUMPRODUCT(E18:G18,$AA$15:$AC$15) -> 0.0072217427 | Z18: Riesgo SD | AA18: {=MMULT(MMULT(AA15:AC15,AA5:AC7),TRANSPOSE(AA15:AC15))} -> 6.675614e-05
A19: 2024-01-26 | B19: 191.6926 | C19: 169.29958 | D19: 401.73438 | E19: =LN(B19/B18) -> -0.009053546 | F19: =LN(C19/C18) -> -0.0038236105 | G19: =LN(D19/D18) -> -0.0023244708 | H19: =SUMPRODUCT(E19:G19,$K$15:$M$15) -> -0.0038088477 | J19: Sharpe SD | K19: =(K17-N18)/K18 -> 0.15604326 | P19: =SUMPRODUCT(E19:G19,$S$15:$U$15) -> -0.0038064038 | R19: Riesgo VaR | S19: =STDEV(P3:P125)*NORMSINV(1-95%)*SQRT(1) -> -0.013126232 | X19: =SUMPRODUCT(E19:G19,$AA$15:$AC$15) -> -0.0040143306 | Z19: Riesgo VaR | AA19: =STDEV(X3:X125)*NORMSINV(1-95%)*SQRT(1) -> -0.013446842
A20: 2024-01-29 | B20: 191.0052 | C20: 169.74178 | D20: 407.49292 | E20: =LN(B20/B19) -> -0.003592359 | F20: =LN(C20/C19) -> 0.0026085311 | G20: =LN(D20/D19) -> 0.014232447 | H20: =SUMPRODUCT(E20:G20,$K$15:$M$15) -> 0.006820183 | P20: =SUMPRODUCT(E20:G20,$S$15:$U$15) -> 0.0068237639 | R20: Sharpe VaR | S20: =-(S17-N18)/S19 -> 0.094838458 | X20: =SUMPRODUCT(E20:G20,$AA$15:$AC$15) -> 0.0072180083 | Z20: Riesgo CVaR | AA20: =AVERAGEIF(X3:X125,"<="&AA19,X3:X125) -> -0.018511155
A21: 2024-01-30 | B21: 187.32915 | C21: 173.22055 | D21: 406.36908 | E21: =LN(B21/B20) -> -0.019433454 | F21: =LN(C21/C20) -> 0.020287326 | G21: =LN(D21/D20) -> -0.0027617483 | H21: =SUMPRODUCT(E21:G21,$K$15:$M$15) -> 0.0057317365 | P21: =SUMPRODUCT(E21:G21,$S$15:$U$15) -> 0.0057479085 | X21: =SUMPRODUCT(E21:G21,$AA$15:$AC$15) -> 0.0019278242 | Z21: Sharpe CVaR | AA21: =-(AA17-N18)/AA20 -> 0.066580492
A22: 2024-01-31 | B22: 183.70291 | C22: 171.3436 | D22: 395.41891 | E22: =LN(B22/B21) -> -0.019547375 | F22: =LN(C22/C21) -> -0.010894759 | G22: =LN(D22/D21) -> -0.027316063 | H22: =SUMPRODUCT(E22:G22,$K$15:$M$15) -> -0.018921543 | P22: =SUMPRODUCT(E22:G22,$S$15:$U$15) -> -0.018918812 | S22: AAPL | T22: JPM | U22: MSFT | X22: =SUMPRODUCT(E22:G22,$AA$15:$AC$15) -> -0.020492861
A23: 2024-02-01 | B23: 186.15363 | C23: 170.72449 | D23: 401.58521 | E23: =LN(B23/B22) -> 0.013252436 | F23: =LN(C23/C22) -> -0.0036198102 | G23: =LN(D23/D22) -> 0.015473981 | H23: =SUMPRODUCT(E23:G23,$K$15:$M$15) -> 0.0065257348 | P23: =SUMPRODUCT(E23:G23,$S$15:$U$15) -> 0.0065195109 | R23: VaR Activos | S23: =STDEV(E3:E125)*NORMSINV(1-95%)*SQRT(1) -> -0.02484257 | T23: =STDEV(F3:F125)*NORMSINV(1-95%)*SQRT(1) -> -0.019681987 | U23: =STDEV(G3:G125)*NORMSINV(1-95%)*SQRT(1) -> -0.019688639 | X23: =SUMPRODUCT(E23:G23,$AA$15:$AC$15) -> 0.0087475936 | AA23: AAPL | AB23: JPM | AC23: MSFT
A24: 2024-02-02 | B24: 185.14743 | C24: 171.70718 | D24: 408.98474 | E24: =LN(B24/B23) -> -0.0054198476 | F24: =LN(C24/C23) -> 0.0057395345 | G24: =LN(D24/D23) -> 0.01825812 | H24: =SUMPRODUCT(E24:G24,$K$15:$M$15) -> 0.0097408489 | P24: =SUMPRODUCT(E24:G24,$S$15:$U$15) -> 0.0097467102 | X24: =SUMPRODUCT(E24:G24,$AA$15:$AC$15) -> 0.0099095463 | Z24: CVaR | AA24: =AVERAGEIF(E3:E125,"<"&S23,E3:E125) -> -0.032092581 | AB24: =AVERAGEIF(F3:F125,"<"&T23,F3:F125) -> -0.046511046 | AC24: =AVERAGEIF(G3:G125,"<"&U23,G3:G125) -> -0.026449913
A25: 2024-02-05 | B25: 186.9705 | C25: 171.48116 | D25: 403.44507 | E25: =LN(B25/B24) -> 0.0097984473 | F25: =LN(C25/C24) -> -0.0013172268 | G25: =LN(D25/D24) -> -0.013637507 | H25: =SUMPRODUCT(E25:G25,$K$15:$M$15) -> -0.0052392854 | P25: =SUMPRODUCT(E25:G25,$S$15:$U$15) -> -0.0052451134 | X25: =SUMPRODUCT(E25:G25,$AA$15:$AC$15) -> -0.0053975975
A26: 2024-02-06 | B26: 188.5844 | C26: 172.07079 | D26: 403.28589 | E26: =LN(B26/B25) -> 0.0085947569 | F26: =LN(C26/C25) -> 0.0034325562 | G26: =LN(D26/D25) -> -0.00039462897 | H26: =SUMPRODUCT(E26:G26,$K$15:$M$15) -> 0.0024180714 | P26: =SUMPRODUCT(E26:G26,$S$15:$U$15) -> 0.0024154962 | X26: =SUMPRODUCT(E26:G26,$AA$15:$AC$15) -> 0.0024679654
A27: 2024-02-07 | B27: 188.69398 | C27: 172.39507 | D27: 411.79941 | E27: =LN(B27/B26) -> 0.00058094292 | F27: =LN(C27/C26) -> 0.0018827985 | G27: =LN(D27/D26) -> 0.020890645 | H27: =SUMPRODUCT(E27:G27,$K$15:$M$15) -> 0.009824009 | P27: =SUMPRODUCT(E27:G27,$S$15:$U$15) -> 0.0098259103 | X27: =SUMPRODUCT(E27:G27,$AA$15:$AC$15) -> 0.010986833
A28: 2024-02-08 | B28: 187.60811 | C28: 171.77599 | D28: 411.85904 | E28: =LN(B28/B27) -> -0.005771318 | F28: =LN(C28/C27) -> -0.003597515 | G28: =LN(D28/D27) -> 0.00014479618 | H28: =SUMPRODUCT(E28:G28,$K$15:$M$15) -> -0.0022627399 | P28: =SUMPRODUCT(E28:G28,$S$15:$U$15) -> -0.0022615077 | X28: =SUMPRODUCT(E28:G28,$AA$15:$AC$15) -> -0.0021449449
A29: 2024-02-09 | B29: 188.37616 | C29: 171.98235 | D29: 418.26404 | E29: =LN(B29/B28) -> 0.0040855553 | F29: =LN(C29/C28) -> 0.0012006105 | G29: =LN(D29/D28) -> 0.01543175 | H29: =SUMPRODUCT(E29:G29,$K$15:$M$15) -> 0.0076065409 | P29: =SUMPRODUCT(E29:G29,$S$15:$U$15) -> 0.0076062376 | X29: =SUMPRODUCT(E29:G29,$AA$15:$AC$15) -> 0.0087008637
A30: 2024-02-12 | B30: 186.68042 | C30: 172.74884 | D30: 413.00284 | E30: =LN(B30/B29) -> -0.0090426429 | F30: =LN(C30/C29) -> 0.0044469198 | G30: =LN(D30/D29) -> -0.012658438 | H30: =SUMPRODUCT(E30:G30,$K$15:$M$15) -> -0.0044481705 | P30: =SUMPRODUCT(E30:G30,$S$15:$U$15) -> -0.004443322 | X30: =SUMPRODUCT(E30:G30,$AA$15:$AC$15) -> -0.0063444185
A31: 2024-02-13 | B31: 184.57571 | C31: 171.24532 | D31: 404.11139 | E31: =LN(B31/B30) -> -0.011338417 | F31: =LN(C31/C30) -> -0.0087416268 | G31: =LN(D31/D30) -> -0.021763909 | H31: =SUMPRODUCT(E31:G31,$K$15:$M$15) -> -0.014598268 | P31: =SUMPRODUCT(E31:G31,$S$15:$U$15) -> -0.01459801 | X31: =SUMPRODUCT(E31:G31,$AA$15:$AC$15) -> -0.015597137
A32: 2024-02-14 | B32: 183.68794 | C32: 172.9847 | D32: 408.01727 | E32: =LN(B32/B31) -> -0.0048214007 | F32: =LN(C32/C31) -> 0.010106002 | G32: =LN(D32/D31) -> 0.0096189532 | H32: =SUMPRODUCT(E32:G32,$K$15:$M$15) -> 0.0081180669 | P32: =SUMPRODUCT(E32:G32,$S$15:$U$15) -> 0.0081247117 | X32: =SUMPRODUCT(E32:G32,$AA$15:$AC$15) -> 0.007221092
A33: 2024-02-15 | B33: 183.39868 | C33: 176.75827 | D33: 405.09784 | E33: =LN(B33/B32) -> -0.001575982 | F33: =LN(C33/C32) -> 0.02157997 | G33: =LN(D33/D32) -> -0.0071808924 | H33: =SUMPRODUCT(E33:G33,$K$15:$M$15) -> 0.0065671938 | P33: =SUMPRODUCT(E33:G33,$S$15:$U$15) -> 0.0065755584 | X33: =SUMPRODUCT(E33:G33,$AA$15:$AC$15) -> 0.0033513385
A34: 2024-02-16 | B34: 181.85255 | C34: 175.9328 | D34: 402.60684 | E34: =LN(B34/B33) -> -0.0084661536 | F34: =LN(C34/C33) -> -0.004680989 | G34: =LN(D34/D33) -> -0.0061681091 | H34: =SUMPRODUCT(E34:G34,$K$15:$M$15) -> -0.005765913 | P34: =SUMPRODUCT(E34:G34,$S$15:$U$15) -> -0.0057643227 | X34: =SUMPRODUCT(E34:G34,$AA$15:$AC$15) -> -0.0060821946
A35: 2024-02-20 | B35: 181.10445 | C35: 176.62068 | D35: 401.3414 | E35: =LN(B35/B34) -> -0.0041223008 | F35: =LN(C35/C34) -> 0.0039022866 | G35: =LN(D35/D34) -> -0.0031480707 | H35: =SUMPRODUCT(E35:G35,$K$15:$M$15) -> -5.7986401e-05 | P35: =SUMPRODUCT(E35:G35,$S$15:$U$15) -> -5.4885344e-05 | X35: =SUMPRODUCT(E35:G35,$AA$15:$AC$15) -> -0.00098242238
A36: 2024-02-21 | B36: 181.86255 | C36: 177.77045 | D36: 400.73358 | E36: =LN(B36/B35) -> 0.0041772586 | F36: =LN(C36/C35) -> 0.006488701 | G36: =LN(D36/D35) -> -0.0015156157 | H36: =SUMPRODUCT(E36:G36,$K$15:$M$15) -> 0.0028035226 | P36: =SUMPRODUCT(E36:G36,$S$15:$U$15) -> 0.0028040014 | X36: =SUMPRODUCT(E36:G36,$AA$15:$AC$15) -> 0.0021480943
... A125: 2024-06-28 | B125: 210.37648 | C125: 199.92032 | D125: 446.14587 | E125: =LN(B125/B124) -> -0.016387734 | F125: =LN(C125/C124) -> 0.01539529 | G125: =LN(D125/D124) -> -0.013114188 | H125: =SUMPRODUCT(E125:G125,$K$15:$M$15) -> -0.00053940675 | P125: =SUMPRODUCT(E125:G125,$S$15:$U$15) -> -0.00052716497 | X125: =SUMPRODUCT(E125:G125,$AA$15:$AC$15) -> -0.0042389414

Sheet RiskSim
A1: SLoYkPQu0APGq0MGAJtL/Znx8FCpo3cRlNPQCK/SFyLT/B4QTyMLOyBSaZwWhemND+QaxRaqbaokYwzkNEKoudMcp2llkonQIJ8RUhZJLOcPf2KwlDB5vgyLtFsNjh9EnCdjI3bdFnNru3MQvVP68pLjTs1Ebhh5aWEnoJXwgMOw5JbeZDEVdhYD46hUVw72MNXCm4OHn5HIa8OrHDPNCDMhyPJJKX+hfq5QpBAvnlz8fFXn4OdGPRGRFdk=
A2: T2a7vcJY8J2+z0mX6gRaNagWwrZIfxPoekbaItC/DSSe1cem8TSS+Kvyhvf24QZhXISq/X4mD/EWa8vVLE4dzJNDedyREdfBMjJ9dhm+aRn0vXP232GxGGW/8cmIQ7lAr2S6r9kLXj/Ek1LHi/uQLCHNQ8v3u09iBQIees9ijrBxckAI7+z459S+pp+y0CxRvAEuRkcDbXF6CYBAo6D6fYtuvc7UqtXAObQdMK8p0WG83A906d6+LVtIbxg=
A3: 7A5bNajf2TFfp/E4YGD+Nr/7/Pm1zuVMsNY0ybMwOjo1OnPXmdmFJc3UME3/Zn4IZKLkDoNz4XtkDBrH/Q7PiSWYYzIesMvcIhK7MAoiUeeRqHWZebhdyB5I0uL+pAWW6+GaogivWEY5knZQmcDtAfZXFjKRfKmQWSXTpHcF91/kLwje96Y1d5OM4eJ9kkbgKTxHq5bxpYsnbe/fOjIwUB9dRziww+pHuM63fifM4ULVEpoCsTRX9IAouN4=
A4: 9DQSPsqoGyKknCmm61UvtfwWJacEa4cAljTfje99pSxbjAwWjLv5rktXHg3HK1uaEIxAhNAS3U5k0XulY4sAT0QIY+/531IXda7CSURY/w7zzW9qaReEErZVIhVfP2cBWVuuLtQjNumu33dbXoCf9u0Hgw+1NmL+wBBiEW8kmh8N2m1lO7Y+rHW1bY9Mw7L22uhBYBZLHgn4gu7T0lkbv3oKNIrddOoBGK4dQ7dY4stIb09bejYKf3ZX2nM=
A5: Zi1iVarUxV0eFrpsrdbo4WWWhc82X9rUGd30kmdwe5on7UD2g9bkLdNRRr/29QVQqab/vmrRjpDOUli4CmWYvXg26Q5XP5amuJdK7M5qV6qpCsHjq/6SU2PN4h1rSef6f2v8ARQQIIXXaGM8cM1QSKmHaaswZ8iKBwM85VguELc2lSxXu4wWWWLs2iMBJPP2U85cU14B/z1cyObK7HFJGH1EWR4Ynn4sH2VS/Tj1bWW3anTa/VQM4QpUWTo=
A6: gvXComL7ZgteLTFNWqsMtTjM9s4WE0iYYh++UfiO5JBHqQ+GmSetj3md9EBZ0dn970uMI5dfbWywqJ3Wp7dkiVRDi/tAatOPtJqaFywxETzwlc9Npf+d9LeV5UUXeSH4EHdSAq/OuNxgs3TSoAV/9jTM5gTmehrMKiQp3yNQJch3XZEz3vlCKu0e0rdwxjMSYoAWqNg4dLatHZMdJONl9MEsj7xP5pkQrue5Hsw9VC61BkRIG14DAK4PsPM=
A7: SZTA2KEIrIymh2DUuiC4rdegfin7KWRF+kQ9F8ZwIHmQtSTCDLB7p6gzk2E1EZyl2F9Ffo1G3o/QL79h5NvWFDDZJ7B8QDL8DArippdI2dLKLgHgjBGlE4EwZXbRtat3JpOBS7lBb9yMN5OQcmMQCyTmwDIAlWeTtiCIMKRYg/TrCJb83U58kyOoX3um1C3pDV+NIGgBqft8hAaFL4iM2XkQoiI3OumzdbD2bby5ykMnBOrl+XAYOcZeKtY=
A8: LQEVHhq9AAXwVYGUzDYY7w/hHwWXfh0DDwnFDw2zuBoE0TL+232tz7MX26XuQGhRMzu/97KddCM3cWrx54bRbiT9eTVJF25I5MxevKbgIMEIW9ZmGYHPTmuN00kk1cxfluhUD7xrVmVK/S4fmcMNpaGsxP0NA4L3maeGrw/gOsCyFx5tAFT0rRDkexRakO16SJ4azgOO5RCdepxS8M1ntBnVPAfs8H+wkum1uc4sN4jRWNv6fvrbqcPL9TI=
A9: 5E9pNi4Mfj+lc5K+0pdq8ExCfs9+hE+8ibba7TQ4bRL9OerUduYf0T87kv6oaIpAKJCGJDE7/GvoPN+RUblqXBE5WLvSEvA6WJKCaoA5Kj4ZWq1ZaOHEsz1YY4956RUzc/dnztIDZZvJgrfof25oEjyFUmXmVdBfP3tubmj4azbN9M5hXCxT4ao6MaA25uQ/q3B4QgCQFcHe51xBwrv09VeBojsrPwEO+Tlc+gZXac5N4LYrqWjvZmSsgko=
A10: mew55anf7a6xtdeS9OTSDK2tAdJXINVQEf9mRP5GFpSSZ1RWpeQNYfFHHB7bhtHrh8YPrijEbOX8sEpZtRl+Eiu+I11CucjTx5yJcDMhBHM+Dc2XdZz+O04yX8KvE2zmYpsPUkdVE9po8NKb/NUrfmc3IHaOVPJTyJWvUcDXto5T1DNyuPXrN2zcw6hr+eIRSoAB/irfTPmf3CxdY+BBuPv9GD84X9z/zU+K1yQtqNLxwopPapcfAY6nyvs=
A11: y0qP9JIPba87sEI8cLfowiLL75njcy6B4Twa+r5rAsniCaWhScm/QgXzhG7YAUzyK03LznRYDhPd4p+M76u7QmssJGynuLnaasLiTkOI0wngnkS3AHXVR/kixmdkJVuzzpRsNWs1ZpfFAz8q2hoRGkqzadb68MFl+7d5yE+AzY+GWCmtvv5eCC6GN6y/8eMZoNGSwtKwIffiIi15tnmbFRlwfpWQV4Ayg+7wtxbyhuABFtSLrBl1P5KUMIA=
A12: XELWMnr/C+mnrFt7FMDjV//IgqGztibx5kUxhYZe6eRR3JXh5DVOiJbZLF8Q9VcW58zIL5uF8Smepm8ijC7zZN9kMvVxeD+6zpadg4d8vq+Wq+74fDh+waiH0iGEIC4JoGZ+QofGyUELkxh2vodWFxVoDRjwcYrODE5QUzC2N7eE20G4Va/whB4Beq+FGA9poxPT7KlG8OQs6n/bhdPhFs66AVyddEAG2+4QbBKKg/NRFcRh8cw9Z25oOUk=
... A919: QH2PJRqsOCb9GivWyr781aHR3Cvw5K+4AXRiB0XZfJP9YZ1cBm9Y+Q==

Sheet VaR SD
A1: =Portafolio!A1 -> fecha
A2: =Portafolio!A2 -> 2024-01-02 | B2: =Portafolio!E2 -> AAPL | C2: =Portafolio!F2 -> JPM | D2: =Portafolio!G2 -> MSFT | E2: =Portafolio!H2 -> Portafolio
A3: =Portafolio!A3 -> 2024-01-03 | B3: =Portafolio!E3 -> -0.0075157276 | C3: =Portafolio!F3 -> -0.0043679949 | D3: =Portafolio!G3 -> -0.00072826083 | E3: =Portafolio!H3 -> -0.003193079 | G3: VaR Delta- Normal
A4: =Portafolio!A4 -> 2024-01-04 | B4: =Portafolio!E4 -> -0.012781429 | C4: =Portafolio!F4 -> 0.0066141592 | D4: =Portafolio!G4 -> -0.0072035078 | E4: =Portafolio!H4 -> -0.0015849665
A5: =Portafolio!A5 -> 2024-01-05 | B5: =Portafolio!E5 -> -0.0040211799 | C5: =Portafolio!F5 -> 0.0050046725 | D5: =Portafolio!G5 -> -0.0005164319 | E5: =Portafolio!H5 -> 0.0015763662 | G5: Nivel de Confianza | H5: 0.95
A6: =Portafolio!A6 -> 2024-01-08 | B6: =Portafolio!E6 -> 0.023887306 | C6: =Portafolio!F6 -> -0.0014522139 | D6: =Portafolio!G6 -> 0.018695673 | E6: =Portafolio!H6 -> 0.010152267 | G6: Horizonte de tiempo | H6: 1
A7: =Portafolio!A7 -> 2024-01-09 | B7: =Portafolio!E7 -> -0.0022659785 | C7: =Portafolio!F7 -> -0.0079374717 | D7: =Portafolio!G7 -> 0.0029313879 | E7: =Portafolio!H7 -> -0.0026313546
A8: =Portafolio!A8 -> 2024-01-10 | B8: =Portafolio!E8 -> 0.0056553893 | C8: =Portafolio!F8 -> 0.0021072531 | D8: =Portafolio!G8 -> 0.018403858 | E8: =Portafolio!H8 -> 0.0094720816 | H8: AAPL | I8: JPM | J8: MSFT | K8: Portafolio
A9: =Portafolio!A9 -> 2024-01-11 | B9: =Portafolio!E9 -> -0.0032277218 | C9: =Portafolio!F9 -> -0.0042189561 | D9: =Portafolio!G9 -> 0.0048475314 | E9: =Portafolio!H9 -> -0.00023880911 | G9: Desviación Estandar | H9: =STDEV(B3:B125) -> 0.01510321 | I9: =STDEV(C3:C125) -> 0.011965798 | J9: =STDEV(D3:D125) -> 0.011969843 | K9: =STDEV(E3:E125) -> 0.0079790845
A10: =Portafolio!A10 -> 2024-01-12 | B10: =Portafolio!E10 -> 0.0017765238 | C10: =Portafolio!F10 -> -0.0073670772 | D10: =Portafolio!G10 -> 0.0099341008 | E10: =Portafolio!H10 -> 0.0010930566 | G10: VaR por activo | H10: =H9*NORMSINV(1-$H$5)*SQRT($H$6) -> -0.02484257 | I10: =I9*NORMSINV(1-$H$5)*SQRT($H$6) -> -0.019681987 | J10: =J9*NORMSINV(1-$H$5)*SQRT($H$6) -> -0.019688639 | K10: =K9*NORMSINV(1-$H$5)*SQRT($H$6) -> -0.013124426
A11: =Portafolio!A11 -> 2024-01-16 | B11: =Portafolio!E11 -> -0.012393602 | C11: =Portafolio!F11 -> -0.0062900411 | D11: =Portafolio!G11 -> 0.0046228765 | E11: =Portafolio!H11 -> -0.0023696334
A12: =Portafolio!A12 -> 2024-01-17 | B12: =Portafolio!E12 -> -0.0051868884 | C12: =Portafolio!F12 -> -0.0053719561 | D12: =Portafolio!G12 -> -0.0020519739 | E12: =Portafolio!H12 -> -0.0039357185 | G12: VaR(%) No Diversificado | H12: =SUM(H10:J10) -> -0.064213196 | J12: CVaR
A13: =Portafolio!A13 -> 2024-01-18 | B13: =Portafolio!E13 -> 0.032051509 | C13: =Portafolio!F13 -> 0.00197306 | D13: =Portafolio!G13 -> 0.011234026 | E13: =Portafolio!H13 -> 0.0095054398 | G13: VaR(%) Diversificado | H13: =K10 -> -0.013124426 | J13: =AVERAGEIF(E3:E125,"<"&H13,$E$3:$E$125) -> -0.020743251
A14: =Portafolio!A14 -> 2024-01-19 | B14: =Portafolio!E14 -> 0.015413603 | C14: =Portafolio!F14 -> 0.017114639 | D14: =Portafolio!G14 -> 0.012113144 | E14: =Portafolio!H14 -> 0.014781335
A15: =Portafolio!A15 -> 2024-01-22 | B15: =Portafolio!E15 -> 0.012089863 | C15: =Portafolio!F15 -> -0.00117507 | D15: =Portafolio!G15 -> -0.0054326563 | E15: =Portafolio!H15 -> -0.0014064286 | G15: Exposición | H15: 100000000
A16: =Portafolio!A16 -> 2024-01-23 | B16: =Portafolio!E16 -> 0.0066312339 | C16: =Portafolio!F16 -> -0.0066056077 | D16: =Portafolio!G16 -> 0.0060094334 | E16: =Portafolio!H16 -> 0.0003466655 | G16: VaR($) No Diversificado | H16: =H12*H15 -> -6421319.6
A17: =Portafolio!A17 -> 2024-01-24 | B17: =Portafolio!E17 -> -0.0034900458 | C17: =Portafolio!F17 -> 0.008895721 | D17: =Portafolio!G17 -> 0.00913332 | E17: =Portafolio!H17 -> 0.0075196083 | G17: VaR($) Diversificado | H17: =H13*H15 -> -1312442.6
A18: =Portafolio!A18 -> 2024-01-25 | B18: =Portafolio!E18 -> -0.0016980893 | C18: =Portafolio!F18 -> 0.014209376 | D18: =Portafolio!G18 -> 0.0057219015 | E18: =Portafolio!H18 -> 0.0086967208
A19: =Portafolio!A19 -> 2024-01-26 | B19: =Portafolio!E19 -> -0.009053546 | C19: =Portafolio!F19 -> -0.0038236105 | D19: =Portafolio!G19 -> -0.0023244708 | E19: =Portafolio!H19 -> -0.0038088477
A20: =Portafolio!A20 -> 2024-01-29 | B20: =Portafolio!E20 -> -0.003592359 | C20: =Portafolio!F20 -> 0.0026085311 | D20: =Portafolio!G20 -> 0.014232447 | E20: =Portafolio!H20 -> 0.006820183
A21: =Portafolio!A21 -> 2024-01-30 | B21: =Portafolio!E21 -> -0.019433454 | C21: =Portafolio!F21 -> 0.020287326 | D21: =Portafolio!G21 -> -0.0027617483 | E21: =Portafolio!H21 -> 0.0057317365
A22: =Portafolio!A22 -> 2024-01-31 | B22: =Portafolio!E22 -> -0.019547375 | C22: =Portafolio!F22 -> -0.010894759 | D22: =Portafolio!G22 -> -0.027316063 | E22: =Portafolio!H22 -> -0.018921543
A23: =Portafolio!A23 -> 2024-02-01 | B23: =Portafolio!E23 -> 0.013252436 | C23: =Portafolio!F23 -> -0.0036198102 | D23: =Portafolio!G23 -> 0.015473981 | E23: =Portafolio!H23 -> 0.0065257348
A24: =Portafolio!A24 -> 2024-02-02 | B24: =Portafolio!E24 -> -0.0054198476 | C24: =Portafolio!F24 -> 0.0057395345 | D24: =Portafolio!G24 -> 0.01825812 | E24: =Portafolio!H24 -> 0.0097408489
A25: =Portafolio!A25 -> 2024-02-05 | B25: =Portafolio!E25 -> 0.0097984473 | C25: =Portafolio!F25 -> -0.0013172268 | D25: =Portafolio!G25 -> -0.013637507 | E25: =Portafolio!H25 -> -0.0052392854
A26: =Portafolio!A26 -> 2024-02-06 | B26: =Portafolio!E26 -> 0.0085947569 | C26: =Portafolio!F26 -> 0.0034325562 | D26: =Portafolio!G26 -> -0.00039462897 | E26: =Portafolio!H26 -> 0.0024180714
A27: =Portafolio!A27 -> 2024-02-07 | B27: =Portafolio!E27 -> 0.00058094292 | C27: =Portafolio!F27 -> 0.0018827985 | D27: =Portafolio!G27 -> 0.020890645 | E27: =Portafolio!H27 -> 0.009824009
A28: =Portafolio!A28 -> 2024-02-08 | B28: =Portafolio!E28 -> -0.005771318 | C28: =Portafolio!F28 -> -0.003597515 | D28: =Portafolio!G28 -> 0.00014479618 | E28: =Portafolio!H28 -> -0.0022627399
A29: =Portafolio!A29 -> 2024-02-09 | B29: =Portafolio!E29 -> 0.0040855553 | C29: =Portafolio!F29 -> 0.0012006105 | D29: =Portafolio!G29 -> 0.01543175 | E29: =Portafolio!H29 -> 0.0076065409
... A125: =Portafolio!A125 -> 2024-06-28 | B125: =Portafolio!E125 -> -0.016387734 | C125: =Portafolio!F125 -> 0.01539529 | D125: =Portafolio!G125 -> -0.013114188 | E125: =Portafolio!H125 -> -0.00053940675

Sheet VaR Semi-SD
A1: =Portafolio!A1 -> fecha
A2: =Portafolio!A2 -> 2024-01-02 | B2: =Portafolio!E2 -> AAPL | C2: =Portafolio!F2 -> JPM | D2: =Portafolio!G2 -> MSFT | E2: =Portafolio!H2 -> Portafolio | F2: AAPL | G2: JPM | H2: MSFT | I2: Portafolio
A3: =Portafolio!A3 -> 2024-01-03 | B3: =Portafolio!E3 -> -0.0075157276 | C3: =Portafolio!F3 -> -0.0043679949 | D3: =Portafolio!G3 -> -0.00072826083 | E3: =Portafolio!H3 -> -0.003193079 | F3: =MIN((B3-AVERAGE($B$3:$B$125)),0)^2 -> 7.3333654e-05 | G3: =MIN((C3-AVERAGE($C$3:$C$125)),0)^2 -> 3.339725e-05 | H3: =MIN((D3-AVERAGE($D$3:$D$125)),0)^2 -> 5.175473e-06 | I3: =MIN((E3-AVERAGE($E$3:$E$125)),0)^2 -> 2.1331269e-05 | K3: VaR Delta- Normal
A4: =Portafolio!A4 -> 2024-01-04 | B4: =Portafolio!E4 -> -0.012781429 | C4: =Portafolio!F4 -> 0.0066141592 | D4: =Portafolio!G4 -> -0.0072035078 | E4: =Portafolio!H4 -> -0.0015849665 | F4: =MIN((B4-AVERAGE($B$3:$B$125)),0)^2 -> 0.000191247 | G4: =MIN((C4-AVERAGE($C$3:$C$125)),0)^2 -> 0 | H4: =MIN((D4-AVERAGE($D$3:$D$125)),0)^2 -> 7.6566237e-05 | I4: =MIN((E4-AVERAGE($E$3:$E$125)),0)^2 -> 9.0629067e-06
A5: =Portafolio!A5 -> 2024-01-05 | B5: =Portafolio!E5 -> -0.0040211799 | C5: =Portafolio!F5 -> 0.0050046725 | D5: =Portafolio!G5 -> -0.0005164319 | E5: =Portafolio!H5 -> 0.0015763662 | F5: =MIN((B5-AVERAGE($B$3:$B$125)),0)^2 -> 2.5694349e-05 | G5: =MIN((C5-AVERAGE($C$3:$C$125)),0)^2 -> 0 | H5: =MIN((D5-AVERAGE($D$3:$D$125)),0)^2 -> 4.256537e-06 | I5: =MIN((E5-AVERAGE($E$3:$E$125)),0)^2 -> 0 | K5: Nivel de Confianza | L5: 0.95
A6: =Portafolio!A6 -> 2024-01-08 | B6: =Portafolio!E6 -> 0.023887306 | C6: =Portafolio!F6 -> -0.0014522139 | D6: =Portafolio!G6 -> 0.018695673 | E6: =Portafolio!H6 -> 0.010152267 | F6: =MIN((B6-AVERAGE($B$3:$B$125)),0)^2 -> 0 | G6: =MIN((C6-AVERAGE($C$3:$C$125)),0)^2 -> 8.1982255e-06 | H6: =MIN((D6-AVERAGE($D$3:$D$125)),0)^2 -> 0 | I6: =MIN((E6-AVERAGE($E$3:$E$125)),0)^2 -> 0 | K6: Horizonte de tiempo | L6: 1
A7: =Portafolio!A7 -> 2024-01-09 | B7: =Portafolio!E7 -> -0.0022659785 | C7: =Portafolio!F7 -> -0.0079374717 | D7: =Portafolio!G7 -> 0.0029313879 | E7: =Portafolio!H7 -> -0.0026313546 | F7: =MIN((B7-AVERAGE($B$3:$B$125)),0)^2 -> 1.0980992e-05 | G7: =MIN((C7-AVERAGE($C$3:$C$125)),0)^2 -> 8.739468e-05 | H7: =MIN((D7-AVERAGE($D$3:$D$125)),0)^2 -> 0 | I7: =MIN((E7-AVERAGE($E$3:$E$125)),0)^2 -> 1.6458066e-05
A8: =Portafolio!A8 -> 2024-01-10 | B8: =Portafolio!E8 -> 0.0056553893 | C8: =Portafolio!F8 -> 0.0021072531 | D8: =Portafolio!G8 -> 0.018403858 | E8: =Portafolio!H8 -> 0.0094720816 | F8: =MIN((B8-AVERAGE($B$3:$B$125)),0)^2 -> 0 | G8: =MIN((C8-AVERAGE($C$3:$C$125)),0)^2 -> 0 | H8: =MIN((D8-AVERAGE($D$3:$D$125)),0)^2 -> 0 | I8: =MIN((E8-AVERAGE($E$3:$E$125)),0)^2 -> 0 | L8: AAPL | M8: JPM | N8: MSFT | O8: Portafolio
A9: =Portafolio!A9 -> 2024-01-11 | B9: =Portafolio!E9 -> -0.0032277218 | C9: =Portafolio!F9 -> -0.0042189561 | D9: =Portafolio!G9 -> 0.0048475314 | E9: =Portafolio!H9 -> -0.00023880911 | F9: =MIN((B9-AVERAGE($B$3:$B$125)),0)^2 -> 1.8279912e-05 | G9: =MIN((C9-AVERAGE($C$3:$C$125)),0)^2 -> 3.1696861e-05 | H9: =MIN((D9-AVERAGE($D$3:$D$125)),0)^2 -> 0 | I9: =MIN((E9-AVERAGE($E$3:$E$125)),0)^2 -> 2.7699237e-06 | K9: Semi Desviación Estandar | L9: =SQRT(AVERAGE(F3:F125)) -> 0.0093930147 | M9: =SQRT(AVERAGE(G3:G125)) -> 0.0095252322 | N9: =SQRT(AVERAGE(H3:H125)) -> 0.008899706 | O9: =SQRT(AVERAGE(I3:I125)) -> 0.0061049844
A10: =Portafolio!A10 -> 2024-01-12 | B10: =Portafolio!E10 -> 0.0017765238 | C10: =Portafolio!F10 -> -0.0073670772 | D10: =Portafolio!G10 -> 0.0099341008 | E10: =Portafolio!H10 -> 0.0010930566 | F10: =MIN((B10-AVERAGE($B$3:$B$125)),0)^2 -> 0 | G10: =MIN((C10-AVERAGE($C$3:$C$125)),0)^2 -> 7.705535e-05 | H10: =MIN((D10-AVERAGE($D$3:$D$125)),0)^2 -> 0 | I10: =MIN((E10-AVERAGE($E$3:$E$125)),0)^2 -> 1.105184e-07 | K10: VaR por activo | L10: =L9*NORMSINV(1-$L$5)*SQRT($L$6) -> -0.015450134 | M10: =M9*NORMSINV(1-$L$5)*SQRT($L$6) -> -0.015667613 | N10: =N9*NORMSINV(1-$L$5)*SQRT($L$6) -> -0.014638714 | O10: =O9*NORMSINV(1-$L$5)*SQRT($L$6) -> -0.010041806
A11: =Portafolio!A11 -> 2024-01-16 | B11: =Portafolio!E11 -> -0.012393602 | C11: =Portafolio!F11 -> -0.0062900411 | D11: =Portafolio!G11 -> 0.0046228765 | E11: =Portafolio!H11 -> -0.0023696334 | F11: =MIN((B11-AVERAGE($B$3:$B$125)),0)^2 -> 0.00018067074 | G11: =MIN((C11-AVERAGE($C$3:$C$125)),0)^2 -> 5.9306658e-05 | H11: =MIN((D11-AVERAGE($D$3:$D$125)),0)^2 -> 0 | I11: =MIN((E11-AVERAGE($E$3:$E$125)),0)^2 -> 1.4403035e-05
A12: =Portafolio!A12 -> 2024-01-17 | B12: =Portafolio!E12 -> -0.0051868884 | C12: =Portafolio!F12 -> -0.0053719561 | D12: =Portafolio!G12 -> -0.0020519739 | E12: =Portafolio!H12 -> -0.0039357185 | F12: =MIN((B12-AVERAGE($B$3:$B$125)),0)^2 -> 3.8871084e-05 | G12: =MIN((C12-AVERAGE($C$3:$C$125)),0)^2 -> 4.6009042e-05 | H12: =MIN((D12-AVERAGE($D$3:$D$125)),0)^2 -> 1.2950496e-05 | I12: =MIN((E12-AVERAGE($E$3:$E$125)),0)^2 -> 2.8742661e-05 | K12: VaR(%) No Diversificado | L12: =SUM(L10:N10) -> -0.045756461 | N12: CVaR
A13: =Portafolio!A13 -> 2024-01-18 | B13: =Portafolio!E13 -> 0.032051509 | C13: =Portafolio!F13 -> 0.00197306 | D13: =Portafolio!G13 -> 0.011234026 | E13: =Portafolio!H13 -> 0.0095054398 | F13: =MIN((B13-AVERAGE($B$3:$B$125)),0)^2 -> 0 | G13: =MIN((C13-AVERAGE($C$3:$C$125)),0)^2 -> 0 | H13: =MIN((D13-AVERAGE($D$3:$D$125)),0)^2 -> 0 | I13: =MIN((E13-AVERAGE($E$3:$E$125)),0)^2 -> 0 | K13: VaR(%) Diversificado | L13: =O10 -> -0.010041806 | N13: =AVERAGEIF(E3:E125,"<"&L13,$E$3:$E$125) -> -0.01650035
A14: =Portafolio!A14 -> 2024-01-19 | B14: =Portafolio!E14 -> 0.015413603 | C14: =Portafolio!F14 -> 0.017114639 | D14: =Portafolio!G14 -> 0.012113144 | E14: =Portafolio!H14 -> 0.014781335 | F14: =MIN((B14-AVERAGE($B$3:$B$125)),0)^2 -> 0 | G14: =MIN((C14-AVERAGE($C$3:$C$125)),0)^2 -> 0 | H14: =MIN((D14-AVERAGE($D$3:$D$125)),0)^2 -> 0 | I14: =MIN((E14-AVERAGE($E$3:$E$125)),0)^2 -> 0
A15: =Portafolio!A15 -> 2024-01-22 | B15: =Portafolio!E15 -> 0.012089863 | C15: =Portafolio!F15 -> -0.00117507 | D15: =Portafolio!G15 -> -0.0054326563 | E15: =Portafolio!H15 -> -0.0014064286 | F15: =MIN((B15-AVERAGE($B$3:$B$125)),0)^2 -> 0 | G15: =MIN((C15-AVERAGE($C$3:$C$125)),0)^2 -> 6.6879674e-06 | H15: =MIN((D15-AVERAGE($D$3:$D$125)),0)^2 -> 4.8711495e-05 | I15: =MIN((E15-AVERAGE($E$3:$E$125)),0)^2 -> 8.0198176e-06 | K15: Exposición | L15: 100000000
A16: =Portafolio!A16 -> 2024-01-23 | B16: =Portafolio!E16 -> 0.0066312339 | C16: =Portafolio!F16 -> -0.0066056077 | D16: =Portafolio!G16 -> 0.0060094334 | E16: =Portafolio!H16 -> 0.0003466655 | F16: =MIN((B16-AVERAGE($B$3:$B$125)),0)^2 -> 0 | G16: =MIN((C16-AVERAGE($C$3:$C$125)),0)^2 -> 6.4266648e-05 | H16: =MIN((D16-AVERAGE($D$3:$D$125)),0)^2 -> 0 | I16: =MIN((E16-AVERAGE($E$3:$E$125)),0)^2 -> 1.1638831e-06 | K16: VaR($) No Diversificado | L16: =L12*L15 -> -4575646.1
A17: =Portafolio!A17 -> 2024-01-24 | B17: =Portafolio!E17 -> -0.0034900458 | C17: =Portafolio!F17 -> 0.008895721 | D17: =Portafolio!G17 -> 0.00913332 | E17: =Portafolio!H17 -> 0.0075196083 | F17: =MIN((B17-AVERAGE($B$3:$B$125)),0)^2 -> 2.0591858e-05 | G17: =MIN((C17-AVERAGE($C$3:$C$125)),0)^2 -> 0 | H17: =MIN((D17-AVERAGE($D$3:$D$125)),0)^2 -> 0 | I17: =MIN((E17-AVERAGE($E$3:$E$125)),0)^2 -> 0 | K17: VaR($) Diversificado | L17: =L13*L15 -> -1004180.6
A18: =Portafolio!A18 -> 2024-01-25 | B18: =Portafolio!E18 -> -0.0016980893 | C18: =Portafolio!F18 -> 0.014209376 | D18: =Portafolio!G18 -> 0.0057219015 | E18: =Portafolio!H18 -> 0.0086967208 | F18: =MIN((B18-AVERAGE($B$3:$B$125)),0)^2 -> 7.5397954e-06 | G18: =MIN((C18-AVERAGE($C$3:$C$125)),0)^2 -> 0 | H18: =MIN((D18-AVERAGE($D$3:$D$125)),0)^2 -> 0 | I18: =MIN((E18-AVERAGE($E$3:$E$125)),0)^2 -> 0
A19: =Portafolio!A19 -> 2024-01-26 | B19: =Portafolio!E19 -> -0.009053546 | C19: =Portafolio!F19 -> -0.0038236105 | D19: =Portafolio!G19 -> -0.0023244708 | E19: =Portafolio!H19 -> -0.0038088477 | F19: =MIN((B19-AVERAGE($B$3:$B$125)),0)^2 -> 0.00010203678 | G19: =MIN((C19-AVERAGE($C$3:$C$125)),0)^2 -> 2.7401571e-05 | H19: =MIN((D19-AVERAGE($D$3:$D$125)),0)^2 -> 1.4986008e-05 | I19: =MIN((E19-AVERAGE($E$3:$E$125)),0)^2 -> 2.7398392e-05
A20: =Portafolio!A20 -> 2024-01-29 | B20: =Portafolio!E20 -> -0.003592359 | C20: =Portafolio!F20 -> 0.0026085311 | D20: =Portafolio!G20 -> 0.014232447 | E20: =Portafolio!H20 -> 0.006820183 | F20: =MIN((B20-AVERAGE($B$3:$B$125)),0)^2 -> 2.1530885e-05 | G20: =MIN((C20-AVERAGE($C$3:$C$125)),0)^2 -> 0 | H20: =MIN((D20-AVERAGE($D$3:$D$125)),0)^2 -> 0 | I20: =MIN((E20-AVERAGE($E$3:$E$125)),0)^2 -> 0
A21: =Portafolio!A21 -> 2024-01-30 | B21: =Portafolio!E21 -> -0.019433454 | C21: =Portafolio!F21 -> 0.020287326 | D21: =Portafolio!G21 -> -0.0027617483 | E21: =Portafolio!H21 -> 0.0057317365 | F21: =MIN((B21-AVERAGE($B$3:$B$125)),0)^2 -> 0.00041948092 | G21: =MIN((C21-AVERAGE($C$3:$C$125)),0)^2 -> 0 | H21: =MIN((D21-AVERAGE($D$3:$D$125)),0)^2 -> 1.8562777e-05 | I21: =MIN((E21-AVERAGE($E$3:$E$125)),0)^2 -> 0
A22: =Portafolio!A22 -> 2024-01-31 | B22: =Portafolio!E22 -> -0.019547375 | C22: =Portafolio!F22 -> -0.010894759 | D22: =Portafolio!G22 -> -0.027316063 | E22: =Portafolio!H22 -> -0.018921543 | F22: =MIN((B22-AVERAGE($B$3:$B$125)),0)^2 -> 0.00042416038 | G22: =MIN((C22-AVERAGE($C$3:$C$125)),0)^2 -> 0.0001514327 | H22: =MIN((D22-AVERAGE($D$3:$D$125)),0)^2 -> 0.00083305942 | I22: =MIN((E22-AVERAGE($E$3:$E$125)),0)^2 -> 0.00041400216
A23: =Portafolio!A23 -> 2024-02-01 | B23: =Portafolio!E23 -> 0.013252436 | C23: =Portafolio!F23 -> -0.0036198102 | D23: =Portafolio!G23 -> 0.015473981 | E23: =Portafolio!H23 -> 0.0065257348 | F23: =MIN((B23-AVERAGE($B$3:$B$125)),0)^2 -> 0 | G23: =MIN((C23-AVERAGE($C$3:$C$125)),0)^2 -> 2.5309459e-05 | H23: =MIN((D23-AVERAGE($D$3:$D$125)),0)^2 -> 0 | I23: =MIN((E23-AVERAGE($E$3:$E$125)),0)^2 -> 0
A24: =Portafolio!A24 -> 2024-02-02 | B24: =Portafolio!E24 -> -0.0054198476 | C24: =Portafolio!F24 -> 0.0057395345 | D24: =Portafolio!G24 -> 0.01825812 | E24: =Portafolio!H24 -> 0.0097408489 | F24: =MIN((B24-AVERAGE($B$3:$B$125)),0)^2 -> 4.18302e-05 | G24: =MIN((C24-AVERAGE($C$3:$C$125)),0)^2 -> 0 | H24: =MIN((D24-AVERAGE($D$3:$D$125)),0)^2 -> 0 | I24: =MIN((E24-AVERAGE($E$3:$E$125)),0)^2 -> 0
A25: =Portafolio!A25 -> 2024-02-05 | B25: =Portafolio!E25 -> 0.0097984473 | C25: =Portafolio!F25 -> -0.0013172268 | D25: =Portafolio!G25 -> -0.013637507 | E25: =Portafolio!H25 -> -0.0052392854 | F25: =MIN((B25-AVERAGE($B$3:$B$125)),0)^2 -> 0 | G25: =MIN((C25-AVERAGE($C$3:$C$125)),0)^2 -> 7.4434421e-06 | H25: =MIN((D25-AVERAGE($D$3:$D$125)),0)^2 -> 0.00023056032 | I25: =MIN((E25-AVERAGE($E$3:$E$125)),0)^2 -> 4.4419359e-05
A26: =Portafolio!A26 -> 2024-02-06 | B26: =Portafolio!E26 -> 0.0085947569 | C26: =Portafolio!F26 -> 0.0034325562 | D26: =Portafolio!G26 -> -0.00039462897 | E26: =Portafolio!H26 -> 0.0024180714 | F26: =MIN((B26-AVERAGE($B$3:$B$125)),0)^2 -> 0 | G26: =MIN((C26-AVERAGE($C$3:$C$125)),0)^2 -> 0 | H26: =MIN((D26-AVERAGE($D$3:$D$125)),0)^2 -> 3.7687806e-06 | I26: =MIN((E26-AVERAGE($E$3:$E$125)),0)^2 -> 0
A27: =Portafolio!A27 -> 2024-02-07 | B27: =Portafolio!E27 -> 0.00058094292 | C27: =Portafolio!F27 -> 0.0018827985 | D27: =Portafolio!G27 -> 0.020890645 | E27: =Portafolio!H27 -> 0.009824009 | F27: =MIN((B27-AVERAGE($B$3:$B$125)),0)^2 -> 2.179364e-07 | G27: =MIN((C27-AVERAGE($C$3:$C$125)),0)^2 -> 0 | H27: =MIN((D27-AVERAGE($D$3:$D$125)),0)^2 -> 0 | I27: =MIN((E27-AVERAGE($E$3:$E$125)),0)^2 -> 0
A28: =Portafolio!A28 -> 2024-02-08 | B28: =Portafolio!E28 -> -0.005771318 | C28: =Portafolio!F28 -> -0.003597515 | D28: =Portafolio!G28 -> 0.00014479618 | E28: =Portafolio!H28 -> -0.0022627399 | F28: =MIN((B28-AVERAGE($B$3:$B$125)),0)^2 -> 4.650009e-05 | G28: =MIN((C28-AVERAGE($C$3:$C$125)),0)^2 -> 2.5085628e-05 | H28: =MIN((D28-AVERAGE($D$3:$D$125)),0)^2 -> 1.9653505e-06 | I28: =MIN((E28-AVERAGE($E$3:$E$125)),0)^2 -> 1.3603111e-05
A29: =Portafolio!A29 -> 2024-02-09 | B29: =Portafolio!E29 -> 0.0040855553 | C29: =Portafolio!F29 -> 0.0012006105 | D29: =Portafolio!G29 -> 0.01543175 | E29: =Portafolio!H29 -> 0.0076065409 | F29: =MIN((B29-AVERAGE($B$3:$B$125)),0)^2 -> 0 | G29: =MIN((C29-AVERAGE($C$3:$C$125)),0)^2 -> 4.4280789e-08 | H29: =MIN((D29-AVERAGE($D$3:$D$125)),0)^2 -> 0 | I29: =MIN((E29-AVERAGE($E$3:$E$125)),0)^2 -> 0
... A125: =Portafolio!A125 -> 2024-06-28 | B125: =Portafolio!E125 -> -0.016387734 | C125: =Portafolio!F125 -> 0.01539529 | D125: =Portafolio!G125 -> -0.013114188 | E125: =Portafolio!H125 -> -0.00053940675 | F125: =MIN((B125-AVERAGE($B$3:$B$125)),0)^2 -> 0.00030399714 | G125: =MIN((C125-AVERAGE($C$3:$C$125)),0)^2 -> 0 | H125: =MIN((D125-AVERAGE($D$3:$D$125)),0)^2 -> 0.00021494182 | I125: =MIN((E125-AVERAGE($E$3:$E$125)),0)^2 -> 3.8608572e-06

Sheet VaR No Parametrico
A1: =Portafolio!A1 -> fecha
A2: =Portafolio!A2 -> 2024-01-02 | B2: =Portafolio!E2 -> AAPL | C2: =Portafolio!F2 -> JPM | D2: =Portafolio!G2 -> MSFT | E2: =Portafolio!H2 -> Portafolio
A3: =Portafolio!A3 -> 2024-01-03 | B3: =Portafolio!E3 -> -0.0075157276 | C3: =Portafolio!F3 -> -0.0043679949 | D3: =Portafolio!G3 -> -0.00072826083 | E3: =Portafolio!H3 -> -0.003193079 | G3: VaR No-Parametrico
A4: =Portafolio!A4 -> 2024-01-04 | B4: =Portafolio!E4 -> -0.012781429 | C4: =Portafolio!F4 -> 0.0066141592 | D4: =Portafolio!G4 -> -0.0072035078 | E4: =Portafolio!H4 -> -0.0015849665
A5: =Portafolio!A5 -> 2024-01-05 | B5: =Portafolio!E5 -> -0.0040211799 | C5: =Portafolio!F5 -> 0.0050046725 | D5: =Portafolio!G5 -> -0.0005164319 | E5: =Portafolio!H5 -> 0.0015763662
A6: =Portafolio!A6 -> 2024-01-08 | B6: =Portafolio!E6 -> 0.023887306 | C6: =Portafolio!F6 -> -0.0014522139 | D6: =Portafolio!G6 -> 0.018695673 | E6: =Portafolio!H6 -> 0.010152267 | G6: Horizonte de tiempo | H6: 1
A7: =Portafolio!A7 -> 2024-01-09 | B7: =Portafolio!E7 -> -0.0022659785 | C7: =Portafolio!F7 -> -0.0079374717 | D7: =Portafolio!G7 -> 0.0029313879 | E7: =Portafolio!H7 -> -0.0026313546
A8: =Portafolio!A8 -> 2024-01-10 | B8: =Portafolio!E8 -> 0.0056553893 | C8: =Portafolio!F8 -> 0.0021072531 | D8: =Portafolio!G8 -> 0.018403858 | E8: =Portafolio!H8 -> 0.0094720816 | H8: AAPL | I8: JPM | J8: MSFT | K8: Portafolio
A9: =Portafolio!A9 -> 2024-01-11 | B9: =Portafolio!E9 -> -0.0032277218 | C9: =Portafolio!F9 -> -0.0042189561 | D9: =Portafolio!G9 -> 0.0048475314 | E9: =Portafolio!H9 -> -0.00023880911 | G9: Rentabilidad al 5% | H9: =_xlfn.PERCENTILE.INC(B3:B125,5%) -> -0.019535983 | I9: =_xlfn.PERCENTILE.INC(C3:C125,5%) -> -0.012300017 | J9: =_xlfn.PERCENTILE.INC(D3:D125,5%) -> -0.020798288 | K9: =_xlfn.PERCENTILE.INC(E3:E125,5%) -> -0.011206536
A10: =Portafolio!A10 -> 2024-01-12 | B10: =Portafolio!E10 -> 0.0017765238 | C10: =Portafolio!F10 -> -0.0073670772 | D10: =Portafolio!G10 -> 0.0099341008 | E10: =Portafolio!H10 -> 0.0010930566 | G10: VaR por activo | H10: =H9*SQRT($H$6) -> -0.019535983 | I10: =I9*SQRT($H$6) -> -0.012300017 | J10: =J9*SQRT($H$6) -> -0.020798288 | K10: =K9*SQRT($H$6) -> -0.011206536
A11: =Portafolio!A11 -> 2024-01-16 | B11: =Portafolio!E11 -> -0.012393602 | C11: =Portafolio!F11 -> -0.0062900411 | D11: =Portafolio!G11 -> 0.0046228765 | E11: =Portafolio!H11 -> -0.0023696334
A12: =Portafolio!A12 -> 2024-01-17 | B12: =Portafolio!E12 -> -0.0051868884 | C12: =Portafolio!F12 -> -0.0053719561 | D12: =Portafolio!G12 -> -0.0020519739 | E12: =Portafolio!H12 -> -0.0039357185 | G12: VaR(%) No Diversificado | H12: =SUM(H10:J10) -> -0.052634288 | J12: CVaR
A13: =Portafolio!A13 -> 2024-01-18 | B13: =Portafolio!E13 -> 0.032051509 | C13: =Portafolio!F13 -> 0.00197306 | D13: =Portafolio!G13 -> 0.011234026 | E13: =Portafolio!H13 -> 0.0095054398 | G13: VaR(%) Diversificado | H13: =K10 -> -0.011206536 | J13: =AVERAGEIF(E3:E125,"<"&H13,$E$3:$E$125) -> -0.018090595
A14: =Portafolio!A14 -> 2024-01-19 | B14: =Portafolio!E14 -> 0.015413603 | C14: =Portafolio!F14 -> 0.017114639 | D14: =Portafolio!G14 -> 0.012113144 | E14: =Portafolio!H14 -> 0.014781335
A15: =Portafolio!A15 -> 2024-01-22 | B15: =Portafolio!E15 -> 0.012089863 | C15: =Portafolio!F15 -> -0.00117507 | D15: =Portafolio!G15 -> -0.0054326563 | E15: =Portafolio!H15 -> -0.0014064286 | G15: Exposición | H15: 100000000
A16: =Portafolio!A16 -> 2024-01-23 | B16: =Portafolio!E16 -> 0.0066312339 | C16: =Portafolio!F16 -> -0.0066056077 | D16: =Portafolio!G16 -> 0.0060094334 | E16: =Portafolio!H16 -> 0.0003466655 | G16: VaR($) No Diversificado | H16: =H12*H15 -> -5263428.8
A17: =Portafolio!A17 -> 2024-01-24 | B17: =Portafolio!E17 -> -0.0034900458 | C17: =Portafolio!F17 -> 0.008895721 | D17: =Portafolio!G17 -> 0.00913332 | E17: =Portafolio!H17 -> 0.0075196083 | G17: VaR($) Diversificado | H17: =H13*H15 -> -1120653.6
A18: =Portafolio!A18 -> 2024-01-25 | B18: =Portafolio!E18 -> -0.0016980893 | C18: =Portafolio!F18 -> 0.014209376 | D18: =Portafolio!G18 -> 0.0057219015 | E18: =Portafolio!H18 -> 0.0086967208
A19: =Portafolio!A19 -> 2024-01-26 | B19: =Portafolio!E19 -> -0.009053546 | C19: =Portafolio!F19 -> -0.0038236105 | D19: =Portafolio!G19 -> -0.0023244708 | E19: =Portafolio!H19 -> -0.0038088477
A20: =Portafolio!A20 -> 2024-01-29 | B20: =Portafolio!E20 -> -0.003592359 | C20: =Portafolio!F20 -> 0.0026085311 | D20: =Portafolio!G20 -> 0.014232447 | E20: =Portafolio!H20 -> 0.006820183
A21: =Portafolio!A21 -> 2024-01-30 | B21: =Portafolio!E21 -> -0.019433454 | C21: =Portafolio!F21 -> 0.020287326 | D21: =Portafolio!G21 -> -0.0027617483 | E21: =Portafolio!H21 -> 0.0057317365
A22: =Portafolio!A22 -> 2024-01-31 | B22: =Portafolio!E22 -> -0.019547375 | C22: =Portafolio!F22 -> -0.010894759 | D22: =Portafolio!G22 -> -0.027316063 | E22: =Portafolio!H22 -> -0.018921543
A23: =Portafolio!A23 -> 2024-02-01 | B23: =Portafolio!E23 -> 0.013252436 | C23: =Portafolio!F23 -> -0.0036198102 | D23: =Portafolio!G23 -> 0.015473981 | E23: =Portafolio!H23 -> 0.0065257348
A24: =Portafolio!A24 -> 2024-02-02 | B24: =Portafolio!E24 -> -0.0054198476 | C24: =Portafolio!F24 -> 0.0057395345 | D24: =Portafolio!G24 -> 0.01825812 | E24: =Portafolio!H24 -> 0.0097408489
A25: =Portafolio!A25 -> 2024-02-05 | B25: =Portafolio!E25 -> 0.0097984473 | C25: =Portafolio!F25 -> -0.0013172268 | D25: =Portafolio!G25 -> -0.013637507 | E25: =Portafolio!H25 -> -0.0052392854
A26: =Portafolio!A26 -> 2024-02-06 | B26: =Portafolio!E26 -> 0.0085947569 | C26: =Portafolio!F26 -> 0.0034325562 | D26: =Portafolio!G26 -> -0.00039462897 | E26: =Portafolio!H26 -> 0.0024180714
A27: =Portafolio!A27 -> 2024-02-07 | B27: =Portafolio!E27 -> 0.00058094292 | C27: =Portafolio!F27 -> 0.0018827985 | D27: =Portafolio!G27 -> 0.020890645 | E27: =Portafolio!H27 -> 0.009824009
A28: =Portafolio!A28 -> 2024-02-08 | B28: =Portafolio!E28 -> -0.005771318 | C28: =Portafolio!F28 -> -0.003597515 | D28: =Portafolio!G28 -> 0.00014479618 | E28: =Portafolio!H28 -> -0.0022627399
A29: =Portafolio!A29 -> 2024-02-09 | B29: =Portafolio!E29 -> 0.0040855553 | C29: =Portafolio!F29 -> 0.0012006105 | D29: =Portafolio!G29 -> 0.01543175 | E29: =Portafolio!H29 -> 0.0076065409
... A125: =Portafolio!A125 -> 2024-06-28 | B125: =Portafolio!E125 -> -0.016387734 | C125: =Portafolio!F125 -> 0.01539529 | D125: =Portafolio!G125 -> -0.013114188 | E125: =Portafolio!H125 -> -0.00053940675

Sheet VaR Montecarlo
A1: =Portafolio!A1 -> fecha
A2: =Portafolio!A2 -> 2024-01-02 | B2: =Portafolio!E2 -> AAPL | C2: =Portafolio!F2 -> JPM | D2: =Portafolio!G2 -> MSFT | E2: =Portafolio!H2 -> Portafolio
A3: =Portafolio!A3 -> 2024-01-03 | B3: =Portafolio!E3 -> -0.0075157276 | C3: =Portafolio!F3 -> -0.0043679949 | D3: =Portafolio!G3 -> -0.00072826083 | E3: =Portafolio!H3 -> -0.003193079 | G3: VaR - Simulación por Montecarlo
A4: =Portafolio!A4 -> 2024-01-04 | B4: =Portafolio!E4 -> -0.012781429 | C4: =Portafolio!F4 -> 0.0066141592 | D4: =Portafolio!G4 -> -0.0072035078 | E4: =Portafolio!H4 -> -0.0015849665
A5: =Portafolio!A5 -> 2024-01-05 | B5: =Portafolio!E5 -> -0.0040211799 | C5: =Portafolio!F5 -> 0.0050046725 | D5: =Portafolio!G5 -> -0.0005164319 | E5: =Portafolio!H5 -> 0.0015763662 | G5: Horizonte de tiempo | H5: 1
A6: =Portafolio!A6 -> 2024-01-08 | B6: =Portafolio!E6 -> 0.023887306 | C6: =Portafolio!F6 -> -0.0014522139 | D6: =Portafolio!G6 -> 0.018695673 | E6: =Portafolio!H6 -> 0.010152267
A7: =Portafolio!A7 -> 2024-01-09 | B7: =Portafolio!E7 -> -0.0022659785 | C7: =Portafolio!F7 -> -0.0079374717 | D7: =Portafolio!G7 -> 0.0029313879 | E7: =Portafolio!H7 -> -0.0026313546 | H7: AAPL | I7: JPM | J7: MSFT | K7: Portafolio
A8: =Portafolio!A8 -> 2024-01-10 | B8: =Portafolio!E8 -> 0.0056553893 | C8: =Portafolio!F8 -> 0.0021072531 | D8: =Portafolio!G8 -> 0.018403858 | E8: =Portafolio!H8 -> 0.0094720816 | G8: Distribución Entrada | H8: 0.0010477795 | I8: 0.0014110405 | J8: 0.0015467058 | K8: 0.001366095
A9: =Portafolio!A9 -> 2024-01-11 | B9: =Portafolio!E9 -> -0.0032277218 | C9: =Portafolio!F9 -> -0.0042189561 | D9: =Portafolio!G9 -> 0.0048475314 | E9: =Portafolio!H9 -> -0.00023880911 | G9: Retronos Simulados al 5% | H9: =H8 -> 0.0010477795 | I9: =I8 -> 0.0014110405 | J9: =J8 -> 0.0015467058 | K9: =K8 -> 0.001366095
A10: =Portafolio!A10 -> 2024-01-12 | B10: =Portafolio!E10 -> 0.0017765238 | C10: =Portafolio!F10 -> -0.0073670772 | D10: =Portafolio!G10 -> 0.0099341008 | E10: =Portafolio!H10 -> 0.0010930566 | G10: VaR por activo | H10: {=_xll.ROV.RiskSim.RSFunctions.RSForecastStatistic(H9,"Percentile0.05")*SQRT($H$5)} -> -0.019217653 | I10: {=_xll.ROV.RiskSim.RSFunctions.RSForecastStatistic(I9,"Percentile0.05")*SQRT($H$5)} -> -0.014338209 | J10: {=_xll.ROV.RiskSim.RSFunctions.RSForecastStatistic(J9,"Percentile0.05")*SQRT($H$5)} -> -0.01745371 | K10: {=_xll.ROV.RiskSim.RSFunctions.RSForecastStatistic(K9,"Percentile0.05")*SQRT($H$5)} -> -0.010822775
A11: =Portafolio!A11 -> 2024-01-16 | B11: =Portafolio!E11 -> -0.012393602 | C11: =Portafolio!F11 -> -0.0062900411 | D11: =Portafolio!G11 -> 0.0046228765 | E11: =Portafolio!H11 -> -0.0023696334
A12: =Portafolio!A12 -> 2024-01-17 | B12: =Portafolio!E12 -> -0.0051868884 | C12: =Portafolio!F12 -> -0.0053719561 | D12: =Portafolio!G12 -> -0.0020519739 | E12: =Portafolio!H12 -> -0.0039357185 | G12: VaR(%) No Diversificado | H12: =SUM(H10:J10) -> -0.051009572 | J12: CVaR
A13: =Portafolio!A13 -> 2024-01-18 | B13: =Portafolio!E13 -> 0.032051509 | C13: =Portafolio!F13 -> 0.00197306 | D13: =Portafolio!G13 -> 0.011234026 | E13: =Portafolio!H13 -> 0.0095054398 | G13: VaR(%) Diversificado | H13: =K10 -> -0.010822775 | J13: =AVERAGEIF(E3:E125,"<"&H13,$E$3:$E$125) -> -0.017211633
A14: =Portafolio!A14 -> 2024-01-19 | B14: =Portafolio!E14 -> 0.015413603 | C14: =Portafolio!F14 -> 0.017114639 | D14: =Portafolio!G14 -> 0.012113144 | E14: =Portafolio!H14 -> 0.014781335
A15: =Portafolio!A15 -> 2024-01-22 | B15: =Portafolio!E15 -> 0.012089863 | C15: =Portafolio!F15 -> -0.00117507 | D15: =Portafolio!G15 -> -0.0054326563 | E15: =Portafolio!H15 -> -0.0014064286 | G15: Exposición | H15: 100000000
A16: =Portafolio!A16 -> 2024-01-23 | B16: =Portafolio!E16 -> 0.0066312339 | C16: =Portafolio!F16 -> -0.0066056077 | D16: =Portafolio!G16 -> 0.0060094334 | E16: =Portafolio!H16 -> 0.0003466655 | G16: VaR($) No Diversificado | H16: =H12*H15 -> -5100957.2
A17: =Portafolio!A17 -> 2024-01-24 | B17: =Portafolio!E17 -> -0.0034900458 | C17: =Portafolio!F17 -> 0.008895721 | D17: =Portafolio!G17 -> 0.00913332 | E17: =Portafolio!H17 -> 0.0075196083 | G17: VaR($) Diversificado | H17: =H13*H15 -> -1082277.5
A18: =Portafolio!A18 -> 2024-01-25 | B18: =Portafolio!E18 -> -0.0016980893 | C18: =Portafolio!F18 -> 0.014209376 | D18: =Portafolio!G18 -> 0.0057219015 | E18: =Portafolio!H18 -> 0.0086967208
A19: =Portafolio!A19 -> 2024-01-26 | B19: =Portafolio!E19 -> -0.009053546 | C19: =Portafolio!F19 -> -0.0038236105 | D19: =Portafolio!G19 -> -0.0023244708 | E19: =Portafolio!H19 -> -0.0038088477
A20: =Portafolio!A20 -> 2024-01-29 | B20: =Portafolio!E20 -> -0.003592359 | C20: =Portafolio!F20 -> 0.0026085311 | D20: =Portafolio!G20 -> 0.014232447 | E20: =Portafolio!H20 -> 0.006820183
A21: =Portafolio!A21 -> 2024-01-30 | B21: =Portafolio!E21 -> -0.019433454 | C21: =Portafolio!F21 -> 0.020287326 | D21: =Portafolio!G21 -> -0.0027617483 | E21: =Portafolio!H21 -> 0.0057317365
A22: =Portafolio!A22 -> 2024-01-31 | B22: =Portafolio!E22 -> -0.019547375 | C22: =Portafolio!F22 -> -0.010894759 | D22: =Portafolio!G22 -> -0.027316063 | E22: =Portafolio!H22 -> -0.018921543
A23: =Portafolio!A23 -> 2024-02-01 | B23: =Portafolio!E23 -> 0.013252436 | C23: =Portafolio!F23 -> -0.0036198102 | D23: =Portafolio!G23 -> 0.015473981 | E23: =Portafolio!H23 -> 0.0065257348
A24: =Portafolio!A24 -> 2024-02-02 | B24: =Portafolio!E24 -> -0.0054198476 | C24: =Portafolio!F24 -> 0.0057395345 | D24: =Portafolio!G24 -> 0.01825812 | E24: =Portafolio!H24 -> 0.0097408489
A25: =Portafolio!A25 -> 2024-02-05 | B25: =Portafolio!E25 -> 0.0097984473 | C25: =Portafolio!F25 -> -0.0013172268 | D25: =Portafolio!G25 -> -0.013637507 | E25: =Portafolio!H25 -> -0.0052392854
A26: =Portafolio!A26 -> 2024-02-06 | B26: =Portafolio!E26 -> 0.0085947569 | C26: =Portafolio!F26 -> 0.0034325562 | D26: =Portafolio!G26 -> -0.00039462897 | E26: =Portafolio!H26 -> 0.0024180714
A27: =Portafolio!A27 -> 2024-02-07 | B27: =Portafolio!E27 -> 0.00058094292 | C27: =Portafolio!F27 -> 0.0018827985 | D27: =Portafolio!G27 -> 0.020890645 | E27: =Portafolio!H27 -> 0.009824009
A28: =Portafolio!A28 -> 2024-02-08 | B28: =Portafolio!E28 -> -0.005771318 | C28: =Portafolio!F28 -> -0.003597515 | D28: =Portafolio!G28 -> 0.00014479618 | E28: =Portafolio!H28 -> -0.0022627399
A29: =Portafolio!A29 -> 2024-02-09 | B29: =Portafolio!E29 -> 0.0040855553 | C29: =Portafolio!F29 -> 0.0012006105 | D29: =Portafolio!G29 -> 0.01543175 | E29: =Portafolio!H29 -> 0.0076065409
... A125: =Portafolio!A125 -> 2024-06-28 | B125: =Portafolio!E125 -> -0.016387734 | C125: =Portafolio!F125 -> 0.01539529 | D125: =Portafolio!G125 -> -0.013114188 | E125: =Portafolio!H125 -> -0.00053940675

Sheet Ajuste Distribución MC
B1: Ajuste de Distribución de Variables Múltiples
B3: Resumen Estadístico
D5: Nombre de la Variable | E5: AAPL | H5: Nombre de la Variable | I5: JPM | L5: Nombre de la Variable | M5: MSFT
D6: Mejor Supuesto Ajustado | E6: 0.0010477795 | H6: Mejor Supuesto Ajustado | I6: 0.0014110405 | L6: Mejor Supuesto Ajustado | M6: 0.0015467058
D8: Distribución Ajustada | E8: Gumbel Máxima | H8: Distribución Ajustada | I8: Normal | L8: Distribución Ajustada | M8: Logística
D9: Alfa | E9: -0.0048845365 | H9: Media | I9: 0.0022611462 | L9: Alfa | M9: 0.0019352512
D10: Beta | E10: 0.011370615 | H10: Desv.Est | I10: 0.010259976 | L10: Beta | M10: 0.0064611129
D13: Estadístico Kolmogorov-Smirnov | E13: 0.058199618 | H13: Estadístico Kolmogorov-Smirnov | I13: 0.043001077 | L13: Estadístico Kolmogorov-Smirnov | M13: 0.044470329
D14: Prueba Estadística de P-Value | E14: 0.787311 | H14: Prueba Estadística de P-Value | I14: 0.97405333 | L14: Prueba Estadística de P-Value | M14: 0.96459556
D16: Real | E16: Teórica | H16: Real | I16: Teórica | L16: Real | M16: Teórica
C17: Media | D17: 0.0010477795 | E17: 0.0016787608 | G17: Media | H17: 0.0014110405 | I17: 0.0022611462 | K17: Media | L17: 0.0015467058 | M17: 0.0019352512
C18: Desviación Estándar | D18: 0.01510321 | E18: 0.014583381 | G18: Desviación Estándar | H18: 0.011965798 | I18: 0.010259976 | K18: Desviación Estándar | L18: 0.011969843 | M18: 0.011719163
C19: Asimetría | D19: 1.1626748 | E19: 1.1395471 | G19: Asimetría | H19: -1.9080999 | I19: 0 | K19: Asimetría | L19: -0.52595914 | M19: 0
C20: Curtosis | D20: 4.549767 | E20: 2.4 | G20: Curtosis | H20: 9.3075653 | I20: 0 | K20: Curtosis | L20: 0.60124165 | M20: 1.2
D23: Nombre de la Variable | E23: Portafolio
D24: Mejor Supuesto Ajustado | E24: 0.001366095
D26: Distribución Ajustada | E26: Beta Desplazada
D27: Ubicación | E27: -0.033432763
D28: Alfa | E28: 19.510149
D29: Beta | E29: 530.89667
D31: Estadístico Kolmogorov-Smirnov | E31: 0.050585439
D32: Prueba Estadística de P-Value | E32: 0.90407327
D34: Real | E34: Teórica
C35: Media | D35: 0.001366095 | E35: 0.002014016
C36: Desviación Estándar | D36: 0.0078073005 | E36: 0.0078743628
C37: Asimetría | D37: -0.81313858 | E37: 0.42718994
C38: Curtosis | D38: 2.4976101 | E38: 0.26240029
B40: Matriz de Correlación
C42: AAPL | D42: JPM | E42: MSFT | F42: Portafolio
B43: AAPL | C43: 1
B44: JPM | C44: -0.13971785 | D44: 1
B45: MSFT | C45: 0.37314185 | D45: 0.012571687 | E45: 1
B46: Portafolio | C46: 0.52516406 | D46: 0.65788794 | E46: 0.63556466 | F46: 1

Sheet VaR GARCH
A1: =Portafolio!A1 -> fecha | B1: AAPL | C1: JPM | D1: MSFT | E1: Portafolio
A2: =Portafolio!A2 -> 2024-01-02 | B2: 184.93822 | C2: 168.0667 | D2: 368.8541 | E2: =SUMPRODUCT(Portafolio!B2:D2,Portafolio!$K$15:$M$15) -> 255.60548 | F2: =Portafolio!H2 -> Portafolio
A3: =Portafolio!A3 -> 2024-01-03 | B3: 183.55348 | C3: 167.33418 | D3: 368.58557 | E3: =SUMPRODUCT(Portafolio!B3:D3,Portafolio!$K$15:$M$15) -> 254.99281 | F3: =Portafolio!H3 -> -0.003193079 | H3: VaR - Volatilidad Condicional al Tiempo
A4: =Portafolio!A4 -> 2024-01-04 | B4: 181.22234 | C4: 168.44463 | D4: 365.94 | E4: =SUMPRODUCT(Portafolio!B4:D4,Portafolio!$K$15:$M$15) -> 254.09287 | F4: =Portafolio!H4 -> -0.0015849665
A5: =Portafolio!A5 -> 2024-01-05 | B5: 180.49507 | C5: 169.28975 | D5: 365.75107 | E5: =SUMPRODUCT(Portafolio!B5:D5,Portafolio!$K$15:$M$15) -> 254.30998 | F5: =Portafolio!H5 -> 0.0015763662 | H5: Nivel de Confianza | I5: 0.95
A6: =Portafolio!A6 -> 2024-01-08 | B6: 184.85852 | C6: 169.04408 | D6: 372.65335 | E6: =SUMPRODUCT(Portafolio!B6:D6,Portafolio!$K$15:$M$15) -> 257.65877 | F6: =Portafolio!H6 -> 0.010152267 | H6: Horizonte de tiempo | I6: 1
A7: =Portafolio!A7 -> 2024-01-09 | B7: 184.44011 | C7: 167.70761 | D7: 373.74734 | E7: =SUMPRODUCT(Portafolio!B7:D7,Portafolio!$K$15:$M$15) -> 257.46707 | F7: =Portafolio!H7 -> -0.0026313546
A8: =Portafolio!A8 -> 2024-01-10 | B8: 185.48614 | C8: 168.06139 | D8: 380.68942 | E8: =SUMPRODUCT(Portafolio!B8:D8,Portafolio!$K$15:$M$15) -> 260.70974 | F8: =Portafolio!H8 -> 0.0094720816 | I8: AAPL | J8: JPM | K8: MSFT | L8: Portafolio
A9: =Portafolio!A9 -> 2024-01-11 | B9: 184.88841 | C9: 167.35384 | D9: 382.53931 | E9: =SUMPRODUCT(Portafolio!B9:D9,Portafolio!$K$15:$M$15) -> 261.10464 | F9: =Portafolio!H9 -> -0.00023880911 | H9: Desviación Estandar | I9: ='GARCH AAPL'!$D$141*SQRT(1/252) -> 0.015053796 | J9: ='GARCH JPM'!$D$141*SQRT(1/252) -> 0.011903914 | K9: ='GARCH MSFT'!$D$141*SQRT(1/252) -> 0.01192445 | L9: ='GARCH Portafolio'!$D$141*SQRT(1/252) -> 0.0081535267
A10: =Portafolio!A10 -> 2024-01-12 | B10: 185.21716 | C10: 166.12546 | D10: 386.35843 | E10: =SUMPRODUCT(Portafolio!B10:D10,Portafolio!$K$15:$M$15) -> 262.212 | F10: =Portafolio!H10 -> 0.0010930566 | H10: VaR por activo | I10: =I9*NORMSINV(1-$I$5)*SQRT($I$6) -> -0.024761291 | J10: =J9*NORMSINV(1-$I$5)*SQRT($I$6) -> -0.019580197 | K10: =K9*NORMSINV(1-$I$5)*SQRT($I$6) -> -0.019613974 | L10: =L9*NORMSINV(1-$I$5)*SQRT($I$6) -> -0.013411358
A11: =Portafolio!A11 -> 2024-01-16 | B11: 182.93582 | C11: 165.0838 | D11: 388.14865 | E11: =SUMPRODUCT(Portafolio!B11:D11,Portafolio!$K$15:$M$15) -> 262.22873 | F11: =Portafolio!H11 -> -0.0023696334
A12: =Portafolio!A12 -> 2024-01-17 | B12: 181.98941 | C12: 164.19936 | D12: 387.353 | E12: =SUMPRODUCT(Portafolio!B12:D12,Portafolio!$K$15:$M$15) -> 261.37472 | F12: =Portafolio!H12 -> -0.0039357185 | H12: VaR(%) No Diversificado | I12: =SUM(I10:K10) -> -0.063955462 | K12: CVaR
A13: =Portafolio!A13 -> 2024-01-18 | B13: 187.91693 | C13: 164.52365 | D13: 391.72906 | E13: =SUMPRODUCT(Portafolio!B13:D13,Portafolio!$K$15:$M$15) -> 264.09321 | F13: =Portafolio!H13 -> 0.0095054398 | H13: VaR(%) Diversificado | I13: =L10 -> -0.013411358 | K13: =AVERAGEIF(F3:F125,"<"&I13,$F$3:$F$125) -> -0.020743251
A14: =Portafolio!A14 -> 2024-01-19 | B14: 190.83585 | C14: 167.36365 | D14: 396.50299 | E14: =SUMPRODUCT(Portafolio!B14:D14,Portafolio!$K$15:$M$15) -> 267.76639 | F14: =Portafolio!H14 -> 0.014781335
A15: =Portafolio!A15 -> 2024-01-22 | B15: 193.15703 | C15: 167.1671 | D15: 394.35477 | E15: =SUMPRODUCT(Portafolio!B15:D15,Portafolio!$K$15:$M$15) -> 267.03882 | F15: =Portafolio!H15 -> -0.0014064286 | H15: Exposición | I15: 100000000
A16: =Portafolio!A16 -> 2024-01-23 | B16: 194.44215 | C16: 166.0665 | D16: 396.73175 | E16: =SUMPRODUCT(Portafolio!B16:D16,Portafolio!$K$15:$M$15) -> 267.70407 | F16: =Portafolio!H16 -> 0.0003466655 | H16: VaR($) No Diversificado | I16: =I12*I15 -> -6395546.2
A17: =Portafolio!A17 -> 2024-01-24 | B17: 193.76472 | C17: 167.55037 | D17: 400.37183 | E17: =SUMPRODUCT(Portafolio!B17:D17,Portafolio!$K$15:$M$15) -> 269.8486 | F17: =Portafolio!H17 -> 0.0075196083 | H17: VaR($) Diversificado | I17: =I13*I15 -> -1341135.8
A18: =Portafolio!A18 -> 2024-01-25 | B18: 193.43597 | C18: 169.94815 | D18: 402.66928 | E18: =SUMPRODUCT(Portafolio!B18:D18,Portafolio!$K$15:$M$15) -> 271.87844 | F18: =Portafolio!H18 -> 0.0086967208
A19: =Portafolio!A19 -> 2024-01-26 | B19: 191.6926 | C19: 169.29958 | D19: 401.73438 | E19: =SUMPRODUCT(Portafolio!B19:D19,Portafolio!$K$15:$M$15) -> 270.97731 | F19: =Portafolio!H19 -> -0.0038088477
A20: =Portafolio!A20 -> 2024-01-29 | B20: 191.0052 | C20: 169.74178 | D20: 407.49292 | E20: =SUMPRODUCT(Portafolio!B20:D20,Portafolio!$K$15:$M$15) -> 273.5493 | F20: =Portafolio!H20 -> 0.006820183
A21: =Portafolio!A21 -> 2024-01-30 | B21: 187.32915 | C21: 173.22055 | D21: 406.36908 | E21: =SUMPRODUCT(Portafolio!B21:D21,Portafolio!$K$15:$M$15) -> 274.21418 | F21: =Portafolio!H21 -> 0.0057317365
A22: =Portafolio!A22 -> 2024-01-31 | B22: 183.70291 | C22: 171.3436 | D22: 395.41891 | E22: =SUMPRODUCT(Portafolio!B22:D22,Portafolio!$K$15:$M$15) -> 268.26379 | F22: =Portafolio!H22 -> -0.018921543
A23: =Portafolio!A23 -> 2024-02-01 | B23: 186.15363 | C23: 170.72449 | D23: 401.58521 | E23: =SUMPRODUCT(Portafolio!B23:D23,Portafolio!$K$15:$M$15) -> 270.90112 | F23: =Portafolio!H23 -> 0.0065257348
A24: =Portafolio!A24 -> 2024-02-02 | B24: 185.14743 | C24: 171.70718 | D24: 408.98474 | E24: =SUMPRODUCT(Portafolio!B24:D24,Portafolio!$K$15:$M$15) -> 274.37987 | F24: =Portafolio!H24 -> 0.0097408489
A25: =Portafolio!A25 -> 2024-02-05 | B25: 186.9705 | C25: 171.48116 | D25: 403.44507 | E25: =SUMPRODUCT(Portafolio!B25:D25,Portafolio!$K$15:$M$15) -> 272.13488 | F25: =Portafolio!H25 -> -0.0052392854
A26: =Portafolio!A26 -> 2024-02-06 | B26: 188.5844 | C26: 172.07079 | D26: 403.28589 | E26: =SUMPRODUCT(Portafolio!B26:D26,Portafolio!$K$15:$M$15) -> 272.52772 | F26: =Portafolio!H26 -> 0.0024180714
A27: =Portafolio!A27 -> 2024-02-07 | B27: 188.69398 | C27: 172.39507 | D27: 411.79941 | E27: =SUMPRODUCT(Portafolio!B27:D27,Portafolio!$K$15:$M$15) -> 276.31464 | F27: =Portafolio!H27 -> 0.009824009
A28: =Portafolio!A28 -> 2024-02-08 | B28: 187.60811 | C28: 171.77599 | D28: 411.85904 | E28: =SUMPRODUCT(Portafolio!B28:D28,Portafolio!$K$15:$M$15) -> 275.92898 | F28: =Portafolio!H28 -> -0.0022627399
A29: =Portafolio!A29 -> 2024-02-09 | B29: 188.37616 | C29: 171.98235 | D29: 418.26404 | E29: =SUMPRODUCT(Portafolio!B29:D29,Portafolio!$K$15:$M$15) -> 278.84268 | F29: =Portafolio!H29 -> 0.0076065409
... A125: =Portafolio!A125 -> 2024-06-28 | B125: 210.37648 | C125: 199.92032 | D125: 446.14587 | E125: =SUMPRODUCT(Portafolio!B125:D125,Portafolio!$K$15:$M$15) -> 306.04852 | F125: =Portafolio!H125 -> -0.00053940675

Sheet GARCH AAPL
B1: GARCH: Proceso General Autorregresivo de Heterocedasticidad Condicional (Pronóstico de la Volatililidad)
B4: GARCH es un término que incorpora una familia de modelos que toman una variedad de formas de acuerdo a sus enfoques (GARCH, T-GARCH, I-GARCH, etc.); específicamente un GARCH (P,Q), es un modelo donde P y Q son enteros positivos que definen el modelo resultante; en este caso, P corresponde al rezago de la varianza condicionada y Q corresponde al rezago de los errores al cuadrado. Los procesos GARCH se utilizan principalmente para calcular la inestabilidad o volatilidad en el precio de un activo financiero, como acciones, opciones financieras, bonos; aunque este modelo también se usa también para modelar otros productos comerciales como el precio del aceite, electricidad, combustibles, productos básicos etc. En términos estadísticos un proceso GARCH busca modelar la volatilidad de la varianza, debido a que esta no es homocedastica, es decir, presenta heterocedasticidad o cambios sistemáticos en la varianza a través del tiempo. Uno de los inconvenientes para construir modelos GARCH es que se requieren muchos datos para hacer funcional el análisis, además de necesitar algo de pericia en modelación econométrica avanzada, y por tanto este enfoque es sumamente susceptible a la manipulación del usuario. El beneficio en la realización de este riguroso análisis econométrico y estadístico esta en encontrar el mejor modelo que ajuste a los datos, dada la inestabilidad de los mismos, permitiendo pronosticar la volatilidad de la varianza. En la mayoría de los casos para instrumentos financieros, un GARCH (1,1) es suficiente y es generalmente muy utilizado.
B11: GARCH Modelo (P,Q) | E11: 1,12 | G11: Periodicidad (Períodos/Año) | J11: 252
B12: Optimización Alfa | E12: 0.57532824 | G12: Base Predictiva | J12: 252
B13: Optimización Beta | E13: 0 | G13: Pronostique Períodos | J13: 1
B14: Optimización Omega | E14: 9.6870583e-05 | G14: Variación Targeting | J14: TRUE
B16: Período | C16: Datos | D16: Volatilidad | F16: Los modelos GARCH son generalmente usados para pronosticar la inestabilidad de instrumentos financieros al usar los precios de si mismo. Solo pueden utilizarse valores positivos para pronosticar la volatilidad en un modelo GARCH. La periodicidad es el número de periodos por año (por ejemplo, 12 para datos mensuales, 252 para días hábiles, 365 para datos diarios, etc.) Es indispensable cerciorarse de tener los valores a modelar en orden cronológico. La Base Predictiva es el número de periodos base, es decir, el número de periodos rezagados que va a usar como una base de pronóstico para predecir la volatilidad futura, se ubica típicamente entre 1 y 12. Varianza Targeting es un método de estimación que consiste en asignarle a la varianza promedio a largo plazo un valor igual a la varianza muestral. Para finalizar debe estar seguro que sus datos originales estén organizados en orden cronológico.
B17: 0 | C17: 184.93822
B18: 1 | C18: 183.55348
B19: 2 | C19: 181.22234
B20: 3 | C20: 180.49507
B21: 4 | C21: 184.85852
B22: 5 | C22: 184.44011
B23: 6 | C23: 185.48614
B24: 7 | C24: 184.88841
B25: 8 | C25: 185.21716
B26: 9 | C26: 182.93582
B27: 10 | C27: 181.98941
B28: 11 | C28: 187.91693
B29: 12 | C29: 190.83585
B30: 13 | C30: 193.15703 | D30: 0.24260309
B31: 14 | C31: 194.44215 | D31: 0.21354801
B32: 15 | C32: 193.76472 | D32: 0.17546153
B33: 16 | C33: 193.43597 | D33: 0.16179412
B34: 17 | C34: 191.6926 | D34: 0.15757362
B35: 18 | C35: 191.0052 | D35: 0.19051284
B36: 19 | C36: 187.32915 | D36: 0.16211846
B37: 20 | C37: 183.70291 | D37: 0.28136353
B38: 21 | C38: 186.15363 | D38: 0.28250533
B39: 22 | C39: 185.14743 | D39: 0.22332549
B40: 23 | C40: 186.9705 | D40: 0.16932282
B41: 24 | C41: 188.5844 | D41: 0.19578334
... B140: 123 | C140: 210.37648 | D140: 0.16341891
D141: 0.2389716

Sheet GARCH JPM
B1: GARCH: Proceso General Autorregresivo de Heterocedasticidad Condicional (Pronóstico de la Volatililidad)
B4: GARCH es un término que incorpora una familia de modelos que toman una variedad de formas de acuerdo a sus enfoques (GARCH, T-GARCH, I-GARCH, etc.); específicamente un GARCH (P,Q), es un modelo donde P y Q son enteros positivos que definen el modelo resultante; en este caso, P corresponde al rezago de la varianza condicionada y Q corresponde al rezago de los errores al cuadrado. Los procesos GARCH se utilizan principalmente para calcular la inestabilidad o volatilidad en el precio de un activo financiero, como acciones, opciones financieras, bonos; aunque este modelo también se usa también para modelar otros productos comerciales como el precio del aceite, electricidad, combustibles, productos básicos etc. En términos estadísticos un proceso GARCH busca modelar la volatilidad de la varianza, debido a que esta no es homocedastica, es decir, presenta heterocedasticidad o cambios sistemáticos en la varianza a través del tiempo. Uno de los inconvenientes para construir modelos GARCH es que se requieren muchos datos para hacer funcional el análisis, además de necesitar algo de pericia en modelación econométrica avanzada, y por tanto este enfoque es sumamente susceptible a la manipulación del usuario. El beneficio en la realización de este riguroso análisis econométrico y estadístico esta en encontrar el mejor modelo que ajuste a los datos, dada la inestabilidad de los mismos, permitiendo pronosticar la volatilidad de la varianza. En la mayoría de los casos para instrumentos financieros, un GARCH (1,1) es suficiente y es generalmente muy utilizado.
B11: GARCH Modelo (P,Q) | E11: 0,1 | G11: Periodicidad (Períodos/Año) | J11: 252
B12: Optimización Alfa | E12: 1 | G12: Base Predictiva | J12: 252
B13: Optimización Beta | E13: 0 | G13: Pronostique Períodos | J13: 1
B14: Optimización Omega | E14: -3.1792419e-20 | G14: Variación Targeting | J14: TRUE
B16: Período | C16: Datos | D16: Volatilidad | F16: Los modelos GARCH son generalmente usados para pronosticar la inestabilidad de instrumentos financieros al usar los precios de si mismo. Solo pueden utilizarse valores positivos para pronosticar la volatilidad en un modelo GARCH. La periodicidad es el número de periodos por año (por ejemplo, 12 para datos mensuales, 252 para días hábiles, 365 para datos diarios, etc.) Es indispensable cerciorarse de tener los valores a modelar en orden cronológico. La Base Predictiva es el número de periodos base, es decir, el número de periodos rezagados que va a usar como una base de pronóstico para predecir la volatilidad futura, se ubica típicamente entre 1 y 12. Varianza Targeting es un método de estimación que consiste en asignarle a la varianza promedio a largo plazo un valor igual a la varianza muestral. Para finalizar debe estar seguro que sus datos originales estén organizados en orden cronológico.
B17: 0 | C17: 168.0667
B18: 1 | C18: 167.33418
B19: 2 | C19: 168.44463 | D19: 0.10499652
B20: 3 | C20: 169.28975 | D20: 0.079446712
B21: 4 | C21: 169.04408 | D21: 0.023053181
B22: 5 | C22: 167.70761 | D22: 0.12600346
B23: 6 | C23: 168.06139 | D23: 0.033451606
B24: 7 | C24: 167.35384 | D24: 0.066973852
B25: 8 | C25: 166.12546 | D25: 0.11694873
B26: 9 | C26: 165.0838 | D26: 0.099851308
B27: 10 | C27: 164.19936 | D27: 0.085277159
B28: 11 | C28: 164.52365 | D28: 0.031321356
B29: 12 | C29: 167.36365 | D29: 0.27168648
B30: 13 | C30: 167.1671 | D30: 0.018653658
... B140: 123 | C140: 199.92032 | D140: 0.24439265
D141: 0.18896878

Sheet GARCH MSFT
B1: GARCH: Proceso General Autorregresivo de Heterocedasticidad Condicional (Pronóstico de la Volatililidad)
B4: GARCH es un término que incorpora una familia de modelos que toman una variedad de formas de acuerdo a sus enfoques (GARCH, T-GARCH, I-GARCH, etc.); específicamente un GARCH (P,Q), es un modelo donde P y Q son enteros positivos que definen el modelo resultante; en este caso, P corresponde al rezago de la varianza condicionada y Q corresponde al rezago de los errores al cuadrado. Los procesos GARCH se utilizan principalmente para calcular la inestabilidad o volatilidad en el precio de un activo financiero, como acciones, opciones financieras, bonos; aunque este modelo también se usa también para modelar otros productos comerciales como el precio del aceite, electricidad, combustibles, productos básicos etc. En términos estadísticos un proceso GARCH busca modelar la volatilidad de la varianza, debido a que esta no es homocedastica, es decir, presenta heterocedasticidad o cambios sistemáticos en la varianza a través del tiempo. Uno de los inconvenientes para construir modelos GARCH es que se requieren muchos datos para hacer funcional el análisis, además de necesitar algo de pericia en modelación econométrica avanzada, y por tanto este enfoque es sumamente susceptible a la manipulación del usuario. El beneficio en la realización de este riguroso análisis econométrico y estadístico esta en encontrar el mejor modelo que ajuste a los datos, dada la inestabilidad de los mismos, permitiendo pronosticar la volatilidad de la varianza. En la mayoría de los casos para instrumentos financieros, un GARCH (1,1) es suficiente y es generalmente muy utilizado.
B11: GARCH Modelo (P,Q) | E11: 0,1 | G11: Periodicidad (Períodos/Año) | J11: 252
B12: Optimización Alfa | E12: 1 | G12: Base Predictiva | J12: 252
B13: Optimización Beta | E13: 0 | G13: Pronostique Períodos | J13: 1
B14: Optimización Omega | E14: 1.5906957e-20 | G14: Variación Targeting | J14: TRUE
B16: Período | C16: Datos | D16: Volatilidad | F16: Los modelos GARCH son generalmente usados para pronosticar la inestabilidad de instrumentos financieros al usar los precios de si mismo. Solo pueden utilizarse valores positivos para pronosticar la volatilidad en un modelo GARCH. La periodicidad es el número de periodos por año (por ejemplo, 12 para datos mensuales, 252 para días hábiles, 365 para datos diarios, etc.) Es indispensable cerciorarse de tener los valores a modelar en orden cronológico. La Base Predictiva es el número de periodos base, es decir, el número de periodos rezagados que va a usar como una base de pronóstico para predecir la volatilidad futura, se ubica típicamente entre 1 y 12. Varianza Targeting es un método de estimación que consiste en asignarle a la varianza promedio a largo plazo un valor igual a la varianza muestral. Para finalizar debe estar seguro que sus datos originales estén organizados en orden cronológico.
B17: 0 | C17: 368.8541
B18: 1 | C18: 368.58557
B19: 2 | C19: 365.94 | D19: 0.11435214
B20: 3 | C20: 365.75107 | D20: 0.0081981022
B21: 4 | C21: 372.65335 | D21: 0.29678461
B22: 5 | C22: 373.74734 | D22: 0.04653434
B23: 6 | C23: 380.68942 | D23: 0.29215219
B24: 7 | C24: 382.53931 | D24: 0.076952176
B25: 8 | C25: 386.35843 | D25: 0.15769896
B26: 9 | C26: 388.14865 | D26: 0.073385889
B27: 10 | C27: 387.353 | D27: 0.032574076
B28: 11 | C28: 391.72906 | D28: 0.17833464
B29: 12 | C29: 396.50299 | D29: 0.1922902
B30: 13 | C30: 394.35477 | D30: 0.086240745
... B140: 123 | C140: 446.14587 | D140: 0.20818129
D141: 0.18929477

Sheet GARCH Portafolio
B1: GARCH: Proceso General Autorregresivo de Heterocedasticidad Condicional (Pronóstico de la Volatililidad)
B4: GARCH es un término que incorpora una familia de modelos que toman una variedad de formas de acuerdo a sus enfoques (GARCH, T-GARCH, I-GARCH, etc.); específicamente un GARCH (P,Q), es un modelo donde P y Q son enteros positivos que definen el modelo resultante; en este caso, P corresponde al rezago de la varianza condicionada y Q corresponde al rezago de los errores al cuadrado. Los procesos GARCH se utilizan principalmente para calcular la inestabilidad o volatilidad en el precio de un activo financiero, como acciones, opciones financieras, bonos; aunque este modelo también se usa también para modelar otros productos comerciales como el precio del aceite, electricidad, combustibles, productos básicos etc. En términos estadísticos un proceso GARCH busca modelar la volatilidad de la varianza, debido a que esta no es homocedastica, es decir, presenta heterocedasticidad o cambios sistemáticos en la varianza a través del tiempo. Uno de los inconvenientes para construir modelos GARCH es que se requieren muchos datos para hacer funcional el análisis, además de necesitar algo de pericia en modelación econométrica avanzada, y por tanto este enfoque es sumamente susceptible a la manipulación del usuario. El beneficio en la realización de este riguroso análisis econométrico y estadístico esta en encontrar el mejor modelo que ajuste a los datos, dada la inestabilidad de los mismos, permitiendo pronosticar la volatilidad de la varianza. En la mayoría de los casos para instrumentos financieros, un GARCH (1,1) es suficiente y es generalmente muy utilizado.
B11: GARCH Modelo (P,Q) | E11: 1,1 | G11: Periodicidad (Períodos/Año) | J11: 252
B12: Optimización Alfa | E12: 0.010581496 | G12: Base Predictiva | J12: 252
B13: Optimización Beta | E13: 0 | G13: Pronostique Períodos | J13: 1
B14: Optimización Omega | E14: 6.5767166e-05 | G14: Variación Targeting | J14: TRUE
B16: Período | C16: Datos | D16: Volatilidad | F16: Los modelos GARCH son generalmente usados para pronosticar la inestabilidad de instrumentos financieros al usar los precios de si mismo. Solo pueden utilizarse valores positivos para pronosticar la volatilidad en un modelo GARCH. La periodicidad es el número de periodos por año (por ejemplo, 12 para datos mensuales, 252 para días hábiles, 365 para datos diarios, etc.) Es indispensable cerciorarse de tener los valores a modelar en orden cronológico. La Base Predictiva es el número de periodos base, es decir, el número de periodos rezagados que va a usar como una base de pronóstico para predecir la volatilidad futura, se ubica típicamente entre 1 y 12. Varianza Targeting es un método de estimación que consiste en asignarle a la varianza promedio a largo plazo un valor igual a la varianza muestral. Para finalizar debe estar seguro que sus datos originales estén organizados en orden cronológico.
B17: 0 | C17: 234.03275
B18: 1 | C18: 233.27557
B19: 2 | C19: 232.44434 | D19: 0.12884614
B20: 3 | C20: 232.61032 | D20: 0.12886933
B21: 4 | C21: 235.61277 | D21: 0.12874271
B22: 5 | C22: 235.21241 | D22: 0.13042976
B23: 6 | C23: 237.71235 | D23: 0.12876738
B24: 7 | C24: 237.79131 | D24: 0.12988987
B25: 8 | C25: 238.43861 | D25: 0.12873857
B26: 9 | C26: 237.93858 | D26: 0.12881394
B27: 10 | C27: 237.05705 | D27: 0.12878306
B28: 11 | C28: 239.9449 | D28: 0.12888003
B29: 12 | C29: 243.41241 | D29: 0.13024699
B30: 13 | C30: 243.23265 | D30: 0.13085207
... B140: 123 | C140: 278.29667 | D140: 0.1289351
D141: 0.12943322

Sheet VaR Dinámico
A1: =Portafolio!A1 -> fecha | B1: Retornos Portafolio | C1: VaR SD | D1: VaR N-P | E1: VaR Prom. Móvil | G1: VaR Semi-Desviación | I1: VaR EWMA | K1: Simulación de Montecarlo
E2: Pronóstico | F2: VaR Prm-M | G2: Semi-SD | H2: VaR S-SD | I2: Pronóstico | J2: VaR EWMA | K2: Entrada | L2: Salida | M2: VaR MC | N2: VaR MC
A3: =Portafolio!A3 -> 2024-01-03 | B3: =Portafolio!H3 -> -0.003193079 | E3: =B3*B3 -> 1.0195754e-05 | G3: {=MIN(B3-$B$3:$B$62,0)^2} -> 0.00039454073
A4: =Portafolio!A4 -> 2024-01-04 | B4: =Portafolio!H4 -> -0.0015849665 | E4: =B4*B4 -> 2.5121189e-06 | G4: {=MIN(B4-$B$3:$B$62,0)^2} -> 0.00033324272
A5: =Portafolio!A5 -> 2024-01-05 | B5: =Portafolio!H5 -> 0.0015763662 | E5: =B5*B5 -> 2.4849302e-06 | G5: {=MIN(B5-$B$3:$B$62,0)^2} -> 0.00022781689
A6: =Portafolio!A6 -> 2024-01-08 | B6: =Portafolio!H6 -> 0.010152267 | E6: =B6*B6 -> 0.00010306853 | G6: {=MIN(B6-$B$3:$B$62,0)^2} -> 4.2480453e-05
A7: =Portafolio!A7 -> 2024-01-09 | B7: =Portafolio!H7 -> -0.0026313546 | E7: =B7*B7 -> 6.9240269e-06 | G7: {=MIN(B7-$B$3:$B$62,0)^2} -> 0.00037254115
A8: =Portafolio!A8 -> 2024-01-10 | B8: =Portafolio!H8 -> 0.0094720816 | E8: =B8*B8 -> 8.972033e-05 | G8: {=MIN(B8-$B$3:$B$62,0)^2} -> 5.1809603e-05
A9: =Portafolio!A9 -> 2024-01-11 | B9: =Portafolio!H9 -> -0.00023880911 | E9: =B9*B9 -> 5.7029791e-08 | G9: {=MIN(B9-$B$3:$B$62,0)^2} -> 0.00028590683
A10: =Portafolio!A10 -> 2024-01-12 | B10: =Portafolio!H10 -> 0.0010930566 | E10: =B10*B10 -> 1.1947727e-06 | G10: {=MIN(B10-$B$3:$B$62,0)^2} -> 0.00024264025
A11: =Portafolio!A11 -> 2024-01-16 | B11: =Portafolio!H11 -> -0.0023696334 | E11: =B11*B11 -> 5.6151623e-06 | G11: {=MIN(B11-$B$3:$B$62,0)^2} -> 0.00036250651
A12: =Portafolio!A12 -> 2024-01-17 | B12: =Portafolio!H12 -> -0.0039357185 | E12: =B12*B12 -> 1.5489881e-05 | G12: {=MIN(B12-$B$3:$B$62,0)^2} -> 0.00042459442
A13: =Portafolio!A13 -> 2024-01-18 | B13: =Portafolio!H13 -> 0.0095054398 | E13: =B13*B13 -> 9.0353385e-05 | G13: {=MIN(B13-$B$3:$B$62,0)^2} -> 5.13305e-05
A14: =Portafolio!A14 -> 2024-01-19 | B14: =Portafolio!H14 -> 0.014781335 | E14: =B14*B14 -> 0.00021848785 | G14: {=MIN(B14-$B$3:$B$62,0)^2} -> 3.5669451e-06
... A61: =Portafolio!A61 -> 2024-03-27 | B61: =Portafolio!H61 -> 0.011003065 | E61: =B61*B61 -> 0.00012106745 | G61: {=MIN(B61-$B$3:$B$62,0)^2} -> 3.2113813e-05
A62: =Portafolio!A62 -> 2024-03-28 | B62: =Portafolio!H62 -> -0.00020992588 | E62: =B62*B62 -> 4.4068877e-08 | G62: {=MIN(B62-$B$3:B62,0)^2} -> 0.0002849309
A63: =Portafolio!A63 -> 2024-04-01 | B63: =Portafolio!H63 -> -0.00023101207 | C63: =STDEV(B3:B62)*NORMSINV(1-95%)*SQRT(1) -> -0.01172252 | D63: =_xlfn.PERCENTILE.INC(B3:B62,1-95%)*SQRT(1) -> -0.011090698 | E63: =B63*B63 -> 5.3366576e-08 | F63: =SQRT(AVERAGE(E3:E62))*NORMSINV(1-95%)*SQRT(1) -> -0.012059183 | G63: {=MIN(B63-$B$3:B63,0)^2} -> 0.00028564321 | H63: =SQRT(AVERAGE(G3:G62))*NORMSINV(1-95%)*SQRT(1) -> -0.026856852 | I63: =B62^2 -> 4.4068877e-08 | J63: =SQRT(I63)*NORMSINV(1-95%)*SQRT(1) -> -0.00034529735 | K63: 0.0015594644 | L63: =K63 -> 0.0015594644 | M63: {=_xll.ROV.RiskSim.RSFunctions.RSForecastStatistic(L63,"Percentile0.05")*SQRT(1)} -> -0.0090437179 | N63: -0.0090437179
A64: =Portafolio!A64 -> 2024-04-02 | B64: =Portafolio!H64 -> -0.004172482 | C64: =STDEV(B4:B63)*NORMSINV(1-95%)*SQRT(1) -> -0.011679713 | D64: =_xlfn.PERCENTILE.INC(B4:B63,1-95%)*SQRT(1) -> -0.011090698 | E64: =B64*B64 -> 1.7409606e-05 | F64: =SQRT(AVERAGE(E4:E63))*NORMSINV(1-95%)*SQRT(1) -> -0.012040206 | G64: {=MIN(B64-$B$3:B64,0)^2} -> 0.00043440782 | H64: =SQRT(AVERAGE(G4:G63))*NORMSINV(1-95%)*SQRT(1) -> -0.026765277 | I64: =(0.94*B63^2)+((1-0.94)*I63) -> 5.2808714e-08 | J64: =SQRT(I64)*NORMSINV(1-95%)*SQRT(1) -> -0.00037798978 | K64: 0.0015594644 | L64: =K64 -> 0.0015594644 | M64: {=_xll.ROV.RiskSim.RSFunctions.RSForecastStatistic(L64,"Percentile0.05")*SQRT(1)} -> -0.0078188379 | N64: -0.0078188379
A65: =Portafolio!A65 -> 2024-04-03 | B65: =Portafolio!H65 -> -0.0017133963 | C65: =STDEV(B5:B64)*NORMSINV(1-95%)*SQRT(1) -> -0.011728955 | D65: =_xlfn.PERCENTILE.INC(B5:B64,1-95%)*SQRT(1) -> -0.011090698 | E65: =B65*B65 -> 2.9357268e-06 | F65: =SQRT(AVERAGE(E5:E64))*NORMSINV(1-95%)*SQRT(1) -> -0.01206807 | G65: {=MIN(B65-$B$3:B65,0)^2} -> 0.00033794817 | H65: =SQRT(AVERAGE(G5:G64))*NORMSINV(1-95%)*SQRT(1) -> -0.02685036 | I65: =(0.94*B64^2)+((1-0.94)*I64) -> 1.6368198e-05 | J65: =SQRT(I65)*NORMSINV(1-95%)*SQRT(1) -> -0.0066546879 | K65: 0.0015594644 | L65: =K65 -> 0.0015594644 | M65: {=_xll.ROV.RiskSim.RSFunctions.RSForecastStatistic(L65,"Percentile0.05")*SQRT(1)} -> -0.0072016294 | N65: -0.0072016294
A66: =Portafolio!A66 -> 2024-04-04 | B66: =Portafolio!H66 -> -0.0066699185 | C66: =STDEV(B6:B65)*NORMSINV(1-95%)*SQRT(1) -> -0.011754628 | D66: =_xlfn.PERCENTILE.INC(B6:B65,1-95%)*SQRT(1) -> -0.011090698 | E66: =B66*B66 -> 4.4487813e-05 | F66: =SQRT(AVERAGE(E6:E65))*NORMSINV(1-95%)*SQRT(1) -> -0.012068912 | G66: {=MIN(B66-$B$3:B66,0)^2} -> 0.00054475041 | H66: =SQRT(AVERAGE(G6:G65))*NORMSINV(1-95%)*SQRT(1) -> -0.026942678 | I66: =(0.94*B65^2)+((1-0.94)*I65) -> 3.7416751e-06 | J66: =SQRT(I66)*NORMSINV(1-95%)*SQRT(1) -> -0.0031817078 | K66: 0.0015594644 | L66: =K66 -> 0.0015594644 | M66: {=_xll.ROV.RiskSim.RSFunctions.RSForecastStatistic(L66,"Percentile0.05")*SQRT(1)} -> -0.0065690298 | N66: -0.0065690298
A67: =Portafolio!A67 -> 2024-04-05 | B67: =Portafolio!H67 -> 0.012417793 | C67: =STDEV(B7:B66)*NORMSINV(1-95%)*SQRT(1) -> -0.011755999 | D67: =_xlfn.PERCENTILE.INC(B7:B66,1-95%)*SQRT(1) -> -0.011090698 | E67: =B67*B67 -> 0.00015420157 | F67: =SQRT(AVERAGE(E7:E66))*NORMSINV(1-95%)*SQRT(1) -> -0.011958976 | G67: {=MIN(B67-$B$3:B67,0)^2} -> 1.8081017e-05 | H67: =SQRT(AVERAGE(G7:G66))*NORMSINV(1-95%)*SQRT(1) -> -0.02735976 | I67: =(0.94*B66^2)+((1-0.94)*I66) -> 4.2043044e-05 | J67: =SQRT(I67)*NORMSINV(1-95%)*SQRT(1) -> -0.010665331 | K67: 0.0015594644 | L67: =K67 -> 0.0015594644 | M67: {=_xll.ROV.RiskSim.RSFunctions.RSForecastStatistic(L67,"Percentile0.05")*SQRT(1)} -> -0.0068587684 | N67: -0.0068587684
A68: =Portafolio!A68 -> 2024-04-08 | B68: =Portafolio!H68 -> 0.00063673863 | C68: =STDEV(B8:B67)*NORMSINV(1-95%)*SQRT(1) -> -0.011939244 | D68: =_xlfn.PERCENTILE.INC(B8:B67,1-95%)*SQRT(1) -> -0.011090698 | E68: =B68*B68 -> 4.0543608e-07 | F68: =SQRT(AVERAGE(E8:E67))*NORMSINV(1-95%)*SQRT(1) -> -0.012233487 | G68: {=MIN(B68-$B$3:B68,0)^2} -> 0.00025706452 | H68: =SQRT(AVERAGE(G8:G67))*NORMSINV(1-95%)*SQRT(1) -> -0.027066086 | I68: =(0.94*B67^2)+((1-0.94)*I67) -> 0.00014747206 | J68: =SQRT(I68)*NORMSINV(1-95%)*SQRT(1) -> -0.019974786 | K68: 0.0015594644 | L68: =K68 -> 0.0015594644 | M68: {=_xll.ROV.RiskSim.RSFunctions.RSForecastStatistic(L68,"Percentile0.05")*SQRT(1)} -> -0.0073622789 | N68: -0.0073622789
A69: =Portafolio!A69 -> 2024-04-09 | B69: =Portafolio!H69 -> -0.00050480241 | C69: =STDEV(B9:B68)*NORMSINV(1-95%)*SQRT(1) -> -0.011828258 | D69: =_xlfn.PERCENTILE.INC(B9:B68,1-95%)*SQRT(1) -> -0.011090698 | E69: =B69*B69 -> 2.5482547e-07 | F69: =SQRT(AVERAGE(E9:E68))*NORMSINV(1-95%)*SQRT(1) -> -0.012067758 | G69: {=MIN(B69-$B$3:B69,0)^2} -> 0.00029497282 | H69: =SQRT(AVERAGE(G9:G68))*NORMSINV(1-95%)*SQRT(1) -> -0.027236528 | I69: =(0.94*B68^2)+((1-0.94)*I68) -> 9.2294335e-06 | J69: =SQRT(I69)*NORMSINV(1-95%)*SQRT(1) -> -0.0049970625 | K69: 0.0015594644 | L69: =K69 -> 0.0015594644 | M69: {=_xll.ROV.RiskSim.RSFunctions.RSForecastStatistic(L69,"Percentile0.05")*SQRT(1)} -> -0.0085213346 | N69: -0.0085213346
A70: =Portafolio!A70 -> 2024-04-10 | B70: =Portafolio!H70 -> -0.0082564104 | C70: =STDEV(B10:B69)*NORMSINV(1-95%)*SQRT(1) -> -0.011830418 | D70: =_xlfn.PERCENTILE.INC(B10:B69,1-95%)*SQRT(1) -> -0.011090698 | E70: =B70*B70 -> 6.8168313e-05 | F70: =SQRT(AVERAGE(E10:E69))*NORMSINV(1-95%)*SQRT(1) -> -0.012068127 | G70: {=MIN(B70-$B$3:B70,0)^2} -> 0.00062132446 | H70: =SQRT(AVERAGE(G10:G69))*NORMSINV(1-95%)*SQRT(1) -> -0.027244032 | I70: =(0.94*B69^2)+((1-0.94)*I69) -> 7.9330195e-07 | J70: =SQRT(I70)*NORMSINV(1-95%)*SQRT(1) -> -0.00146503 | K70: 0.0015594644 | L70: =K70 -> 0.0015594644 | M70: {=_xll.ROV.RiskSim.RSFunctions.RSForecastStatistic(L70,"Percentile0.05")*SQRT(1)} -> -0.0074467236 | N70: -0.0074467236
A71: =Portafolio!A71 -> 2024-04-11 | B71: =Portafolio!H71 -> 0.0096334751 | C71: =STDEV(B11:B70)*NORMSINV(1-95%)*SQRT(1) -> -0.012018273 | D71: =_xlfn.PERCENTILE.INC(B11:B70,1-95%)*SQRT(1) -> -0.011090698 | E71: =B71*B71 -> 9.2803843e-05 | F71: =SQRT(AVERAGE(E11:E70))*NORMSINV(1-95%)*SQRT(1) -> -0.012192608 | G71: {=MIN(B71-$B$3:B71,0)^2} -> 4.9512266e-05 | H71: =SQRT(AVERAGE(G11:G70))*NORMSINV(1-95%)*SQRT(1) -> -0.027555635 | I71: =(0.94*B70^2)+((1-0.94)*I70) -> 6.4125813e-05 | J71: =SQRT(I71)*NORMSINV(1-95%)*SQRT(1) -> -0.013171757 | K71: 0.0015594644 | L71: =K71 -> 0.0015594644 | M71: {=_xll.ROV.RiskSim.RSFunctions.RSForecastStatistic(L71,"Percentile0.05")*SQRT(1)} -> -0.0097390237 | N71: -0.0097390237
A72: =Portafolio!A72 -> 2024-04-12 | B72: =Portafolio!H72 -> -0.035428091 | C72: =STDEV(B12:B71)*NORMSINV(1-95%)*SQRT(1) -> -0.012108011 | D72: =_xlfn.PERCENTILE.INC(B12:B71,1-95%)*SQRT(1) -> -0.011090698 | E72: =B72*B72 -> 0.0012551496 | F72: =SQRT(AVERAGE(E12:E71))*NORMSINV(1-95%)*SQRT(1) -> -0.012352783 | G72: {=MIN(B72-$B$3:B72,0)^2} -> 0.002714208 | H72: =SQRT(AVERAGE(G12:G71))*NORMSINV(1-95%)*SQRT(1) -> -0.02729834 | I72: =(0.94*B71^2)+((1-0.94)*I71) -> 9.1083162e-05 | J72: =SQRT(I72)*NORMSINV(1-95%)*SQRT(1) -> -0.015698072 | K72: 0.0015594644 | L72: =K72 -> 0.0015594644 | M72: {=_xll.ROV.RiskSim.RSFunctions.RSForecastStatistic(L72,"Percentile0.05")*SQRT(1)} -> -0.0069585449 | N72: -0.0069585449
A73: =Portafolio!A73 -> 2024-04-15 | B73: =Portafolio!H73 -> -0.010810085 | C73: =STDEV(B13:B72)*NORMSINV(1-95%)*SQRT(1) -> -0.014414961 | D73: =_xlfn.PERCENTILE.INC(B13:B72,1-95%)*SQRT(1) -> -0.011840139 | E73: =B73*B73 -> 0.00011685793 | F73: =SQRT(AVERAGE(E13:E72))*NORMSINV(1-95%)*SQRT(1) -> -0.014439199 | G73: {=MIN(B73-$B$3:B73,0)^2} -> 0.00075515342 | H73: =SQRT(AVERAGE(G13:G72))*NORMSINV(1-95%)*SQRT(1) -> -0.029128054 | I73: =(0.94*B72^2)+((1-0.94)*I72) -> 0.0011853056 | J73: =SQRT(I73)*NORMSINV(1-95%)*SQRT(1) -> -0.056629461 | K73: 0.0015594644 | L73: =K73 -> 0.0015594644 | M73: {=_xll.ROV.RiskSim.RSFunctions.RSForecastStatistic(L73,"Percentile0.05")*SQRT(1)} -> -0.0074114453 | N73: -0.0074114453
A74: =Portafolio!A74 -> 2024-04-16 | B74: =Portafolio!H74 -> -0.0065683505 | C74: =STDEV(B14:B73)*NORMSINV(1-95%)*SQRT(1) -> -0.014525913 | D74: =_xlfn.PERCENTILE.INC(B14:B73,1-95%)*SQRT(1) -> -0.011840139 | E74: =B74*B74 -> 4.3143228e-05 | F74: =SQRT(AVERAGE(E14:E73))*NORMSINV(1-95%)*SQRT(1) -> -0.014480525 | G74: {=MIN(B74-$B$3:B74,0)^2} -> 0.00054001956 | H74: =SQRT(AVERAGE(G14:G73))*NORMSINV(1-95%)*SQRT(1) -> -0.029667838 | I74: =(0.94*B73^2)+((1-0.94)*I73) -> 0.00018096479 | J74: =SQRT(I74)*NORMSINV(1-95%)*SQRT(1) -> -0.02212709 | K74: 0.0015594644 | L74: =K74 -> 0.0015594644 | M74: {=_xll.ROV.RiskSim.RSFunctions.RSForecastStatistic(L74,"Percentile0.05")*SQRT(1)} -> -0.0081325317 | N74: -0.0081325317
A75: =Portafolio!A75 -> 2024-04-17 | B75: =Portafolio!H75 -> -0.0056149536 | C75: =STDEV(B15:B74)*NORMSINV(1-95%)*SQRT(1) -> -0.014296111 | D75: =_xlfn.PERCENTILE.INC(B15:B74,1-95%)*SQRT(1) -> -0.011840139 | E75: =B75*B75 -> 3.1527704e-05 | F75: =SQRT(AVERAGE(E15:E74))*NORMSINV(1-95%)*SQRT(1) -> -0.01420489 | G75: {=MIN(B75-$B$3:B75,0)^2} -> 0.00049661784 | H75: =SQRT(AVERAGE(G15:G74))*NORMSINV(1-95%)*SQRT(1) -> -0.030072754 | I75: =(0.94*B74^2)+((1-0.94)*I74) -> 5.1412521e-05 | J75: =SQRT(I75)*NORMSINV(1-95%)*SQRT(1) -> -0.011794016 | K75: 0.0015594644 | L75: =K75 -> 0.0015594644 | M75: {=_xll.ROV.RiskSim.RSFunctions.RSForecastStatistic(L75,"Percentile0.05")*SQRT(1)} -> -0.007634074 | N75: -0.007634074
... A125: =Portafolio!A125 -> 2024-06-28 | B125: =Portafolio!H125 -> -0.00053940675 | C125: =STDEV(B65:B124)*NORMSINV(1-95%)*SQRT(1) -> -0.014692934 | D125: =_xlfn.PERCENTILE.INC(B65:B124,1-95%)*SQRT(1) -> -0.011413046 | E125: =B125*B125 -> 2.9095964e-07 | F125: =SQRT(AVERAGE(E65:E124))*NORMSINV(1-95%)*SQRT(1) -> -0.014672724 | G125: {=MIN(B125-$B$3:B125,0)^2} -> 0.00029616266 | H125: =SQRT(AVERAGE(G65:G124))*NORMSINV(1-95%)*SQRT(1) -> -0.02953083 | I125: =(0.94*B124^2)+((1-0.94)*I124) -> 2.4835361e-05 | J125: =SQRT(I125)*NORMSINV(1-95%)*SQRT(1) -> -0.0081971427 | K125: 0.0015594644 | L125: =K125 -> 0.0015594644 | M125: {=_xll.ROV.RiskSim.RSFunctions.RSForecastStatistic(L125,"Percentile0.05")*SQRT(1)} -> -0.007886275 | N125: -0.007886275

Sheet Ajuste Distr. Portafolio
B1: Ajuste de Distribución para Variables Únicas
B3: Resumen Estadístico
E6: Supuesto Ajustado | F6: 0.0015594644
E8: Distribución Ajustada | F8: Beta Desplazada
E9: Ubicación | F9: -0.017822264
E10: Alfa | F10: 8.1185401
E11: Beta | F11: 404.10574
E13: Estadístico Kolmogorov-Smirnov | F13: 0.069245505
E14: Prueba Estadística para P-Value | F14: 0.9271026
E16: Real | F16: Teórica
D17: Media | E17: 0.0015594644 | F17: 0.0018722093
D18: Desviación Estándar | E18: 0.0067830095 | F18: 0.006835338
D19: Asimetría | E19: -0.18955563 | F19: 0.67855027
D20: Curtosis | E20: 0.37410558 | F20: 0.67453238
B23: Datos Originales Ajustados
B24: -0.017822264 | C24: -0.013232861 | D24: -0.011073055 | E24: -0.010369011 | F24: -0.006013803 | G24: -0.005399995 | H24: -0.004951868 | I24: -0.004606018 | J24: -0.004472271 | K24: -0.004339035 | L24: -0.004023083 | M24: -0.003821267 | N24: -0.003365361
B25: -0.002993132 | C25: -0.002968748 | D25: -0.002376433 | E25: -0.00206231 | F25: -0.002021035 | G25: -0.001283983 | H25: -0.001175411 | I25: -0.000996555 | J25: -0.0009794 | K25: -0.000468602 | L25: -0.00025146 | M25: -8.48741e-05 | N25: -6.19558e-05
B26: 0.000264973 | C26: 0.00062029 | D26: 0.000673714 | E26: 0.000776966 | F26: 0.000905458 | G26: 0.000974351 | H26: 0.001128156 | I26: 0.001237936 | J26: 0.001337631 | K26: 0.001688251 | L26: 0.002084723 | M26: 0.003505238 | N26: 0.003559991
B27: 0.004082707 | C27: 0.004615319 | D27: 0.006035998 | E27: 0.006055524 | F27: 0.006119834 | G27: 0.006452489 | H27: 0.006847567 | I27: 0.007241565 | J27: 0.007566321 | K27: 0.007661915 | L27: 0.007797898 | M27: 0.00789164 | N27: 0.007941225
B28: 0.008808724 | C28: 0.010507787 | D28: 0.011802311 | E28: 0.01220178 | F28: 0.012303929 | G28: 0.013733175 | H28: 0.015131971 | I28: 0.015224296

Sheet Backtesting
A1: =Portafolio!A1 -> fecha | B1: Retornos Portafolio | C1: VaR SD | D1: VaR N-P | E1: VaR Prm-M | F1: VaR S-SD | G1: VaR EWMA | H1: VaR MC | J1: Prueba de Semáforo de Basilea
J2: VaR SD | K2: VaR N-P | L2: VaR Prm-M | M2: VaR S-SD | N2: VaR EWMA | O2: VaR MC
A3: =Portafolio!A3 -> 2024-01-03 | B3: =Portafolio!H3 -> -0.003193079
A4: =Portafolio!A4 -> 2024-01-04 | B4: =Portafolio!H4 -> -0.0015849665 | Q4: Semáforo
A5: =Portafolio!A5 -> 2024-01-05 | B5: =Portafolio!H5 -> 0.0015763662 | Q5: Zona | R5: N° Excepciones | S5: Inc. Capital | W5: VaR SD | X5: VaR N-P | Y5: VaR Prm-M | Z5: VaR S-SD | AA5: VaR EWMA | AB5: VaR MC
A6: =Portafolio!A6 -> 2024-01-08 | B6: =Portafolio!H6 -> 0.010152267 | Q6: Verde | R6: 0 | S6: 0 | U6: Semáforo BIS | V6: Excepciones | W6: =SUM(J63:J125) -> 3 | X6: =SUM(K63:K125) -> 3 | Y6: =SUM(L63:L125) -> 3 | Z6: =SUM(M63:M125) -> 1 | AA6: =SUM(N63:N125) -> 9 | AB6: =SUM(O63:O125) -> 9
A7: =Portafolio!A7 -> 2024-01-09 | B7: =Portafolio!H7 -> -0.0026313546 | R7: 1 | S7: 0 | V7: Zona | W7: Verde | X7: Verde | Y7: Verde | Z7: Verde | AA7: Rojo | AB7: Amarillo
A8: =Portafolio!A8 -> 2024-01-10 | B8: =Portafolio!H8 -> 0.0094720816 | R8: 2 | S8: 0
A9: =Portafolio!A9 -> 2024-01-11 | B9: =Portafolio!H9 -> -0.00023880911 | R9: 3 | S9: 0 | U9: Test de Kupiec | V9: N° Obs. | W9: =COUNT(B3:B125) -> 123
A10: =Portafolio!A10 -> 2024-01-12 | B10: =Portafolio!H10 -> 0.0010930566 | R10: 4 | S10: 0 | V10: alpha | W10: 0.05
A11: =Portafolio!A11 -> 2024-01-16 | B11: =Portafolio!H11 -> -0.0023696334 | Q11: Amarillo | R11: 5 | S11: 0.4 | V11: Pgorro | W11: =W6/$W$9 -> 0.024390244 | X11: =X6/$W$9 -> 0.024390244 | Y11: =Y6/$W$9 -> 0.024390244 | Z11: =Z6/$W$9 -> 0.0081300813 | AA11: =AA6/$W$9 -> 0.073170732 | AB11: =AB6/$W$9 -> 0.073170732
A12: =Portafolio!A12 -> 2024-01-17 | B12: =Portafolio!H12 -> -0.0039357185 | R12: 6 | S12: 0.5 | V12: LR_numerador | W12: =(($W$10^W6)*(1-$W$10)^($W$9-W6)) -> 2.653033e-07 | X12: =(($W$10^X6)*(1-$W$10)^($W$9-X6)) -> 2.653033e-07 | Y12: =(($W$10^Y6)*(1-$W$10)^($W$9-Y6)) -> 2.653033e-07 | Z12: =(($W$10^Z6)*(1-$W$10)^($W$9-Z6)) -> 9.577449e-05 | AA12: =(($W$10^AA6)*(1-$W$10)^($W$9-AA6)) -> 5.639246e-15 | AB12: =(($W$10^AB6)*(1-$W$10)^($W$9-AB6)) -> 5.639246e-15
A13: =Portafolio!A13 -> 2024-01-18 | B13: =Portafolio!H13 -> 0.0095054398 | R13: 7 | S13: 0.65 | V13: LR_denominador | W13: =((1-W11)^($W$9-W6))*(W11^W6) -> 7.4952234e-07 | X13: =((1-X11)^($W$9-X6))*(X11^X6) -> 7.4952234e-07 | Y13: =((1-Y11)^($W$9-Y6))*(Y11^Y6) -> 7.4952234e-07 | Z13: =((1-Z11)^($W$9-Z6))*(Z11^Z6) -> 0.0030031058 | AA13: =((1-AA11)^($W$9-AA6))*(AA11^AA6) -> 1.0399368e-14 | AB13: =((1-AB11)^($W$9-AB6))*(AB11^AB6) -> 1.0399368e-14
A14: =Portafolio!A14 -> 2024-01-19 | B14: =Portafolio!H14 -> 0.014781335 | R14: 8 | S14: 0.75 | V14: LR | W14: =IFERROR(-2*LN(W12/W13),"") -> 2.0771249 | X14: =IFERROR(-2*LN(X12/X13),"") -> 2.0771249 | Y14: =IFERROR(-2*LN(Y12/Y13),"") -> 2.0771249 | Z14: =IFERROR(-2*LN(Z12/Z13),"") -> 6.8908119 | AA14: =IFERROR(-2*LN(AA12/AA13),"") -> 1.2239892 | AB14: =IFERROR(-2*LN(AB12/AB13),"") -> 1.2239892
A15: =Portafolio!A15 -> 2024-01-22 | B15: =Portafolio!H15 -> -0.0014064286 | R15: 9 | S15: 0.85 | V15: Chi2 | W15: =IFERROR(_xlfn.CHISQ.DIST.RT(W14,2),"") -> 0.35396316 | X15: =IFERROR(_xlfn.CHISQ.DIST.RT(X14,2),"") -> 0.35396316 | Y15: =IFERROR(_xlfn.CHISQ.DIST.RT(Y14,2),"") -> 0.35396316 | Z15: =IFERROR(_xlfn.CHISQ.DIST.RT(Z14,2),"") -> 0.031891813 | AA15: =IFERROR(_xlfn.CHISQ.DIST.RT(AA14,2),"") -> 0.54226817 | AB15: =IFERROR(_xlfn.CHISQ.DIST.RT(AB14,2),"") -> 0.54226817
A16: =Portafolio!A16 -> 2024-01-23 | B16: =Portafolio!H16 -> 0.0003466655 | Q16: Rojo | R16: 10 | S16: 1
A17: =Portafolio!A17 -> 2024-01-24 | B17: =Portafolio!H17 -> 0.0075196083
A18: =Portafolio!A18 -> 2024-01-25 | B18: =Portafolio!H18 -> 0.0086967208
A19: =Portafolio!A19 -> 2024-01-26 | B19: =Portafolio!H19 -> -0.0038088477 | V19: Peor Escenarios | W19: =MIN(B63:B125) -> -0.035428091 | X19: =MIN(C63:C125) -> -0.015518565 | Y19: =MIN(D63:D125) -> -0.011861478 | Z19: =MIN(E63:E125) -> -0.015475673 | AA19: =MIN(F63:F125) -> -0.030770335 | AB19: =MIN(G63:G125) -> -0.056629461
A20: =Portafolio!A20 -> 2024-01-29 | B20: =Portafolio!H20 -> 0.006820183
A21: =Portafolio!A21 -> 2024-01-30 | B21: =Portafolio!H21 -> 0.0057317365
A22: =Portafolio!A22 -> 2024-01-31 | B22: =Portafolio!H22 -> -0.018921543
A23: =Portafolio!A23 -> 2024-02-01 | B23: =Portafolio!H23 -> 0.0065257348
A24: =Portafolio!A24 -> 2024-02-02 | B24: =Portafolio!H24 -> 0.0097408489
A25: =Portafolio!A25 -> 2024-02-05 | B25: =Portafolio!H25 -> -0.0052392854
A26: =Portafolio!A26 -> 2024-02-06 | B26: =Portafolio!H26 -> 0.0024180714
A27: =Portafolio!A27 -> 2024-02-07 | B27: =Portafolio!H27 -> 0.009824009
A28: =Portafolio!A28 -> 2024-02-08 | B28: =Portafolio!H28 -> -0.0022627399
A29: =Portafolio!A29 -> 2024-02-09 | B29: =Portafolio!H29 -> 0.0076065409
A30: =Portafolio!A30 -> 2024-02-12 | B30: =Portafolio!H30 -> -0.0044481705
A31: =Portafolio!A31 -> 2024-02-13 | B31: =Portafolio!H31 -> -0.014598268
... A62: =Portafolio!A62 -> 2024-03-28 | B62: =Portafolio!H62 -> -0.00020992588
A63: =Portafolio!A63 -> 2024-04-01 | B63: =Portafolio!H63 -> -0.00023101207 | C63: ='VaR Dinámico'!C63 -> -0.01172252 | D63: ='VaR Dinámico'!D63 -> -0.011090698 | E63: ='VaR Dinámico'!F63 -> -0.012059183 | F63: ='VaR Dinámico'!H63 -> -0.026856852 | G63: ='VaR Dinámico'!J63 -> -0.00034529735 | H63: ='VaR Dinámico'!N63 -> -0.0090437179 | J63: =IF($B63<C63,1,0) -> 0 | K63: =IF($B63<D63,1,0) -> 0 | L63: =IF($B63<E63,1,0) -> 0 | M63: =IF($B63<F63,1,0) -> 0 | N63: =IF($B63<G63,1,0) -> 0 | O63: =IF($B63<H63,1,0) -> 0
A64: =Portafolio!A64 -> 2024-04-02 | B64: =Portafolio!H64 -> -0.004172482 | C64: ='VaR Dinámico'!C64 -> -0.011679713 | D64: ='VaR Dinámico'!D64 -> -0.011090698 | E64: ='VaR Dinámico'!F64 -> -0.012040206 | F64: ='VaR Dinámico'!H64 -> -0.026765277 | G64: ='VaR Dinámico'!J64 -> -0.00037798978 | H64: ='VaR Dinámico'!N64 -> -0.0078188379 | J64: =IF($B64<C64,1,0) -> 0 | K64: =IF($B64<D64,1,0) -> 0 | L64: =IF($B64<E64,1,0) -> 0 | M64: =IF($B64<F64,1,0) -> 0 | N64: =IF($B64<G64,1,0) -> 1 | O64: =IF($B64<H64,1,0) -> 0
A65: =Portafolio!A65 -> 2024-04-03 | B65: =Portafolio!H65 -> -0.0017133963 | C65: ='VaR Dinámico'!C65 -> -0.011728955 | D65: ='VaR Dinámico'!D65 -> -0.011090698 | E65: ='VaR Dinámico'!F65 -> -0.01206807 | F65: ='VaR Dinámico'!H65 -> -0.02685036 | G65: ='VaR Dinámico'!J65 -> -0.0066546879 | H65: ='VaR Dinámico'!N65 -> -0.0072016294 | J65: =IF($B65<C65,1,0) -> 0 | K65: =IF($B65<D65,1,0) -> 0 | L65: =IF($B65<E65,1,0) -> 0 | M65: =IF($B65<F65,1,0) -> 0 | N65: =IF($B65<G65,1,0) -> 0 | O65: =IF($B65<H65,1,0) -> 0
A66: =Portafolio!A66 -> 2024-04-04 | B66: =Portafolio!H66 -> -0.0066699185 | C66: ='VaR Dinámico'!C66 -> -0.011754628 | D66: ='VaR Dinámico'!D66 -> -0.011090698 | E66: ='VaR Dinámico'!F66 -> -0.012068912 | F66: ='VaR Dinámico'!H66 -> -0.026942678 | G66: ='VaR Dinámico'!J66 -> -0.0031817078 | H66: ='VaR Dinámico'!N66 -> -0.0065690298 | J66: =IF($B66<C66,1,0) -> 0 | K66: =IF($B66<D66,1,0) -> 0 | L66: =IF($B66<E66,1,0) -> 0 | M66: =IF($B66<F66,1,0) -> 0 | N66: =IF($B66<G66,1,0) -> 1 | O66: =IF($B66<H66,1,0) -> 1
A67: =Portafolio!A67 -> 2024-04-05 | B67: =Portafolio!H67 -> 0.012417793 | C67: ='VaR Dinámico'!C67 -> -0.011755999 | D67: ='VaR Dinámico'!D67 -> -0.011090698 | E67: ='VaR Dinámico'!F67 -> -0.011958976 | F67: ='VaR Dinámico'!H67 -> -0.02735976 | G67: ='VaR Dinámico'!J67 -> -0.010665331 | H67: ='VaR Dinámico'!N67 -> -0.0068587684 | J67: =IF($B67<C67,1,0) -> 0 | K67: =IF($B67<D67,1,0) -> 0 | L67: =IF($B67<E67,1,0) -> 0 | M67: =IF($B67<F67,1,0) -> 0 | N67: =IF($B67<G67,1,0) -> 0 | O67: =IF($B67<H67,1,0) -> 0
A68: =Portafolio!A68 -> 2024-04-08 | B68: =Portafolio!H68 -> 0.00063673863 | C68: ='VaR Dinámico'!C68 -> -0.011939244 | D68: ='VaR Dinámico'!D68 -> -0.011090698 | E68: ='VaR Dinámico'!F68 -> -0.012233487 | F68: ='VaR Dinámico'!H68 -> -0.027066086 | G68: ='VaR Dinámico'!J68 -> -0.019974786 | H68: ='VaR Dinámico'!N68 -> -0.0073622789 | J68: =IF($B68<C68,1,0) -> 0 | K68: =IF($B68<D68,1,0) -> 0 | L68: =IF($B68<E68,1,0) -> 0 | M68: =IF($B68<F68,1,0) -> 0 | N68: =IF($B68<G68,1,0) -> 0 | O68: =IF($B68<H68,1,0) -> 0
A69: =Portafolio!A69 -> 2024-04-09 | B69: =Portafolio!H69 -> -0.00050480241 | C69: ='VaR Dinámico'!C69 -> -0.011828258 | D69: ='VaR Dinámico'!D69 -> -0.011090698 | E69: ='VaR Dinámico'!F69 -> -0.012067758 | F69: ='VaR Dinámico'!H69 -> -0.027236528 | G69: ='VaR Dinámico'!J69 -> -0.0049970625 | H69: ='VaR Dinámico'!N69 -> -0.0085213346 | J69: =IF($B69<C69,1,0) -> 0 | K69: =IF($B69<D69,1,0) -> 0 | L69: =IF($B69<E69,1,0) -> 0 | M69: =IF($B69<F69,1,0) -> 0 | N69: =IF($B69<G69,1,0) -> 0 | O69: =IF($B69<H69,1,0) -> 0
A70: =Portafolio!A70 -> 2024-04-10 | B70: =Portafolio!H70 -> -0.0082564104 | C70: ='VaR Dinámico'!C70 -> -0.011830418 | D70: ='VaR Dinámico'!D70 -> -0.011090698 | E70: ='VaR Dinámico'!F70 -> -0.012068127 | F70: ='VaR Dinámico'!H70 -> -0.027244032 | G70: ='VaR Dinámico'!J70 -> -0.00146503 | H70: ='VaR Dinámico'!N70 -> -0.0074467236 | J70: =IF($B70<C70,1,0) -> 0 | K70: =IF($B70<D70,1,0) -> 0 | L70: =IF($B70<E70,1,0) -> 0 | M70: =IF($B70<F70,1,0) -> 0 | N70: =IF($B70<G70,1,0) -> 1 | O70: =IF($B70<H70,1,0) -> 1
A71: =Portafolio!A71 -> 2024-04-11 | B71: =Portafolio!H71 -> 0.0096334751 | C71: ='VaR Dinámico'!C71 -> -0.012018273 | D71: ='VaR Dinámico'!D71 -> -0.011090698 | E71: ='VaR Dinámico'!F71 -> -0.012192608 | F71: ='VaR Dinámico'!H71 -> -0.027555635 | G71: ='VaR Dinámico'!J71 -> -0.013171757 | H71: ='VaR Dinámico'!N71 -> -0.0097390237 | J71: =IF($B71<C71,1,0) -> 0 | K71: =IF($B71<D71,1,0) -> 0 | L71: =IF($B71<E71,1,0) -> 0 | M71: =IF($B71<F71,1,0) -> 0 | N71: =IF($B71<G71,1,0) -> 0 | O71: =IF($B71<H71,1,0) -> 0
A72: =Portafolio!A72 -> 2024-04-12 | B72: =Portafolio!H72 -> -0.035428091 | C72: ='VaR Dinámico'!C72 -> -0.012108011 | D72: ='VaR Dinámico'!D72 -> -0.011090698 | E72: ='VaR Dinámico'!F72 -> -0.012352783 | F72: ='VaR Dinámico'!H72 -> -0.02729834 | G72: ='VaR Dinámico'!J72 -> -0.015698072 | H72: ='VaR Dinámico'!N72 -> -0.0069585449 | J72: =IF($B72<C72,1,0) -> 1 | K72: =IF($B72<D72,1,0) -> 1 | L72: =IF($B72<E72,1,0) -> 1 | M72: =IF($B72<F72,1,0) -> 1 | N72: =IF($B72<G72,1,0) -> 1 | O72: =IF($B72<H72,1,0) -> 1
A73: =Portafolio!A73 -> 2024-04-15 | B73: =Portafolio!H73 -> -0.010810085 | C73: ='VaR Dinámico'!C73 -> -0.014414961 | D73: ='VaR Dinámico'!D73 -> -0.011840139 | E73: ='VaR Dinámico'!F73 -> -0.014439199 | F73: ='VaR Dinámico'!H73 -> -0.029128054 | G73: ='VaR Dinámico'!J73 -> -0.056629461 | H73: ='VaR Dinámico'!N73 -> -0.0074114453 | J73: =IF($B73<C73,1,0) -> 0 | K73: =IF($B73<D73,1,0) -> 0 | L73: =IF($B73<E73,1,0) -> 0 | M73: =IF($B73<F73,1,0) -> 0 | N73: =IF($B73<G73,1,0) -> 0 | O73: =IF($B73<H73,1,0) -> 1
A74: =Portafolio!A74 -> 2024-04-16 | B74: =Portafolio!H74 -> -0.0065683505 | C74: ='VaR Dinámico'!C74 -> -0.014525913 | D74: ='VaR Dinámico'!D74 -> -0.011840139 | E74: ='VaR Dinámico'!F74 -> -0.014480525 | F74: ='VaR Dinámico'!H74 -> -0.029667838 | G74: ='VaR Dinámico'!J74 -> -0.02212709 | H74: ='VaR Dinámico'!N74 -> -0.0081325317 | J74: =IF($B74<C74,1,0) -> 0 | K74: =IF($B74<D74,1,0) -> 0 | L74: =IF($B74<E74,1,0) -> 0 | M74: =IF($B74<F74,1,0) -> 0 | N74: =IF($B74<G74,1,0) -> 0 | O74: =IF($B74<H74,1,0) -> 0
... A125: =Portafolio!A125 -> 2024-06-28 | B125: =Portafolio!H125 -> -0.00053940675 | C125: ='VaR Dinámico'!C125 -> -0.014692934 | D125: ='VaR Dinámico'!D125 -> -0.011413046 | E125: ='VaR Dinámico'!F125 -> -0.014672724 | F125: ='VaR Dinámico'!H125 -> -0.02953083 | G125: ='VaR Dinámico'!J125 -> -0.0081971427 | H125: ='VaR Dinámico'!N125 -> -0.007886275 | J125: =IF($B125<C125,1,0) -> 0 | K125: =IF($B125<D125,1,0) -> 0 | L125: =IF($B125<E125,1,0) -> 0 | M125: =IF($B125<F125,1,0) -> 0 | N125: =IF($B125<G125,1,0) -> 0 | O125: =IF($B125<H125,1,0) -> 0
